Workbook

Sheet DASHBOARD
A1: FINANZAS — DASHBOARD
G2: Last Sync | H2: 46079.219
A3: Inputs | D3: Metrics | G3: NAC File | H3: MovimientosNoFacturadosNacionales_26-02-2026.xls | date=20260226
A4: Salario (CLP) | B4: =CONFIG!B2 -> 3000000 | D4: Compras CC Nacional | E4: =RESUMEN!B2 -> 420514 | G4: INTL File | H4: MovimientosNoFacturadosInternacionales_26-02-2026.xls | date=20260226
A5: Housing (CLP) | B5: =CONFIG!B3 -> 1000000 | D5: Compras CC Intl (CLP) | E5: =RESUMEN!B3 -> 114218.5 | G5: Status | H5: SYNC OK | NAC:IMPORTED INTL:IMPORTED
A6: Familia (CLP) | B6: =CONFIG!B4 -> 300000 | D6: Pagos CC Nacional | E6: =RESUMEN!B4 -> 0 | G6: NAC Hash | H6: 1sVcdDjViWqprvwBy9u94CKQg166DXw5c|27601ba7fecf626a2eff5b0f4b2f57c1
A7: USD→CLP | B7: =CONFIG!B5 -> 950 | D7: Pagos CC Intl (CLP) | E7: =RESUMEN!B5 -> 0 | G7: INTL Hash | H7: 1Yuqq62vCosR0f9SFrcVpxI1fyVKM9D4i|7b5be5a3c8a826fd1bea52fa86e44635
A8: Claude plan (CLP) | B8: =CONFIG!B6 -> 0 | D8: Costos fijos | E8: =PROYECCION!B3 -> 1300000
D9: Margen disponible | E9: =PROYECCION!B7 -> 1165267.5
D10: FSI (margen/ingreso) | E10: =IFERROR(PROYECCION!B7/PROYECCION!B2,0) -> 0.3884225
A11: Stability Status
A12: Status | B12: =IF(E10<0.15,"🔴 RED",IF(E10<0.2,"🟡 YELLOW","🟢 GREEN")) -> 🟢 GREEN
A14: Auto-Savings Recommendation
A15: Recommended savings (CLP) | B15: =MAX(0,MIN(500000,PROYECCION!B7-300000)) -> 500000
A16: Buffer left after savings | B16: =PROYECCION!B7-B15 -> 665267.5
A18: Claude Upgrade Indicator
A19: Max 5x safe? | B19: =IF(PROYECCION!B7-100000>=300000,"YES","NO") -> YES
A20: Max 20x safe? | B20: =IF(PROYECCION!B7-200000>=300000,"YES","NO") -> YES
A22: Psychological Burn Threshold
A23: Threshold (CLP) | B23: =MAX(600000,PROYECCION!B2*0.25) -> 750000
A24: Day you cross threshold | B24: =IFERROR(ROUNDUP(B23/(PROYECCION!B7/30),0),"") -> 20
A26: Actions
A27: Rule | B27: Pay housing + family first. Auto-save B15 on day 1. Then spend normally.

Sheet PREVIEW_SUMMARY
A1: PREVIEW IMPORT SUMMARY
A2: Generated at | B2: 46079.219
A4: NAC file | B4: MovimientosNoFacturadosNacionales_26-02-2026.xls
A5: NAC parsed date | B5: 20260226
A6: NAC checksum (MD5) | B6: 1sVcdDjViWqprvwBy9u94CKQg166DXw5c|27601ba7fecf626a2eff5b0f4b2f57c1
A7: NAC rows (ex header) | B7: 20
A8: NAC total (preview) | B8: 420514
A9: NAC total (current live) | B9: -269753
A10: NAC delta (preview - live) | B10: 690267
A12: INTL file | B12: MovimientosNoFacturadosInternacionales_26-02-2026.xls
A13: INTL parsed date | B13: 20260226
A14: INTL checksum (MD5) | B14: 1Yuqq62vCosR0f9SFrcVpxI1fyVKM9D4i|7b5be5a3c8a826fd1bea52fa86e44635
A15: INTL rows (ex header) | B15: 3
A16: INTL total (preview) | B16: 120.23
A17: INTL total (current live) | B17: -36.69
A18: INTL delta (preview - live) | B18: 156.92
A20: Next step | B20: Use Finanzas menu or buttons: Preview / Confirm / Cancel.

Sheet PREVIEW_NAC
A1: Fecha | B1: Descripcion | C1: Monto_CLP
A2: 25-02-2026 | B2: UBER RIDES UBER RIDES LAS CO | C2: 12931
A3: 25-02-2026 | B3: CHILE DOGS LTDA CON CO | C3: 46990
A4: 24-02-2026 | B4: PAYU *FLIXBUS SANTIA | C4: 6499
A5: 24-02-2026 | B5: PAYU *UBER TRIP SANTIA | C5: 12600
A6: 24-02-2026 | B6: PAYU *FLIXBUS SANTIA | C6: 4999
A7: 24-02-2026 | B7: PAYU *UBER TRIP SANTIA | C7: 6078
A8: 23-02-2026 | B8: MERCADOPAGO*MERCADO COMPRAS | C8: 11980
A9: 23-02-2026 | B9: PAYU *FLIXBUS COMPRAS | C9: 7699
A10: 21-02-2026 | B10: LOCAL EU 15 NORTE COMPRAS | C10: 19990
A11: 21-02-2026 | B11: MORA LOUTIT SWEET S COMPRAS | C11: 11550
A12: 23-02-2026 | B12: MERCADOPAGO*MERCADO 03 CTAS-INT: 0 | C12: 86791
A13: 21-02-2026 | B13: MERPAGO*OPTICASLUXO HUE CC 01-06 | C13: 41030
... A16: 21-01-2026 | B16: MP *MERCADO LIB SAN CC 02-03 | C16: 15295
A17: 46235 | B17: MP *MERCADO LIB SAN CC 03-06 | C17: 20813
A18: 46204 | B18: MERCADOPAGO*STREETD LAS CF 02-06 | C18: 10997
A19: 21-12-2025 | B19: MERPAGO*MERCADOLIBR LAS CC 03-03 | C19: 17538
A20: 28-11-2025 | B20: CIC HOGAR TIENDA CO CON CC 04-06 | C20: 20496
A21: 28-08-2025 | B21: MERCADOPAGO*MONSTER LAS CF 06-06 | C21: 14667

Sheet PREVIEW_INTL
A1: Fecha | B1: Descripcion | C1: Monto_USD
A2: 22-02-2026 | B2: EMBY PREMIERE COMPRAS INT.VI | C2: 4.99
A3: 20-02-2026 | B3: CLAUDE.AI SUBSCRIPT COMPRAS INT.VI | C3: 102.76
A4: 19-02-2026 | B4: APPLE.COM/BILL COMPRAS INT.VI | C4: 12.48

Sheet CONFIG
A1: Parametro | B1: Valor | D1: NOTE
A2: SALARIO | B2: 3000000 | D2: In Google Sheets, set HOUSING to IMPORTRANGE from your other sheet (Gordo!O1) using the sanitize formula.
A3: HOUSING | B3: 1000000
A4: FAMILIA | B4: 300000
A5: USD_CLP | B5: 950
A6: CLAUDE_PLAN | B6: 0

Sheet CUOTAS
A1: Fuente | B1: Fecha | C1: Descripcion | D1: Monto | E1: Moneda | F1: Es_cuotas | G1: Cuota_actual | H1: Cuotas_totales | I1: Cuotas_restantes | J1: Monto_restante_estimado | L1: RESUMEN
A2: NAC | B2: =IF(MOV_CC_NACIONAL!A2="","",MOV_CC_NACIONAL!A2) -> 25-02-2026 | C2: =IF(MOV_CC_NACIONAL!B2="","",MOV_CC_NACIONAL!B2) -> UBER RIDES UBER RIDES LAS CO | D2: =IF(MOV_CC_NACIONAL!C2="","",MOV_CC_NACIONAL!C2) -> 12931 | E2: =IF(B2="","", "CLP") -> CLP | F2: =IFERROR(__xludf.DUMMYFUNCTION("IF(C2="""","""", OR(REGEXMATCH(LOWER(C2),""cuota""), REGEXMATCH(C2,""\d+\s*/\s*\d+"")))"),FALSE) -> FALSE | G2: =IFERROR(__xludf.DUMMYFUNCTION("IFERROR(VALUE(REGEXEXTRACT(C2,""(\d+)\s*/\s*\d+"")),"""")"),"") | H2: =IFERROR(__xludf.DUMMYFUNCTION("IFERROR(VALUE(REGEXEXTRACT(C2,""\d+\s*/\s*(\d+)"")),"""")"),"") | I2: =IF(OR(G2="",H2=""),"",H2-G2) | J2: =IF(OR(D2="",I2=""),"",D2*I2) | L2: Total restante (est.) | M2: =SUMIF(F:F,TRUE,J:J) -> 0
A3: NAC | B3: =IF(MOV_CC_NACIONAL!A3="","",MOV_CC_NACIONAL!A3) -> 25-02-2026 | C3: =IF(MOV_CC_NACIONAL!B3="","",MOV_CC_NACIONAL!B3) -> CHILE DOGS LTDA CON CO | D3: =IF(MOV_CC_NACIONAL!C3="","",MOV_CC_NACIONAL!C3) -> 46990 | E3: =IF(B3="","", "CLP") -> CLP | F3: =IFERROR(__xludf.DUMMYFUNCTION("IF(C3="""","""", OR(REGEXMATCH(LOWER(C3),""cuota""), REGEXMATCH(C3,""\d+\s*/\s*\d+"")))"),FALSE) -> FALSE | G3: =IFERROR(__xludf.DUMMYFUNCTION("IFERROR(VALUE(REGEXEXTRACT(C3,""(\d+)\s*/\s*\d+"")),"""")"),"") | H3: =IFERROR(__xludf.DUMMYFUNCTION("IFERROR(VALUE(REGEXEXTRACT(C3,""\d+\s*/\s*(\d+)"")),"""")"),"") | I3: =IF(OR(G3="",H3=""),"",H3-G3) | J3: =IF(OR(D3="",I3=""),"",D3*I3) | L3: Cuotas activas (count) | M3: =COUNTIF(F:F,TRUE) -> 0
A4: NAC | B4: =IF(MOV_CC_NACIONAL!A4="","",MOV_CC_NACIONAL!A4) -> 24-02-2026 | C4: =IF(MOV_CC_NACIONAL!B4="","",MOV_CC_NACIONAL!B4) -> PAYU *FLIXBUS SANTIA | D4: =IF(MOV_CC_NACIONAL!C4="","",MOV_CC_NACIONAL!C4) -> 6499 | E4: =IF(B4="","", "CLP") -> CLP | F4: =IFERROR(__xludf.DUMMYFUNCTION("IF(C4="""","""", OR(REGEXMATCH(LOWER(C4),""cuota""), REGEXMATCH(C4,""\d+\s*/\s*\d+"")))"),FALSE) -> FALSE | G4: =IFERROR(__xludf.DUMMYFUNCTION("IFERROR(VALUE(REGEXEXTRACT(C4,""(\d+)\s*/\s*\d+"")),"""")"),"") | H4: =IFERROR(__xludf.DUMMYFUNCTION("IFERROR(VALUE(REGEXEXTRACT(C4,""\d+\s*/\s*(\d+)"")),"""")"),"") | I4: =IF(OR(G4="",H4=""),"",H4-G4) | J4: =IF(OR(D4="",I4=""),"",D4*I4)
A5: NAC | B5: =IF(MOV_CC_NACIONAL!A5="","",MOV_CC_NACIONAL!A5) -> 24-02-2026 | C5: =IF(MOV_CC_NACIONAL!B5="","",MOV_CC_NACIONAL!B5) -> PAYU *UBER TRIP SANTIA | D5: =IF(MOV_CC_NACIONAL!C5="","",MOV_CC_NACIONAL!C5) -> 12600 | E5: =IF(B5="","", "CLP") -> CLP | F5: =IFERROR(__xludf.DUMMYFUNCTION("IF(C5="""","""", OR(REGEXMATCH(LOWER(C5),""cuota""), REGEXMATCH(C5,""\d+\s*/\s*\d+"")))"),FALSE) -> FALSE | G5: =IFERROR(__xludf.DUMMYFUNCTION("IFERROR(VALUE(REGEXEXTRACT(C5,""(\d+)\s*/\s*\d+"")),"""")"),"") | H5: =IFERROR(__xludf.DUMMYFUNCTION("IFERROR(VALUE(REGEXEXTRACT(C5,""\d+\s*/\s*(\d+)"")),"""")"),"") | I5: =IF(OR(G5="",H5=""),"",H5-G5) | J5: =IF(OR(D5="",I5=""),"",D5*I5) | L5: Nota: | M5: Estas fórmulas usan REGEX* (funciones de Google Sheets). Al abrir en Google Sheets funcionará.
A6: NAC | B6: =IF(MOV_CC_NACIONAL!A6="","",MOV_CC_NACIONAL!A6) -> 24-02-2026 | C6: =IF(MOV_CC_NACIONAL!B6="","",MOV_CC_NACIONAL!B6) -> PAYU *FLIXBUS SANTIA | D6: =IF(MOV_CC_NACIONAL!C6="","",MOV_CC_NACIONAL!C6) -> 4999 | E6: =IF(B6="","", "CLP") -> CLP | F6: =IFERROR(__xludf.DUMMYFUNCTION("IF(C6="""","""", OR(REGEXMATCH(LOWER(C6),""cuota""), REGEXMATCH(C6,""\d+\s*/\s*\d+"")))"),FALSE) -> FALSE | G6: =IFERROR(__xludf.DUMMYFUNCTION("IFERROR(VALUE(REGEXEXTRACT(C6,""(\d+)\s*/\s*\d+"")),"""")"),"") | H6: =IFERROR(__xludf.DUMMYFUNCTION("IFERROR(VALUE(REGEXEXTRACT(C6,""\d+\s*/\s*(\d+)"")),"""")"),"") | I6: =IF(OR(G6="",H6=""),"",H6-G6) | J6: =IF(OR(D6="",I6=""),"",D6*I6)
A7: NAC | B7: =IF(MOV_CC_NACIONAL!A7="","",MOV_CC_NACIONAL!A7) -> 24-02-2026 | C7: =IF(MOV_CC_NACIONAL!B7="","",MOV_CC_NACIONAL!B7) -> PAYU *UBER TRIP SANTIA | D7: =IF(MOV_CC_NACIONAL!C7="","",MOV_CC_NACIONAL!C7) -> 6078 | E7: =IF(B7="","", "CLP") -> CLP | F7: =IFERROR(__xludf.DUMMYFUNCTION("IF(C7="""","""", OR(REGEXMATCH(LOWER(C7),""cuota""), REGEXMATCH(C7,""\d+\s*/\s*\d+"")))"),FALSE) -> FALSE | G7: =IFERROR(__xludf.DUMMYFUNCTION("IFERROR(VALUE(REGEXEXTRACT(C7,""(\d+)\s*/\s*\d+"")),"""")"),"") | H7: =IFERROR(__xludf.DUMMYFUNCTION("IFERROR(VALUE(REGEXEXTRACT(C7,""\d+\s*/\s*(\d+)"")),"""")"),"") | I7: =IF(OR(G7="",H7=""),"",H7-G7) | J7: =IF(OR(D7="",I7=""),"",D7*I7) | L7: Vista (solo cuotas)
A8: NAC | B8: =IF(MOV_CC_NACIONAL!A8="","",MOV_CC_NACIONAL!A8) -> 23-02-2026 | C8: =IF(MOV_CC_NACIONAL!B8="","",MOV_CC_NACIONAL!B8) -> MERCADOPAGO*MERCADO COMPRAS | D8: =IF(MOV_CC_NACIONAL!C8="","",MOV_CC_NACIONAL!C8) -> 11980 | E8: =IF(B8="","", "CLP") -> CLP | F8: =IFERROR(__xludf.DUMMYFUNCTION("IF(C8="""","""", OR(REGEXMATCH(LOWER(C8),""cuota""), REGEXMATCH(C8,""\d+\s*/\s*\d+"")))"),FALSE) -> FALSE | G8: =IFERROR(__xludf.DUMMYFUNCTION("IFERROR(VALUE(REGEXEXTRACT(C8,""(\d+)\s*/\s*\d+"")),"""")"),"") | H8: =IFERROR(__xludf.DUMMYFUNCTION("IFERROR(VALUE(REGEXEXTRACT(C8,""\d+\s*/\s*(\d+)"")),"""")"),"") | I8: =IF(OR(G8="",H8=""),"",H8-G8) | J8: =IF(OR(D8="",I8=""),"",D8*I8) | L8: =IFERROR(__xludf.DUMMYFUNCTION("QUERY(A1:J,""select A,B,C,D,E,G,H,I,J where F = TRUE"",1)"),"#NAME?") -> #NAME?
A9: NAC | B9: =IF(MOV_CC_NACIONAL!A9="","",MOV_CC_NACIONAL!A9) -> 23-02-2026 | C9: =IF(MOV_CC_NACIONAL!B9="","",MOV_CC_NACIONAL!B9) -> PAYU *FLIXBUS COMPRAS | D9: =IF(MOV_CC_NACIONAL!C9="","",MOV_CC_NACIONAL!C9) -> 7699 | E9: =IF(B9="","", "CLP") -> CLP | F9: =IFERROR(__xludf.DUMMYFUNCTION("IF(C9="""","""", OR(REGEXMATCH(LOWER(C9),""cuota""), REGEXMATCH(C9,""\d+\s*/\s*\d+"")))"),FALSE) -> FALSE | G9: =IFERROR(__xludf.DUMMYFUNCTION("IFERROR(VALUE(REGEXEXTRACT(C9,""(\d+)\s*/\s*\d+"")),"""")"),"") | H9: =IFERROR(__xludf.DUMMYFUNCTION("IFERROR(VALUE(REGEXEXTRACT(C9,""\d+\s*/\s*(\d+)"")),"""")"),"") | I9: =IF(OR(G9="",H9=""),"",H9-G9) | J9: =IF(OR(D9="",I9=""),"",D9*I9)
A10: NAC | B10: =IF(MOV_CC_NACIONAL!A10="","",MOV_CC_NACIONAL!A10) -> 21-02-2026 | C10: =IF(MOV_CC_NACIONAL!B10="","",MOV_CC_NACIONAL!B10) -> LOCAL EU 15 NORTE COMPRAS | D10: =IF(MOV_CC_NACIONAL!C10="","",MOV_CC_NACIONAL!C10) -> 19990 | E10: =IF(B10="","", "CLP") -> CLP | F10: =IFERROR(__xludf.DUMMYFUNCTION("IF(C10="""","""", OR(REGEXMATCH(LOWER(C10),""cuota""), REGEXMATCH(C10,""\d+\s*/\s*\d+"")))"),FALSE) -> FALSE | G10: =IFERROR(__xludf.DUMMYFUNCTION("IFERROR(VALUE(REGEXEXTRACT(C10,""(\d+)\s*/\s*\d+"")),"""")"),"") | H10: =IFERROR(__xludf.DUMMYFUNCTION("IFERROR(VALUE(REGEXEXTRACT(C10,""\d+\s*/\s*(\d+)"")),"""")"),"") | I10: =IF(OR(G10="",H10=""),"",H10-G10) | J10: =IF(OR(D10="",I10=""),"",D10*I10)
A11: NAC | B11: =IF(MOV_CC_NACIONAL!A11="","",MOV_CC_NACIONAL!A11) -> 21-02-2026 | C11: =IF(MOV_CC_NACIONAL!B11="","",MOV_CC_NACIONAL!B11) -> MORA LOUTIT SWEET S COMPRAS | D11: =IF(MOV_CC_NACIONAL!C11="","",MOV_CC_NACIONAL!C11) -> 11550 | E11: =IF(B11="","", "CLP") -> CLP | F11: =IFERROR(__xludf.DUMMYFUNCTION("IF(C11="""","""", OR(REGEXMATCH(LOWER(C11),""cuota""), REGEXMATCH(C11,""\d+\s*/\s*\d+"")))"),FALSE) -> FALSE | G11: =IFERROR(__xludf.DUMMYFUNCTION("IFERROR(VALUE(REGEXEXTRACT(C11,""(\d+)\s*/\s*\d+"")),"""")"),"") | H11: =IFERROR(__xludf.DUMMYFUNCTION("IFERROR(VALUE(REGEXEXTRACT(C11,""\d+\s*/\s*(\d+)"")),"""")"),"") | I11: =IF(OR(G11="",H11=""),"",H11-G11) | J11: =IF(OR(D11="",I11=""),"",D11*I11)
A12: NAC | B12: =IF(MOV_CC_NACIONAL!A12="","",MOV_CC_NACIONAL!A12) -> 23-02-2026 | C12: =IF(MOV_CC_NACIONAL!B12="","",MOV_CC_NACIONAL!B12) -> MERCADOPAGO*MERCADO 03 CTAS-INT: 0 | D12: =IF(MOV_CC_NACIONAL!C12="","",MOV_CC_NACIONAL!C12) -> 86791 | E12: =IF(B12="","", "CLP") -> CLP | F12: =IFERROR(__xludf.DUMMYFUNCTION("IF(C12="""","""", OR(REGEXMATCH(LOWER(C12),""cuota""), REGEXMATCH(C12,""\d+\s*/\s*\d+"")))"),FALSE) -> FALSE | G12: =IFERROR(__xludf.DUMMYFUNCTION("IFERROR(VALUE(REGEXEXTRACT(C12,""(\d+)\s*/\s*\d+"")),"""")"),"") | H12: =IFERROR(__xludf.DUMMYFUNCTION("IFERROR(VALUE(REGEXEXTRACT(C12,""\d+\s*/\s*(\d+)"")),"""")"),"") | I12: =IF(OR(G12="",H12=""),"",H12-G12) | J12: =IF(OR(D12="",I12=""),"",D12*I12)
A13: NAC | B13: =IF(MOV_CC_NACIONAL!A13="","",MOV_CC_NACIONAL!A13) -> 21-02-2026 | C13: =IF(MOV_CC_NACIONAL!B13="","",MOV_CC_NACIONAL!B13) -> MERPAGO*OPTICASLUXO HUE CC 01-06 | D13: =IF(MOV_CC_NACIONAL!C13="","",MOV_CC_NACIONAL!C13) -> 41030 | E13: =IF(B13="","", "CLP") -> CLP | F13: =IFERROR(__xludf.DUMMYFUNCTION("IF(C13="""","""", OR(REGEXMATCH(LOWER(C13),""cuota""), REGEXMATCH(C13,""\d+\s*/\s*\d+"")))"),FALSE) -> FALSE | G13: =IFERROR(__xludf.DUMMYFUNCTION("IFERROR(VALUE(REGEXEXTRACT(C13,""(\d+)\s*/\s*\d+"")),"""")"),"") | H13: =IFERROR(__xludf.DUMMYFUNCTION("IFERROR(VALUE(REGEXEXTRACT(C13,""\d+\s*/\s*(\d+)"")),"""")"),"") | I13: =IF(OR(G13="",H13=""),"",H13-G13) | J13: =IF(OR(D13="",I13=""),"",D13*I13)
A14: NAC | B14: =IF(MOV_CC_NACIONAL!A14="","",MOV_CC_NACIONAL!A14) -> 21-02-2026 | C14: =IF(MOV_CC_NACIONAL!B14="","",MOV_CC_NACIONAL!B14) -> MERPAGO*OPTICASLUXO HUE CC 01-06 | D14: =IF(MOV_CC_NACIONAL!C14="","",MOV_CC_NACIONAL!C14) -> 18331 | E14: =IF(B14="","", "CLP") -> CLP | F14: =IFERROR(__xludf.DUMMYFUNCTION("IF(C14="""","""", OR(REGEXMATCH(LOWER(C14),""cuota""), REGEXMATCH(C14,""\d+\s*/\s*\d+"")))"),FALSE) -> FALSE | G14: =IFERROR(__xludf.DUMMYFUNCTION("IFERROR(VALUE(REGEXEXTRACT(C14,""(\d+)\s*/\s*\d+"")),"""")"),"") | H14: =IFERROR(__xludf.DUMMYFUNCTION("IFERROR(VALUE(REGEXEXTRACT(C14,""\d+\s*/\s*(\d+)"")),"""")"),"") | I14: =IF(OR(G14="",H14=""),"",H14-G14) | J14: =IF(OR(D14="",I14=""),"",D14*I14)
A15: NAC | B15: =IF(MOV_CC_NACIONAL!A15="","",MOV_CC_NACIONAL!A15) -> 14-02-2026 | C15: =IF(MOV_CC_NACIONAL!B15="","",MOV_CC_NACIONAL!B15) -> DP *IKEA COM SAN CF 01-03 | D15: =IF(MOV_CC_NACIONAL!C15="","",MOV_CC_NACIONAL!C15) -> 33240 | E15: =IF(B15="","", "CLP") -> CLP | F15: =IFERROR(__xludf.DUMMYFUNCTION("IF(C15="""","""", OR(REGEXMATCH(LOWER(C15),""cuota""), REGEXMATCH(C15,""\d+\s*/\s*\d+"")))"),FALSE) -> FALSE | G15: =IFERROR(__xludf.DUMMYFUNCTION("IFERROR(VALUE(REGEXEXTRACT(C15,""(\d+)\s*/\s*\d+"")),"""")"),"") | H15: =IFERROR(__xludf.DUMMYFUNCTION("IFERROR(VALUE(REGEXEXTRACT(C15,""\d+\s*/\s*(\d+)"")),"""")"),"") | I15: =IF(OR(G15="",H15=""),"",H15-G15) | J15: =IF(OR(D15="",I15=""),"",D15*I15)
A16: NAC | B16: =IF(MOV_CC_NACIONAL!A16="","",MOV_CC_NACIONAL!A16) -> 21-01-2026 | C16: =IF(MOV_CC_NACIONAL!B16="","",MOV_CC_NACIONAL!B16) -> MP *MERCADO LIB SAN CC 02-03 | D16: =IF(MOV_CC_NACIONAL!C16="","",MOV_CC_NACIONAL!C16) -> 15295 | E16: =IF(B16="","", "CLP") -> CLP | F16: =IFERROR(__xludf.DUMMYFUNCTION("IF(C16="""","""", OR(REGEXMATCH(LOWER(C16),""cuota""), REGEXMATCH(C16,""\d+\s*/\s*\d+"")))"),FALSE) -> FALSE | G16: =IFERROR(__xludf.DUMMYFUNCTION("IFERROR(VALUE(REGEXEXTRACT(C16,""(\d+)\s*/\s*\d+"")),"""")"),"") | H16: =IFERROR(__xludf.DUMMYFUNCTION("IFERROR(VALUE(REGEXEXTRACT(C16,""\d+\s*/\s*(\d+)"")),"""")"),"") | I16: =IF(OR(G16="",H16=""),"",H16-G16) | J16: =IF(OR(D16="",I16=""),"",D16*I16)
A17: NAC | B17: =IF(MOV_CC_NACIONAL!A17="","",MOV_CC_NACIONAL!A17) -> 46235 | C17: =IF(MOV_CC_NACIONAL!B17="","",MOV_CC_NACIONAL!B17) -> MP *MERCADO LIB SAN CC 03-06 | D17: =IF(MOV_CC_NACIONAL!C17="","",MOV_CC_NACIONAL!C17) -> 20813 | E17: =IF(B17="","", "CLP") -> CLP | F17: =IFERROR(__xludf.DUMMYFUNCTION("IF(C17="""","""", OR(REGEXMATCH(LOWER(C17),""cuota""), REGEXMATCH(C17,""\d+\s*/\s*\d+"")))"),FALSE) -> FALSE | G17: =IFERROR(__xludf.DUMMYFUNCTION("IFERROR(VALUE(REGEXEXTRACT(C17,""(\d+)\s*/\s*\d+"")),"""")"),"") | H17: =IFERROR(__xludf.DUMMYFUNCTION("IFERROR(VALUE(REGEXEXTRACT(C17,""\d+\s*/\s*(\d+)"")),"""")"),"") | I17: =IF(OR(G17="",H17=""),"",H17-G17) | J17: =IF(OR(D17="",I17=""),"",D17*I17)
A18: NAC | B18: =IF(MOV_CC_NACIONAL!A18="","",MOV_CC_NACIONAL!A18) -> 46204 | C18: =IF(MOV_CC_NACIONAL!B18="","",MOV_CC_NACIONAL!B18) -> MERCADOPAGO*STREETD LAS CF 02-06 | D18: =IF(MOV_CC_NACIONAL!C18="","",MOV_CC_NACIONAL!C18) -> 10997 | E18: =IF(B18="","", "CLP") -> CLP | F18: =IFERROR(__xludf.DUMMYFUNCTION("IF(C18="""","""", OR(REGEXMATCH(LOWER(C18),""cuota""), REGEXMATCH(C18,""\d+\s*/\s*\d+"")))"),FALSE) -> FALSE | G18: =IFERROR(__xludf.DUMMYFUNCTION("IFERROR(VALUE(REGEXEXTRACT(C18,""(\d+)\s*/\s*\d+"")),"""")"),"") | H18: =IFERROR(__xludf.DUMMYFUNCTION("IFERROR(VALUE(REGEXEXTRACT(C18,""\d+\s*/\s*(\d+)"")),"""")"),"") | I18: =IF(OR(G18="",H18=""),"",H18-G18) | J18: =IF(OR(D18="",I18=""),"",D18*I18)
A19: NAC | B19: =IF(MOV_CC_NACIONAL!A19="","",MOV_CC_NACIONAL!A19) -> 21-12-2025 | C19: =IF(MOV_CC_NACIONAL!B19="","",MOV_CC_NACIONAL!B19) -> MERPAGO*MERCADOLIBR LAS CC 03-03 | D19: =IF(MOV_CC_NACIONAL!C19="","",MOV_CC_NACIONAL!C19) -> 17538 | E19: =IF(B19="","", "CLP") -> CLP | F19: =IFERROR(__xludf.DUMMYFUNCTION("IF(C19="""","""", OR(REGEXMATCH(LOWER(C19),""cuota""), REGEXMATCH(C19,""\d+\s*/\s*\d+"")))"),FALSE) -> FALSE | G19: =IFERROR(__xludf.DUMMYFUNCTION("IFERROR(VALUE(REGEXEXTRACT(C19,""(\d+)\s*/\s*\d+"")),"""")"),"") | H19: =IFERROR(__xludf.DUMMYFUNCTION("IFERROR(VALUE(REGEXEXTRACT(C19,""\d+\s*/\s*(\d+)"")),"""")"),"") | I19: =IF(OR(G19="",H19=""),"",H19-G19) | J19: =IF(OR(D19="",I19=""),"",D19*I19)
A20: NAC | B20: =IF(MOV_CC_NACIONAL!A20="","",MOV_CC_NACIONAL!A20) -> 28-11-2025 | C20: =IF(MOV_CC_NACIONAL!B20="","",MOV_CC_NACIONAL!B20) -> CIC HOGAR TIENDA CO CON CC 04-06 | D20: =IF(MOV_CC_NACIONAL!C20="","",MOV_CC_NACIONAL!C20) -> 20496 | E20: =IF(B20="","", "CLP") -> CLP | F20: =IFERROR(__xludf.DUMMYFUNCTION("IF(C20="""","""", OR(REGEXMATCH(LOWER(C20),""cuota""), REGEXMATCH(C20,""\d+\s*/\s*\d+"")))"),FALSE) -> FALSE | G20: =IFERROR(__xludf.DUMMYFUNCTION("IFERROR(VALUE(REGEXEXTRACT(C20,""(\d+)\s*/\s*\d+"")),"""")"),"") | H20: =IFERROR(__xludf.DUMMYFUNCTION("IFERROR(VALUE(REGEXEXTRACT(C20,""\d+\s*/\s*(\d+)"")),"""")"),"") | I20: =IF(OR(G20="",H20=""),"",H20-G20) | J20: =IF(OR(D20="",I20=""),"",D20*I20)
A21: NAC | B21: =IF(MOV_CC_NACIONAL!A21="","",MOV_CC_NACIONAL!A21) -> 28-08-2025 | C21: =IF(MOV_CC_NACIONAL!B21="","",MOV_CC_NACIONAL!B21) -> MERCADOPAGO*MONSTER LAS CF 06-06 | D21: =IF(MOV_CC_NACIONAL!C21="","",MOV_CC_NACIONAL!C21) -> 14667 | E21: =IF(B21="","", "CLP") -> CLP | F21: =IFERROR(__xludf.DUMMYFUNCTION("IF(C21="""","""", OR(REGEXMATCH(LOWER(C21),""cuota""), REGEXMATCH(C21,""\d+\s*/\s*\d+"")))"),FALSE) -> FALSE | G21: =IFERROR(__xludf.DUMMYFUNCTION("IFERROR(VALUE(REGEXEXTRACT(C21,""(\d+)\s*/\s*\d+"")),"""")"),"") | H21: =IFERROR(__xludf.DUMMYFUNCTION("IFERROR(VALUE(REGEXEXTRACT(C21,""\d+\s*/\s*(\d+)"")),"""")"),"") | I21: =IF(OR(G21="",H21=""),"",H21-G21) | J21: =IF(OR(D21="",I21=""),"",D21*I21)
A22: NAC | B22: =IF(MOV_CC_NACIONAL!A22="","",MOV_CC_NACIONAL!A22) | C22: =IF(MOV_CC_NACIONAL!B22="","",MOV_CC_NACIONAL!B22) | D22: =IF(MOV_CC_NACIONAL!C22="","",MOV_CC_NACIONAL!C22) | E22: =IF(B22="","", "CLP") | F22: =IFERROR(__xludf.DUMMYFUNCTION("IF(C22="""","""", OR(REGEXMATCH(LOWER(C22),""cuota""), REGEXMATCH(C22,""\d+\s*/\s*\d+"")))"),"") | G22: =IFERROR(__xludf.DUMMYFUNCTION("IFERROR(VALUE(REGEXEXTRACT(C22,""(\d+)\s*/\s*\d+"")),"""")"),"") | H22: =IFERROR(__xludf.DUMMYFUNCTION("IFERROR(VALUE(REGEXEXTRACT(C22,""\d+\s*/\s*(\d+)"")),"""")"),"") | I22: =IF(OR(G22="",H22=""),"",H22-G22) | J22: =IF(OR(D22="",I22=""),"",D22*I22)
A23: NAC | B23: =IF(MOV_CC_NACIONAL!A23="","",MOV_CC_NACIONAL!A23) | C23: =IF(MOV_CC_NACIONAL!B23="","",MOV_CC_NACIONAL!B23) | D23: =IF(MOV_CC_NACIONAL!C23="","",MOV_CC_NACIONAL!C23) | E23: =IF(B23="","", "CLP") | F23: =IFERROR(__xludf.DUMMYFUNCTION("IF(C23="""","""", OR(REGEXMATCH(LOWER(C23),""cuota""), REGEXMATCH(C23,""\d+\s*/\s*\d+"")))"),"") | G23: =IFERROR(__xludf.DUMMYFUNCTION("IFERROR(VALUE(REGEXEXTRACT(C23,""(\d+)\s*/\s*\d+"")),"""")"),"") | H23: =IFERROR(__xludf.DUMMYFUNCTION("IFERROR(VALUE(REGEXEXTRACT(C23,""\d+\s*/\s*(\d+)"")),"""")"),"") | I23: =IF(OR(G23="",H23=""),"",H23-G23) | J23: =IF(OR(D23="",I23=""),"",D23*I23)
A24: NAC | B24: =IF(MOV_CC_NACIONAL!A24="","",MOV_CC_NACIONAL!A24) | C24: =IF(MOV_CC_NACIONAL!B24="","",MOV_CC_NACIONAL!B24) | D24: =IF(MOV_CC_NACIONAL!C24="","",MOV_CC_NACIONAL!C24) | E24: =IF(B24="","", "CLP") | F24: =IFERROR(__xludf.DUMMYFUNCTION("IF(C24="""","""", OR(REGEXMATCH(LOWER(C24),""cuota""), REGEXMATCH(C24,""\d+\s*/\s*\d+"")))"),"") | G24: =IFERROR(__xludf.DUMMYFUNCTION("IFERROR(VALUE(REGEXEXTRACT(C24,""(\d+)\s*/\s*\d+"")),"""")"),"") | H24: =IFERROR(__xludf.DUMMYFUNCTION("IFERROR(VALUE(REGEXEXTRACT(C24,""\d+\s*/\s*(\d+)"")),"""")"),"") | I24: =IF(OR(G24="",H24=""),"",H24-G24) | J24: =IF(OR(D24="",I24=""),"",D24*I24)
A25: NAC | B25: =IF(MOV_CC_NACIONAL!A25="","",MOV_CC_NACIONAL!A25) | C25: =IF(MOV_CC_NACIONAL!B25="","",MOV_CC_NACIONAL!B25) | D25: =IF(MOV_CC_NACIONAL!C25="","",MOV_CC_NACIONAL!C25) | E25: =IF(B25="","", "CLP") | F25: =IFERROR(__xludf.DUMMYFUNCTION("IF(C25="""","""", OR(REGEXMATCH(LOWER(C25),""cuota""), REGEXMATCH(C25,""\d+\s*/\s*\d+"")))"),"") | G25: =IFERROR(__xludf.DUMMYFUNCTION("IFERROR(VALUE(REGEXEXTRACT(C25,""(\d+)\s*/\s*\d+"")),"""")"),"") | H25: =IFERROR(__xludf.DUMMYFUNCTION("IFERROR(VALUE(REGEXEXTRACT(C25,""\d+\s*/\s*(\d+)"")),"""")"),"") | I25: =IF(OR(G25="",H25=""),"",H25-G25) | J25: =IF(OR(D25="",I25=""),"",D25*I25)
A26: NAC | B26: =IF(MOV_CC_NACIONAL!A26="","",MOV_CC_NACIONAL!A26) | C26: =IF(MOV_CC_NACIONAL!B26="","",MOV_CC_NACIONAL!B26) | D26: =IF(MOV_CC_NACIONAL!C26="","",MOV_CC_NACIONAL!C26) | E26: =IF(B26="","", "CLP") | F26: =IFERROR(__xludf.DUMMYFUNCTION("IF(C26="""","""", OR(REGEXMATCH(LOWER(C26),""cuota""), REGEXMATCH(C26,""\d+\s*/\s*\d+"")))"),"") | G26: =IFERROR(__xludf.DUMMYFUNCTION("IFERROR(VALUE(REGEXEXTRACT(C26,""(\d+)\s*/\s*\d+"")),"""")"),"") | H26: =IFERROR(__xludf.DUMMYFUNCTION("IFERROR(VALUE(REGEXEXTRACT(C26,""\d+\s*/\s*(\d+)"")),"""")"),"") | I26: =IF(OR(G26="",H26=""),"",H26-G26) | J26: =IF(OR(D26="",I26=""),"",D26*I26)
A27: NAC | B27: =IF(MOV_CC_NACIONAL!A27="","",MOV_CC_NACIONAL!A27) | C27: =IF(MOV_CC_NACIONAL!B27="","",MOV_CC_NACIONAL!B27) | D27: =IF(MOV_CC_NACIONAL!C27="","",MOV_CC_NACIONAL!C27) | E27: =IF(B27="","", "CLP") | F27: =IFERROR(__xludf.DUMMYFUNCTION("IF(C27="""","""", OR(REGEXMATCH(LOWER(C27),""cuota""), REGEXMATCH(C27,""\d+\s*/\s*\d+"")))"),"") | G27: =IFERROR(__xludf.DUMMYFUNCTION("IFERROR(VALUE(REGEXEXTRACT(C27,""(\d+)\s*/\s*\d+"")),"""")"),"") | H27: =IFERROR(__xludf.DUMMYFUNCTION("IFERROR(VALUE(REGEXEXTRACT(C27,""\d+\s*/\s*(\d+)"")),"""")"),"") | I27: =IF(OR(G27="",H27=""),"",H27-G27) | J27: =IF(OR(D27="",I27=""),"",D27*I27)
A28: NAC | B28: =IF(MOV_CC_NACIONAL!A28="","",MOV_CC_NACIONAL!A28) | C28: =IF(MOV_CC_NACIONAL!B28="","",MOV_CC_NACIONAL!B28) | D28: =IF(MOV_CC_NACIONAL!C28="","",MOV_CC_NACIONAL!C28) | E28: =IF(B28="","", "CLP") | F28: =IFERROR(__xludf.DUMMYFUNCTION("IF(C28="""","""", OR(REGEXMATCH(LOWER(C28),""cuota""), REGEXMATCH(C28,""\d+\s*/\s*\d+"")))"),"") | G28: =IFERROR(__xludf.DUMMYFUNCTION("IFERROR(VALUE(REGEXEXTRACT(C28,""(\d+)\s*/\s*\d+"")),"""")"),"") | H28: =IFERROR(__xludf.DUMMYFUNCTION("IFERROR(VALUE(REGEXEXTRACT(C28,""\d+\s*/\s*(\d+)"")),"""")"),"") | I28: =IF(OR(G28="",H28=""),"",H28-G28) | J28: =IF(OR(D28="",I28=""),"",D28*I28)
A29: NAC | B29: =IF(MOV_CC_NACIONAL!A29="","",MOV_CC_NACIONAL!A29) | C29: =IF(MOV_CC_NACIONAL!B29="","",MOV_CC_NACIONAL!B29) | D29: =IF(MOV_CC_NACIONAL!C29="","",MOV_CC_NACIONAL!C29) | E29: =IF(B29="","", "CLP") | F29: =IFERROR(__xludf.DUMMYFUNCTION("IF(C29="""","""", OR(REGEXMATCH(LOWER(C29),""cuota""), REGEXMATCH(C29,""\d+\s*/\s*\d+"")))"),"") | G29: =IFERROR(__xludf.DUMMYFUNCTION("IFERROR(VALUE(REGEXEXTRACT(C29,""(\d+)\s*/\s*\d+"")),"""")"),"") | H29: =IFERROR(__xludf.DUMMYFUNCTION("IFERROR(VALUE(REGEXEXTRACT(C29,""\d+\s*/\s*(\d+)"")),"""")"),"") | I29: =IF(OR(G29="",H29=""),"",H29-G29) | J29: =IF(OR(D29="",I29=""),"",D29*I29)
A30: NAC | B30: =IF(MOV_CC_NACIONAL!A30="","",MOV_CC_NACIONAL!A30) | C30: =IF(MOV_CC_NACIONAL!B30="","",MOV_CC_NACIONAL!B30) | D30: =IF(MOV_CC_NACIONAL!C30="","",MOV_CC_NACIONAL!C30) | E30: =IF(B30="","", "CLP") | F30: =IFERROR(__xludf.DUMMYFUNCTION("IF(C30="""","""", OR(REGEXMATCH(LOWER(C30),""cuota""), REGEXMATCH(C30,""\d+\s*/\s*\d+"")))"),"") | G30: =IFERROR(__xludf.DUMMYFUNCTION("IFERROR(VALUE(REGEXEXTRACT(C30,""(\d+)\s*/\s*\d+"")),"""")"),"") | H30: =IFERROR(__xludf.DUMMYFUNCTION("IFERROR(VALUE(REGEXEXTRACT(C30,""\d+\s*/\s*(\d+)"")),"""")"),"") | I30: =IF(OR(G30="",H30=""),"",H30-G30) | J30: =IF(OR(D30="",I30=""),"",D30*I30)
A31: NAC | B31: =IF(MOV_CC_NACIONAL!A31="","",MOV_CC_NACIONAL!A31) | C31: =IF(MOV_CC_NACIONAL!B31="","",MOV_CC_NACIONAL!B31) | D31: =IF(MOV_CC_NACIONAL!C31="","",MOV_CC_NACIONAL!C31) | E31: =IF(B31="","", "CLP") | F31: =IFERROR(__xludf.DUMMYFUNCTION("IF(C31="""","""", OR(REGEXMATCH(LOWER(C31),""cuota""), REGEXMATCH(C31,""\d+\s*/\s*\d+"")))"),"") | G31: =IFERROR(__xludf.DUMMYFUNCTION("IFERROR(VALUE(REGEXEXTRACT(C31,""(\d+)\s*/\s*\d+"")),"""")"),"") | H31: =IFERROR(__xludf.DUMMYFUNCTION("IFERROR(VALUE(REGEXEXTRACT(C31,""\d+\s*/\s*(\d+)"")),"""")"),"") | I31: =IF(OR(G31="",H31=""),"",H31-G31) | J31: =IF(OR(D31="",I31=""),"",D31*I31)
A32: NAC | B32: =IF(MOV_CC_NACIONAL!A32="","",MOV_CC_NACIONAL!A32) | C32: =IF(MOV_CC_NACIONAL!B32="","",MOV_CC_NACIONAL!B32) | D32: =IF(MOV_CC_NACIONAL!C32="","",MOV_CC_NACIONAL!C32) | E32: =IF(B32="","", "CLP") | F32: =IFERROR(__xludf.DUMMYFUNCTION("IF(C32="""","""", OR(REGEXMATCH(LOWER(C32),""cuota""), REGEXMATCH(C32,""\d+\s*/\s*\d+"")))"),"") | G32: =IFERROR(__xludf.DUMMYFUNCTION("IFERROR(VALUE(REGEXEXTRACT(C32,""(\d+)\s*/\s*\d+"")),"""")"),"") | H32: =IFERROR(__xludf.DUMMYFUNCTION("IFERROR(VALUE(REGEXEXTRACT(C32,""\d+\s*/\s*(\d+)"")),"""")"),"") | I32: =IF(OR(G32="",H32=""),"",H32-G32) | J32: =IF(OR(D32="",I32=""),"",D32*I32)
A33: NAC | B33: =IF(MOV_CC_NACIONAL!A33="","",MOV_CC_NACIONAL!A33) | C33: =IF(MOV_CC_NACIONAL!B33="","",MOV_CC_NACIONAL!B33) | D33: =IF(MOV_CC_NACIONAL!C33="","",MOV_CC_NACIONAL!C33) | E33: =IF(B33="","", "CLP") | F33: =IFERROR(__xludf.DUMMYFUNCTION("IF(C33="""","""", OR(REGEXMATCH(LOWER(C33),""cuota""), REGEXMATCH(C33,""\d+\s*/\s*\d+"")))"),"") | G33: =IFERROR(__xludf.DUMMYFUNCTION("IFERROR(VALUE(REGEXEXTRACT(C33,""(\d+)\s*/\s*\d+"")),"""")"),"") | H33: =IFERROR(__xludf.DUMMYFUNCTION("IFERROR(VALUE(REGEXEXTRACT(C33,""\d+\s*/\s*(\d+)"")),"""")"),"") | I33: =IF(OR(G33="",H33=""),"",H33-G33) | J33: =IF(OR(D33="",I33=""),"",D33*I33)
A34: NAC | B34: =IF(MOV_CC_NACIONAL!A34="","",MOV_CC_NACIONAL!A34) | C34: =IF(MOV_CC_NACIONAL!B34="","",MOV_CC_NACIONAL!B34) | D34: =IF(MOV_CC_NACIONAL!C34="","",MOV_CC_NACIONAL!C34) | E34: =IF(B34="","", "CLP") | F34: =IFERROR(__xludf.DUMMYFUNCTION("IF(C34="""","""", OR(REGEXMATCH(LOWER(C34),""cuota""), REGEXMATCH(C34,""\d+\s*/\s*\d+"")))"),"") | G34: =IFERROR(__xludf.DUMMYFUNCTION("IFERROR(VALUE(REGEXEXTRACT(C34,""(\d+)\s*/\s*\d+"")),"""")"),"") | H34: =IFERROR(__xludf.DUMMYFUNCTION("IFERROR(VALUE(REGEXEXTRACT(C34,""\d+\s*/\s*(\d+)"")),"""")"),"") | I34: =IF(OR(G34="",H34=""),"",H34-G34) | J34: =IF(OR(D34="",I34=""),"",D34*I34)
A35: NAC | B35: =IF(MOV_CC_NACIONAL!A35="","",MOV_CC_NACIONAL!A35) | C35: =IF(MOV_CC_NACIONAL!B35="","",MOV_CC_NACIONAL!B35) | D35: =IF(MOV_CC_NACIONAL!C35="","",MOV_CC_NACIONAL!C35) | E35: =IF(B35="","", "CLP") | F35: =IFERROR(__xludf.DUMMYFUNCTION("IF(C35="""","""", OR(REGEXMATCH(LOWER(C35),""cuota""), REGEXMATCH(C35,""\d+\s*/\s*\d+"")))"),"") | G35: =IFERROR(__xludf.DUMMYFUNCTION("IFERROR(VALUE(REGEXEXTRACT(C35,""(\d+)\s*/\s*\d+"")),"""")"),"") | H35: =IFERROR(__xludf.DUMMYFUNCTION("IFERROR(VALUE(REGEXEXTRACT(C35,""\d+\s*/\s*(\d+)"")),"""")"),"") | I35: =IF(OR(G35="",H35=""),"",H35-G35) | J35: =IF(OR(D35="",I35=""),"",D35*I35)
A36: NAC | B36: =IF(MOV_CC_NACIONAL!A36="","",MOV_CC_NACIONAL!A36) | C36: =IF(MOV_CC_NACIONAL!B36="","",MOV_CC_NACIONAL!B36) | D36: =IF(MOV_CC_NACIONAL!C36="","",MOV_CC_NACIONAL!C36) | E36: =IF(B36="","", "CLP") | F36: =IFERROR(__xludf.DUMMYFUNCTION("IF(C36="""","""", OR(REGEXMATCH(LOWER(C36),""cuota""), REGEXMATCH(C36,""\d+\s*/\s*\d+"")))"),"") | G36: =IFERROR(__xludf.DUMMYFUNCTION("IFERROR(VALUE(REGEXEXTRACT(C36,""(\d+)\s*/\s*\d+"")),"""")"),"") | H36: =IFERROR(__xludf.DUMMYFUNCTION("IFERROR(VALUE(REGEXEXTRACT(C36,""\d+\s*/\s*(\d+)"")),"""")"),"") | I36: =IF(OR(G36="",H36=""),"",H36-G36) | J36: =IF(OR(D36="",I36=""),"",D36*I36)
A37: NAC | B37: =IF(MOV_CC_NACIONAL!A37="","",MOV_CC_NACIONAL!A37) | C37: =IF(MOV_CC_NACIONAL!B37="","",MOV_CC_NACIONAL!B37) | D37: =IF(MOV_CC_NACIONAL!C37="","",MOV_CC_NACIONAL!C37) | E37: =IF(B37="","", "CLP") | F37: =IFERROR(__xludf.DUMMYFUNCTION("IF(C37="""","""", OR(REGEXMATCH(LOWER(C37),""cuota""), REGEXMATCH(C37,""\d+\s*/\s*\d+"")))"),"") | G37: =IFERROR(__xludf.DUMMYFUNCTION("IFERROR(VALUE(REGEXEXTRACT(C37,""(\d+)\s*/\s*\d+"")),"""")"),"") | H37: =IFERROR(__xludf.DUMMYFUNCTION("IFERROR(VALUE(REGEXEXTRACT(C37,""\d+\s*/\s*(\d+)"")),"""")"),"") | I37: =IF(OR(G37="",H37=""),"",H37-G37) | J37: =IF(OR(D37="",I37=""),"",D37*I37)
A38: NAC | B38: =IF(MOV_CC_NACIONAL!A38="","",MOV_CC_NACIONAL!A38) | C38: =IF(MOV_CC_NACIONAL!B38="","",MOV_CC_NACIONAL!B38) | D38: =IF(MOV_CC_NACIONAL!C38="","",MOV_CC_NACIONAL!C38) | E38: =IF(B38="","", "CLP") | F38: =IFERROR(__xludf.DUMMYFUNCTION("IF(C38="""","""", OR(REGEXMATCH(LOWER(C38),""cuota""), REGEXMATCH(C38,""\d+\s*/\s*\d+"")))"),"") | G38: =IFERROR(__xludf.DUMMYFUNCTION("IFERROR(VALUE(REGEXEXTRACT(C38,""(\d+)\s*/\s*\d+"")),"""")"),"") | H38: =IFERROR(__xludf.DUMMYFUNCTION("IFERROR(VALUE(REGEXEXTRACT(C38,""\d+\s*/\s*(\d+)"")),"""")"),"") | I38: =IF(OR(G38="",H38=""),"",H38-G38) | J38: =IF(OR(D38="",I38=""),"",D38*I38)
A39: NAC | B39: =IF(MOV_CC_NACIONAL!A39="","",MOV_CC_NACIONAL!A39) | C39: =IF(MOV_CC_NACIONAL!B39="","",MOV_CC_NACIONAL!B39) | D39: =IF(MOV_CC_NACIONAL!C39="","",MOV_CC_NACIONAL!C39) | E39: =IF(B39="","", "CLP") | F39: =IFERROR(__xludf.DUMMYFUNCTION("IF(C39="""","""", OR(REGEXMATCH(LOWER(C39),""cuota""), REGEXMATCH(C39,""\d+\s*/\s*\d+"")))"),"") | G39: =IFERROR(__xludf.DUMMYFUNCTION("IFERROR(VALUE(REGEXEXTRACT(C39,""(\d+)\s*/\s*\d+"")),"""")"),"") | H39: =IFERROR(__xludf.DUMMYFUNCTION("IFERROR(VALUE(REGEXEXTRACT(C39,""\d+\s*/\s*(\d+)"")),"""")"),"") | I39: =IF(OR(G39="",H39=""),"",H39-G39) | J39: =IF(OR(D39="",I39=""),"",D39*I39)
A40: NAC | B40: =IF(MOV_CC_NACIONAL!A40="","",MOV_CC_NACIONAL!A40) | C40: =IF(MOV_CC_NACIONAL!B40="","",MOV_CC_NACIONAL!B40) | D40: =IF(MOV_CC_NACIONAL!C40="","",MOV_CC_NACIONAL!C40) | E40: =IF(B40="","", "CLP") | F40: =IFERROR(__xludf.DUMMYFUNCTION("IF(C40="""","""", OR(REGEXMATCH(LOWER(C40),""cuota""), REGEXMATCH(C40,""\d+\s*/\s*\d+"")))"),"") | G40: =IFERROR(__xludf.DUMMYFUNCTION("IFERROR(VALUE(REGEXEXTRACT(C40,""(\d+)\s*/\s*\d+"")),"""")"),"") | H40: =IFERROR(__xludf.DUMMYFUNCTION("IFERROR(VALUE(REGEXEXTRACT(C40,""\d+\s*/\s*(\d+)"")),"""")"),"") | I40: =IF(OR(G40="",H40=""),"",H40-G40) | J40: =IF(OR(D40="",I40=""),"",D40*I40)
A41: NAC | B41: =IF(MOV_CC_NACIONAL!A41="","",MOV_CC_NACIONAL!A41) | C41: =IF(MOV_CC_NACIONAL!B41="","",MOV_CC_NACIONAL!B41) | D41: =IF(MOV_CC_NACIONAL!C41="","",MOV_CC_NACIONAL!C41) | E41: =IF(B41="","", "CLP") | F41: =IFERROR(__xludf.DUMMYFUNCTION("IF(C41="""","""", OR(REGEXMATCH(LOWER(C41),""cuota""), REGEXMATCH(C41,""\d+\s*/\s*\d+"")))"),"") | G41: =IFERROR(__xludf.DUMMYFUNCTION("IFERROR(VALUE(REGEXEXTRACT(C41,""(\d+)\s*/\s*\d+"")),"""")"),"") | H41: =IFERROR(__xludf.DUMMYFUNCTION("IFERROR(VALUE(REGEXEXTRACT(C41,""\d+\s*/\s*(\d+)"")),"""")"),"") | I41: =IF(OR(G41="",H41=""),"",H41-G41) | J41: =IF(OR(D41="",I41=""),"",D41*I41)
A42: NAC | B42: =IF(MOV_CC_NACIONAL!A42="","",MOV_CC_NACIONAL!A42) | C42: =IF(MOV_CC_NACIONAL!B42="","",MOV_CC_NACIONAL!B42) | D42: =IF(MOV_CC_NACIONAL!C42="","",MOV_CC_NACIONAL!C42) | E42: =IF(B42="","", "CLP") | F42: =IFERROR(__xludf.DUMMYFUNCTION("IF(C42="""","""", OR(REGEXMATCH(LOWER(C42),""cuota""), REGEXMATCH(C42,""\d+\s*/\s*\d+"")))"),"") | G42: =IFERROR(__xludf.DUMMYFUNCTION("IFERROR(VALUE(REGEXEXTRACT(C42,""(\d+)\s*/\s*\d+"")),"""")"),"") | H42: =IFERROR(__xludf.DUMMYFUNCTION("IFERROR(VALUE(REGEXEXTRACT(C42,""\d+\s*/\s*(\d+)"")),"""")"),"") | I42: =IF(OR(G42="",H42=""),"",H42-G42) | J42: =IF(OR(D42="",I42=""),"",D42*I42)
A43: NAC | B43: =IF(MOV_CC_NACIONAL!A43="","",MOV_CC_NACIONAL!A43) | C43: =IF(MOV_CC_NACIONAL!B43="","",MOV_CC_NACIONAL!B43) | D43: =IF(MOV_CC_NACIONAL!C43="","",MOV_CC_NACIONAL!C43) | E43: =IF(B43="","", "CLP") | F43: =IFERROR(__xludf.DUMMYFUNCTION("IF(C43="""","""", OR(REGEXMATCH(LOWER(C43),""cuota""), REGEXMATCH(C43,""\d+\s*/\s*\d+"")))"),"") | G43: =IFERROR(__xludf.DUMMYFUNCTION("IFERROR(VALUE(REGEXEXTRACT(C43,""(\d+)\s*/\s*\d+"")),"""")"),"") | H43: =IFERROR(__xludf.DUMMYFUNCTION("IFERROR(VALUE(REGEXEXTRACT(C43,""\d+\s*/\s*(\d+)"")),"""")"),"") | I43: =IF(OR(G43="",H43=""),"",H43-G43) | J43: =IF(OR(D43="",I43=""),"",D43*I43)
A44: NAC | B44: =IF(MOV_CC_NACIONAL!A44="","",MOV_CC_NACIONAL!A44) | C44: =IF(MOV_CC_NACIONAL!B44="","",MOV_CC_NACIONAL!B44) | D44: =IF(MOV_CC_NACIONAL!C44="","",MOV_CC_NACIONAL!C44) | E44: =IF(B44="","", "CLP") | F44: =IFERROR(__xludf.DUMMYFUNCTION("IF(C44="""","""", OR(REGEXMATCH(LOWER(C44),""cuota""), REGEXMATCH(C44,""\d+\s*/\s*\d+"")))"),"") | G44: =IFERROR(__xludf.DUMMYFUNCTION("IFERROR(VALUE(REGEXEXTRACT(C44,""(\d+)\s*/\s*\d+"")),"""")"),"") | H44: =IFERROR(__xludf.DUMMYFUNCTION("IFERROR(VALUE(REGEXEXTRACT(C44,""\d+\s*/\s*(\d+)"")),"""")"),"") | I44: =IF(OR(G44="",H44=""),"",H44-G44) | J44: =IF(OR(D44="",I44=""),"",D44*I44)
A45: NAC | B45: =IF(MOV_CC_NACIONAL!A45="","",MOV_CC_NACIONAL!A45) | C45: =IF(MOV_CC_NACIONAL!B45="","",MOV_CC_NACIONAL!B45) | D45: =IF(MOV_CC_NACIONAL!C45="","",MOV_CC_NACIONAL!C45) | E45: =IF(B45="","", "CLP") | F45: =IFERROR(__xludf.DUMMYFUNCTION("IF(C45="""","""", OR(REGEXMATCH(LOWER(C45),""cuota""), REGEXMATCH(C45,""\d+\s*/\s*\d+"")))"),"") | G45: =IFERROR(__xludf.DUMMYFUNCTION("IFERROR(VALUE(REGEXEXTRACT(C45,""(\d+)\s*/\s*\d+"")),"""")"),"") | H45: =IFERROR(__xludf.DUMMYFUNCTION("IFERROR(VALUE(REGEXEXTRACT(C45,""\d+\s*/\s*(\d+)"")),"""")"),"") | I45: =IF(OR(G45="",H45=""),"",H45-G45) | J45: =IF(OR(D45="",I45=""),"",D45*I45)
A46: NAC | B46: =IF(MOV_CC_NACIONAL!A46="","",MOV_CC_NACIONAL!A46) | C46: =IF(MOV_CC_NACIONAL!B46="","",MOV_CC_NACIONAL!B46) | D46: =IF(MOV_CC_NACIONAL!C46="","",MOV_CC_NACIONAL!C46) | E46: =IF(B46="","", "CLP") | F46: =IFERROR(__xludf.DUMMYFUNCTION("IF(C46="""","""", OR(REGEXMATCH(LOWER(C46),""cuota""), REGEXMATCH(C46,""\d+\s*/\s*\d+"")))"),"") | G46: =IFERROR(__xludf.DUMMYFUNCTION("IFERROR(VALUE(REGEXEXTRACT(C46,""(\d+)\s*/\s*\d+"")),"""")"),"") | H46: =IFERROR(__xludf.DUMMYFUNCTION("IFERROR(VALUE(REGEXEXTRACT(C46,""\d+\s*/\s*(\d+)"")),"""")"),"") | I46: =IF(OR(G46="",H46=""),"",H46-G46) | J46: =IF(OR(D46="",I46=""),"",D46*I46)
A47: NAC | B47: =IF(MOV_CC_NACIONAL!A47="","",MOV_CC_NACIONAL!A47) | C47: =IF(MOV_CC_NACIONAL!B47="","",MOV_CC_NACIONAL!B47) | D47: =IF(MOV_CC_NACIONAL!C47="","",MOV_CC_NACIONAL!C47) | E47: =IF(B47="","", "CLP") | F47: =IFERROR(__xludf.DUMMYFUNCTION("IF(C47="""","""", OR(REGEXMATCH(LOWER(C47),""cuota""), REGEXMATCH(C47,""\d+\s*/\s*\d+"")))"),"") | G47: =IFERROR(__xludf.DUMMYFUNCTION("IFERROR(VALUE(REGEXEXTRACT(C47,""(\d+)\s*/\s*\d+"")),"""")"),"") | H47: =IFERROR(__xludf.DUMMYFUNCTION("IFERROR(VALUE(REGEXEXTRACT(C47,""\d+\s*/\s*(\d+)"")),"""")"),"") | I47: =IF(OR(G47="",H47=""),"",H47-G47) | J47: =IF(OR(D47="",I47=""),"",D47*I47)
A48: NAC | B48: =IF(MOV_CC_NACIONAL!A48="","",MOV_CC_NACIONAL!A48) | C48: =IF(MOV_CC_NACIONAL!B48="","",MOV_CC_NACIONAL!B48) | D48: =IF(MOV_CC_NACIONAL!C48="","",MOV_CC_NACIONAL!C48) | E48: =IF(B48="","", "CLP") | F48: =IFERROR(__xludf.DUMMYFUNCTION("IF(C48="""","""", OR(REGEXMATCH(LOWER(C48),""cuota""), REGEXMATCH(C48,""\d+\s*/\s*\d+"")))"),"") | G48: =IFERROR(__xludf.DUMMYFUNCTION("IFERROR(VALUE(REGEXEXTRACT(C48,""(\d+)\s*/\s*\d+"")),"""")"),"") | H48: =IFERROR(__xludf.DUMMYFUNCTION("IFERROR(VALUE(REGEXEXTRACT(C48,""\d+\s*/\s*(\d+)"")),"""")"),"") | I48: =IF(OR(G48="",H48=""),"",H48-G48) | J48: =IF(OR(D48="",I48=""),"",D48*I48)
A49: NAC | B49: =IF(MOV_CC_NACIONAL!A49="","",MOV_CC_NACIONAL!A49) | C49: =IF(MOV_CC_NACIONAL!B49="","",MOV_CC_NACIONAL!B49) | D49: =IF(MOV_CC_NACIONAL!C49="","",MOV_CC_NACIONAL!C49) | E49: =IF(B49="","", "CLP") | F49: =IFERROR(__xludf.DUMMYFUNCTION("IF(C49="""","""", OR(REGEXMATCH(LOWER(C49),""cuota""), REGEXMATCH(C49,""\d+\s*/\s*\d+"")))"),"") | G49: =IFERROR(__xludf.DUMMYFUNCTION("IFERROR(VALUE(REGEXEXTRACT(C49,""(\d+)\s*/\s*\d+"")),"""")"),"") | H49: =IFERROR(__xludf.DUMMYFUNCTION("IFERROR(VALUE(REGEXEXTRACT(C49,""\d+\s*/\s*(\d+)"")),"""")"),"") | I49: =IF(OR(G49="",H49=""),"",H49-G49) | J49: =IF(OR(D49="",I49=""),"",D49*I49)
A50: NAC | B50: =IF(MOV_CC_NACIONAL!A50="","",MOV_CC_NACIONAL!A50) | C50: =IF(MOV_CC_NACIONAL!B50="","",MOV_CC_NACIONAL!B50) | D50: =IF(MOV_CC_NACIONAL!C50="","",MOV_CC_NACIONAL!C50) | E50: =IF(B50="","", "CLP") | F50: =IFERROR(__xludf.DUMMYFUNCTION("IF(C50="""","""", OR(REGEXMATCH(LOWER(C50),""cuota""), REGEXMATCH(C50,""\d+\s*/\s*\d+"")))"),"") | G50: =IFERROR(__xludf.DUMMYFUNCTION("IFERROR(VALUE(REGEXEXTRACT(C50,""(\d+)\s*/\s*\d+"")),"""")"),"") | H50: =IFERROR(__xludf.DUMMYFUNCTION("IFERROR(VALUE(REGEXEXTRACT(C50,""\d+\s*/\s*(\d+)"")),"""")"),"") | I50: =IF(OR(G50="",H50=""),"",H50-G50) | J50: =IF(OR(D50="",I50=""),"",D50*I50)
A51: NAC | B51: =IF(MOV_CC_NACIONAL!A51="","",MOV_CC_NACIONAL!A51) | C51: =IF(MOV_CC_NACIONAL!B51="","",MOV_CC_NACIONAL!B51) | D51: =IF(MOV_CC_NACIONAL!C51="","",MOV_CC_NACIONAL!C51) | E51: =IF(B51="","", "CLP") | F51: =IFERROR(__xludf.DUMMYFUNCTION("IF(C51="""","""", OR(REGEXMATCH(LOWER(C51),""cuota""), REGEXMATCH(C51,""\d+\s*/\s*\d+"")))"),"") | G51: =IFERROR(__xludf.DUMMYFUNCTION("IFERROR(VALUE(REGEXEXTRACT(C51,""(\d+)\s*/\s*\d+"")),"""")"),"") | H51: =IFERROR(__xludf.DUMMYFUNCTION("IFERROR(VALUE(REGEXEXTRACT(C51,""\d+\s*/\s*(\d+)"")),"""")"),"") | I51: =IF(OR(G51="",H51=""),"",H51-G51) | J51: =IF(OR(D51="",I51=""),"",D51*I51)
A52: NAC | B52: =IF(MOV_CC_NACIONAL!A52="","",MOV_CC_NACIONAL!A52) | C52: =IF(MOV_CC_NACIONAL!B52="","",MOV_CC_NACIONAL!B52) | D52: =IF(MOV_CC_NACIONAL!C52="","",MOV_CC_NACIONAL!C52) | E52: =IF(B52="","", "CLP") | F52: =IFERROR(__xludf.DUMMYFUNCTION("IF(C52="""","""", OR(REGEXMATCH(LOWER(C52),""cuota""), REGEXMATCH(C52,""\d+\s*/\s*\d+"")))"),"") | G52: =IFERROR(__xludf.DUMMYFUNCTION("IFERROR(VALUE(REGEXEXTRACT(C52,""(\d+)\s*/\s*\d+"")),"""")"),"") | H52: =IFERROR(__xludf.DUMMYFUNCTION("IFERROR(VALUE(REGEXEXTRACT(C52,""\d+\s*/\s*(\d+)"")),"""")"),"") | I52: =IF(OR(G52="",H52=""),"",H52-G52) | J52: =IF(OR(D52="",I52=""),"",D52*I52)
A53: NAC | B53: =IF(MOV_CC_NACIONAL!A53="","",MOV_CC_NACIONAL!A53) | C53: =IF(MOV_CC_NACIONAL!B53="","",MOV_CC_NACIONAL!B53) | D53: =IF(MOV_CC_NACIONAL!C53="","",MOV_CC_NACIONAL!C53) | E53: =IF(B53="","", "CLP") | F53: =IFERROR(__xludf.DUMMYFUNCTION("IF(C53="""","""", OR(REGEXMATCH(LOWER(C53),""cuota""), REGEXMATCH(C53,""\d+\s*/\s*\d+"")))"),"") | G53: =IFERROR(__xludf.DUMMYFUNCTION("IFERROR(VALUE(REGEXEXTRACT(C53,""(\d+)\s*/\s*\d+"")),"""")"),"") | H53: =IFERROR(__xludf.DUMMYFUNCTION("IFERROR(VALUE(REGEXEXTRACT(C53,""\d+\s*/\s*(\d+)"")),"""")"),"") | I53: =IF(OR(G53="",H53=""),"",H53-G53) | J53: =IF(OR(D53="",I53=""),"",D53*I53)
A54: NAC | B54: =IF(MOV_CC_NACIONAL!A54="","",MOV_CC_NACIONAL!A54) | C54: =IF(MOV_CC_NACIONAL!B54="","",MOV_CC_NACIONAL!B54) | D54: =IF(MOV_CC_NACIONAL!C54="","",MOV_CC_NACIONAL!C54) | E54: =IF(B54="","", "CLP") | F54: =IFERROR(__xludf.DUMMYFUNCTION("IF(C54="""","""", OR(REGEXMATCH(LOWER(C54),""cuota""), REGEXMATCH(C54,""\d+\s*/\s*\d+"")))"),"") | G54: =IFERROR(__xludf.DUMMYFUNCTION("IFERROR(VALUE(REGEXEXTRACT(C54,""(\d+)\s*/\s*\d+"")),"""")"),"") | H54: =IFERROR(__xludf.DUMMYFUNCTION("IFERROR(VALUE(REGEXEXTRACT(C54,""\d+\s*/\s*(\d+)"")),"""")"),"") | I54: =IF(OR(G54="",H54=""),"",H54-G54) | J54: =IF(OR(D54="",I54=""),"",D54*I54)
A55: NAC | B55: =IF(MOV_CC_NACIONAL!A55="","",MOV_CC_NACIONAL!A55) | C55: =IF(MOV_CC_NACIONAL!B55="","",MOV_CC_NACIONAL!B55) | D55: =IF(MOV_CC_NACIONAL!C55="","",MOV_CC_NACIONAL!C55) | E55: =IF(B55="","", "CLP") | F55: =IFERROR(__xludf.DUMMYFUNCTION("IF(C55="""","""", OR(REGEXMATCH(LOWER(C55),""cuota""), REGEXMATCH(C55,""\d+\s*/\s*\d+"")))"),"") | G55: =IFERROR(__xludf.DUMMYFUNCTION("IFERROR(VALUE(REGEXEXTRACT(C55,""(\d+)\s*/\s*\d+"")),"""")"),"") | H55: =IFERROR(__xludf.DUMMYFUNCTION("IFERROR(VALUE(REGEXEXTRACT(C55,""\d+\s*/\s*(\d+)"")),"""")"),"") | I55: =IF(OR(G55="",H55=""),"",H55-G55) | J55: =IF(OR(D55="",I55=""),"",D55*I55)
A56: NAC | B56: =IF(MOV_CC_NACIONAL!A56="","",MOV_CC_NACIONAL!A56) | C56: =IF(MOV_CC_NACIONAL!B56="","",MOV_CC_NACIONAL!B56) | D56: =IF(MOV_CC_NACIONAL!C56="","",MOV_CC_NACIONAL!C56) | E56: =IF(B56="","", "CLP") | F56: =IFERROR(__xludf.DUMMYFUNCTION("IF(C56="""","""", OR(REGEXMATCH(LOWER(C56),""cuota""), REGEXMATCH(C56,""\d+\s*/\s*\d+"")))"),"") | G56: =IFERROR(__xludf.DUMMYFUNCTION("IFERROR(VALUE(REGEXEXTRACT(C56,""(\d+)\s*/\s*\d+"")),"""")"),"") | H56: =IFERROR(__xludf.DUMMYFUNCTION("IFERROR(VALUE(REGEXEXTRACT(C56,""\d+\s*/\s*(\d+)"")),"""")"),"") | I56: =IF(OR(G56="",H56=""),"",H56-G56) | J56: =IF(OR(D56="",I56=""),"",D56*I56)
A57: NAC | B57: =IF(MOV_CC_NACIONAL!A57="","",MOV_CC_NACIONAL!A57) | C57: =IF(MOV_CC_NACIONAL!B57="","",MOV_CC_NACIONAL!B57) | D57: =IF(MOV_CC_NACIONAL!C57="","",MOV_CC_NACIONAL!C57) | E57: =IF(B57="","", "CLP") | F57: =IFERROR(__xludf.DUMMYFUNCTION("IF(C57="""","""", OR(REGEXMATCH(LOWER(C57),""cuota""), REGEXMATCH(C57,""\d+\s*/\s*\d+"")))"),"") | G57: =IFERROR(__xludf.DUMMYFUNCTION("IFERROR(VALUE(REGEXEXTRACT(C57,""(\d+)\s*/\s*\d+"")),"""")"),"") | H57: =IFERROR(__xludf.DUMMYFUNCTION("IFERROR(VALUE(REGEXEXTRACT(C57,""\d+\s*/\s*(\d+)"")),"""")"),"") | I57: =IF(OR(G57="",H57=""),"",H57-G57) | J57: =IF(OR(D57="",I57=""),"",D57*I57)
A58: NAC | B58: =IF(MOV_CC_NACIONAL!A58="","",MOV_CC_NACIONAL!A58) | C58: =IF(MOV_CC_NACIONAL!B58="","",MOV_CC_NACIONAL!B58) | D58: =IF(MOV_CC_NACIONAL!C58="","",MOV_CC_NACIONAL!C58) | E58: =IF(B58="","", "CLP") | F58: =IFERROR(__xludf.DUMMYFUNCTION("IF(C58="""","""", OR(REGEXMATCH(LOWER(C58),""cuota""), REGEXMATCH(C58,""\d+\s*/\s*\d+"")))"),"") | G58: =IFERROR(__xludf.DUMMYFUNCTION("IFERROR(VALUE(REGEXEXTRACT(C58,""(\d+)\s*/\s*\d+"")),"""")"),"") | H58: =IFERROR(__xludf.DUMMYFUNCTION("IFERROR(VALUE(REGEXEXTRACT(C58,""\d+\s*/\s*(\d+)"")),"""")"),"") | I58: =IF(OR(G58="",H58=""),"",H58-G58) | J58: =IF(OR(D58="",I58=""),"",D58*I58)
A59: NAC | B59: =IF(MOV_CC_NACIONAL!A59="","",MOV_CC_NACIONAL!A59) | C59: =IF(MOV_CC_NACIONAL!B59="","",MOV_CC_NACIONAL!B59) | D59: =IF(MOV_CC_NACIONAL!C59="","",MOV_CC_NACIONAL!C59) | E59: =IF(B59="","", "CLP") | F59: =IFERROR(__xludf.DUMMYFUNCTION("IF(C59="""","""", OR(REGEXMATCH(LOWER(C59),""cuota""), REGEXMATCH(C59,""\d+\s*/\s*\d+"")))"),"") | G59: =IFERROR(__xludf.DUMMYFUNCTION("IFERROR(VALUE(REGEXEXTRACT(C59,""(\d+)\s*/\s*\d+"")),"""")"),"") | H59: =IFERROR(__xludf.DUMMYFUNCTION("IFERROR(VALUE(REGEXEXTRACT(C59,""\d+\s*/\s*(\d+)"")),"""")"),"") | I59: =IF(OR(G59="",H59=""),"",H59-G59) | J59: =IF(OR(D59="",I59=""),"",D59*I59)
A60: NAC | B60: =IF(MOV_CC_NACIONAL!A60="","",MOV_CC_NACIONAL!A60) | C60: =IF(MOV_CC_NACIONAL!B60="","",MOV_CC_NACIONAL!B60) | D60: =IF(MOV_CC_NACIONAL!C60="","",MOV_CC_NACIONAL!C60) | E60: =IF(B60="","", "CLP") | F60: =IFERROR(__xludf.DUMMYFUNCTION("IF(C60="""","""", OR(REGEXMATCH(LOWER(C60),""cuota""), REGEXMATCH(C60,""\d+\s*/\s*\d+"")))"),"") | G60: =IFERROR(__xludf.DUMMYFUNCTION("IFERROR(VALUE(REGEXEXTRACT(C60,""(\d+)\s*/\s*\d+"")),"""")"),"") | H60: =IFERROR(__xludf.DUMMYFUNCTION("IFERROR(VALUE(REGEXEXTRACT(C60,""\d+\s*/\s*(\d+)"")),"""")"),"") | I60: =IF(OR(G60="",H60=""),"",H60-G60) | J60: =IF(OR(D60="",I60=""),"",D60*I60)
A61: NAC | B61: =IF(MOV_CC_NACIONAL!A61="","",MOV_CC_NACIONAL!A61) | C61: =IF(MOV_CC_NACIONAL!B61="","",MOV_CC_NACIONAL!B61) | D61: =IF(MOV_CC_NACIONAL!C61="","",MOV_CC_NACIONAL!C61) | E61: =IF(B61="","", "CLP") | F61: =IFERROR(__xludf.DUMMYFUNCTION("IF(C61="""","""", OR(REGEXMATCH(LOWER(C61),""cuota""), REGEXMATCH(C61,""\d+\s*/\s*\d+"")))"),"") | G61: =IFERROR(__xludf.DUMMYFUNCTION("IFERROR(VALUE(REGEXEXTRACT(C61,""(\d+)\s*/\s*\d+"")),"""")"),"") | H61: =IFERROR(__xludf.DUMMYFUNCTION("IFERROR(VALUE(REGEXEXTRACT(C61,""\d+\s*/\s*(\d+)"")),"""")"),"") | I61: =IF(OR(G61="",H61=""),"",H61-G61) | J61: =IF(OR(D61="",I61=""),"",D61*I61)
A62: NAC | B62: =IF(MOV_CC_NACIONAL!A62="","",MOV_CC_NACIONAL!A62) | C62: =IF(MOV_CC_NACIONAL!B62="","",MOV_CC_NACIONAL!B62) | D62: =IF(MOV_CC_NACIONAL!C62="","",MOV_CC_NACIONAL!C62) | E62: =IF(B62="","", "CLP") | F62: =IFERROR(__xludf.DUMMYFUNCTION("IF(C62="""","""", OR(REGEXMATCH(LOWER(C62),""cuota""), REGEXMATCH(C62,""\d+\s*/\s*\d+"")))"),"") | G62: =IFERROR(__xludf.DUMMYFUNCTION("IFERROR(VALUE(REGEXEXTRACT(C62,""(\d+)\s*/\s*\d+"")),"""")"),"") | H62: =IFERROR(__xludf.DUMMYFUNCTION("IFERROR(VALUE(REGEXEXTRACT(C62,""\d+\s*/\s*(\d+)"")),"""")"),"") | I62: =IF(OR(G62="",H62=""),"",H62-G62) | J62: =IF(OR(D62="",I62=""),"",D62*I62)
A63: NAC | B63: =IF(MOV_CC_NACIONAL!A63="","",MOV_CC_NACIONAL!A63) | C63: =IF(MOV_CC_NACIONAL!B63="","",MOV_CC_NACIONAL!B63) | D63: =IF(MOV_CC_NACIONAL!C63="","",MOV_CC_NACIONAL!C63) | E63: =IF(B63="","", "CLP") | F63: =IFERROR(__xludf.DUMMYFUNCTION("IF(C63="""","""", OR(REGEXMATCH(LOWER(C63),""cuota""), REGEXMATCH(C63,""\d+\s*/\s*\d+"")))"),"") | G63: =IFERROR(__xludf.DUMMYFUNCTION("IFERROR(VALUE(REGEXEXTRACT(C63,""(\d+)\s*/\s*\d+"")),"""")"),"") | H63: =IFERROR(__xludf.DUMMYFUNCTION("IFERROR(VALUE(REGEXEXTRACT(C63,""\d+\s*/\s*(\d+)"")),"""")"),"") | I63: =IF(OR(G63="",H63=""),"",H63-G63) | J63: =IF(OR(D63="",I63=""),"",D63*I63)
A64: NAC | B64: =IF(MOV_CC_NACIONAL!A64="","",MOV_CC_NACIONAL!A64) | C64: =IF(MOV_CC_NACIONAL!B64="","",MOV_CC_NACIONAL!B64) | D64: =IF(MOV_CC_NACIONAL!C64="","",MOV_CC_NACIONAL!C64) | E64: =IF(B64="","", "CLP") | F64: =IFERROR(__xludf.DUMMYFUNCTION("IF(C64="""","""", OR(REGEXMATCH(LOWER(C64),""cuota""), REGEXMATCH(C64,""\d+\s*/\s*\d+"")))"),"") | G64: =IFERROR(__xludf.DUMMYFUNCTION("IFERROR(VALUE(REGEXEXTRACT(C64,""(\d+)\s*/\s*\d+"")),"""")"),"") | H64: =IFERROR(__xludf.DUMMYFUNCTION("IFERROR(VALUE(REGEXEXTRACT(C64,""\d+\s*/\s*(\d+)"")),"""")"),"") | I64: =IF(OR(G64="",H64=""),"",H64-G64) | J64: =IF(OR(D64="",I64=""),"",D64*I64)
A65: NAC | B65: =IF(MOV_CC_NACIONAL!A65="","",MOV_CC_NACIONAL!A65) | C65: =IF(MOV_CC_NACIONAL!B65="","",MOV_CC_NACIONAL!B65) | D65: =IF(MOV_CC_NACIONAL!C65="","",MOV_CC_NACIONAL!C65) | E65: =IF(B65="","", "CLP") | F65: =IFERROR(__xludf.DUMMYFUNCTION("IF(C65="""","""", OR(REGEXMATCH(LOWER(C65),""cuota""), REGEXMATCH(C65,""\d+\s*/\s*\d+"")))"),"") | G65: =IFERROR(__xludf.DUMMYFUNCTION("IFERROR(VALUE(REGEXEXTRACT(C65,""(\d+)\s*/\s*\d+"")),"""")"),"") | H65: =IFERROR(__xludf.DUMMYFUNCTION("IFERROR(VALUE(REGEXEXTRACT(C65,""\d+\s*/\s*(\d+)"")),"""")"),"") | I65: =IF(OR(G65="",H65=""),"",H65-G65) | J65: =IF(OR(D65="",I65=""),"",D65*I65)
A66: NAC | B66: =IF(MOV_CC_NACIONAL!A66="","",MOV_CC_NACIONAL!A66) | C66: =IF(MOV_CC_NACIONAL!B66="","",MOV_CC_NACIONAL!B66) | D66: =IF(MOV_CC_NACIONAL!C66="","",MOV_CC_NACIONAL!C66) | E66: =IF(B66="","", "CLP") | F66: =IFERROR(__xludf.DUMMYFUNCTION("IF(C66="""","""", OR(REGEXMATCH(LOWER(C66),""cuota""), REGEXMATCH(C66,""\d+\s*/\s*\d+"")))"),"") | G66: =IFERROR(__xludf.DUMMYFUNCTION("IFERROR(VALUE(REGEXEXTRACT(C66,""(\d+)\s*/\s*\d+"")),"""")"),"") | H66: =IFERROR(__xludf.DUMMYFUNCTION("IFERROR(VALUE(REGEXEXTRACT(C66,""\d+\s*/\s*(\d+)"")),"""")"),"") | I66: =IF(OR(G66="",H66=""),"",H66-G66) | J66: =IF(OR(D66="",I66=""),"",D66*I66)
A67: NAC | B67: =IF(MOV_CC_NACIONAL!A67="","",MOV_CC_NACIONAL!A67) | C67: =IF(MOV_CC_NACIONAL!B67="","",MOV_CC_NACIONAL!B67) | D67: =IF(MOV_CC_NACIONAL!C67="","",MOV_CC_NACIONAL!C67) | E67: =IF(B67="","", "CLP") | F67: =IFERROR(__xludf.DUMMYFUNCTION("IF(C67="""","""", OR(REGEXMATCH(LOWER(C67),""cuota""), REGEXMATCH(C67,""\d+\s*/\s*\d+"")))"),"") | G67: =IFERROR(__xludf.DUMMYFUNCTION("IFERROR(VALUE(REGEXEXTRACT(C67,""(\d+)\s*/\s*\d+"")),"""")"),"") | H67: =IFERROR(__xludf.DUMMYFUNCTION("IFERROR(VALUE(REGEXEXTRACT(C67,""\d+\s*/\s*(\d+)"")),"""")"),"") | I67: =IF(OR(G67="",H67=""),"",H67-G67) | J67: =IF(OR(D67="",I67=""),"",D67*I67)
A68: NAC | B68: =IF(MOV_CC_NACIONAL!A68="","",MOV_CC_NACIONAL!A68) | C68: =IF(MOV_CC_NACIONAL!B68="","",MOV_CC_NACIONAL!B68) | D68: =IF(MOV_CC_NACIONAL!C68="","",MOV_CC_NACIONAL!C68) | E68: =IF(B68="","", "CLP") | F68: =IFERROR(__xludf.DUMMYFUNCTION("IF(C68="""","""", OR(REGEXMATCH(LOWER(C68),""cuota""), REGEXMATCH(C68,""\d+\s*/\s*\d+"")))"),"") | G68: =IFERROR(__xludf.DUMMYFUNCTION("IFERROR(VALUE(REGEXEXTRACT(C68,""(\d+)\s*/\s*\d+"")),"""")"),"") | H68: =IFERROR(__xludf.DUMMYFUNCTION("IFERROR(VALUE(REGEXEXTRACT(C68,""\d+\s*/\s*(\d+)"")),"""")"),"") | I68: =IF(OR(G68="",H68=""),"",H68-G68) | J68: =IF(OR(D68="",I68=""),"",D68*I68)
A69: NAC | B69: =IF(MOV_CC_NACIONAL!A69="","",MOV_CC_NACIONAL!A69) | C69: =IF(MOV_CC_NACIONAL!B69="","",MOV_CC_NACIONAL!B69) | D69: =IF(MOV_CC_NACIONAL!C69="","",MOV_CC_NACIONAL!C69) | E69: =IF(B69="","", "CLP") | F69: =IFERROR(__xludf.DUMMYFUNCTION("IF(C69="""","""", OR(REGEXMATCH(LOWER(C69),""cuota""), REGEXMATCH(C69,""\d+\s*/\s*\d+"")))"),"") | G69: =IFERROR(__xludf.DUMMYFUNCTION("IFERROR(VALUE(REGEXEXTRACT(C69,""(\d+)\s*/\s*\d+"")),"""")"),"") | H69: =IFERROR(__xludf.DUMMYFUNCTION("IFERROR(VALUE(REGEXEXTRACT(C69,""\d+\s*/\s*(\d+)"")),"""")"),"") | I69: =IF(OR(G69="",H69=""),"",H69-G69) | J69: =IF(OR(D69="",I69=""),"",D69*I69)
A70: NAC | B70: =IF(MOV_CC_NACIONAL!A70="","",MOV_CC_NACIONAL!A70) | C70: =IF(MOV_CC_NACIONAL!B70="","",MOV_CC_NACIONAL!B70) | D70: =IF(MOV_CC_NACIONAL!C70="","",MOV_CC_NACIONAL!C70) | E70: =IF(B70="","", "CLP") | F70: =IFERROR(__xludf.DUMMYFUNCTION("IF(C70="""","""", OR(REGEXMATCH(LOWER(C70),""cuota""), REGEXMATCH(C70,""\d+\s*/\s*\d+"")))"),"") | G70: =IFERROR(__xludf.DUMMYFUNCTION("IFERROR(VALUE(REGEXEXTRACT(C70,""(\d+)\s*/\s*\d+"")),"""")"),"") | H70: =IFERROR(__xludf.DUMMYFUNCTION("IFERROR(VALUE(REGEXEXTRACT(C70,""\d+\s*/\s*(\d+)"")),"""")"),"") | I70: =IF(OR(G70="",H70=""),"",H70-G70) | J70: =IF(OR(D70="",I70=""),"",D70*I70)
A71: NAC | B71: =IF(MOV_CC_NACIONAL!A71="","",MOV_CC_NACIONAL!A71) | C71: =IF(MOV_CC_NACIONAL!B71="","",MOV_CC_NACIONAL!B71) | D71: =IF(MOV_CC_NACIONAL!C71="","",MOV_CC_NACIONAL!C71) | E71: =IF(B71="","", "CLP") | F71: =IFERROR(__xludf.DUMMYFUNCTION("IF(C71="""","""", OR(REGEXMATCH(LOWER(C71),""cuota""), REGEXMATCH(C71,""\d+\s*/\s*\d+"")))"),"") | G71: =IFERROR(__xludf.DUMMYFUNCTION("IFERROR(VALUE(REGEXEXTRACT(C71,""(\d+)\s*/\s*\d+"")),"""")"),"") | H71: =IFERROR(__xludf.DUMMYFUNCTION("IFERROR(VALUE(REGEXEXTRACT(C71,""\d+\s*/\s*(\d+)"")),"""")"),"") | I71: =IF(OR(G71="",H71=""),"",H71-G71) | J71: =IF(OR(D71="",I71=""),"",D71*I71)
A72: NAC | B72: =IF(MOV_CC_NACIONAL!A72="","",MOV_CC_NACIONAL!A72) | C72: =IF(MOV_CC_NACIONAL!B72="","",MOV_CC_NACIONAL!B72) | D72: =IF(MOV_CC_NACIONAL!C72="","",MOV_CC_NACIONAL!C72) | E72: =IF(B72="","", "CLP") | F72: =IFERROR(__xludf.DUMMYFUNCTION("IF(C72="""","""", OR(REGEXMATCH(LOWER(C72),""cuota""), REGEXMATCH(C72,""\d+\s*/\s*\d+"")))"),"") | G72: =IFERROR(__xludf.DUMMYFUNCTION("IFERROR(VALUE(REGEXEXTRACT(C72,""(\d+)\s*/\s*\d+"")),"""")"),"") | H72: =IFERROR(__xludf.DUMMYFUNCTION("IFERROR(VALUE(REGEXEXTRACT(C72,""\d+\s*/\s*(\d+)"")),"""")"),"") | I72: =IF(OR(G72="",H72=""),"",H72-G72) | J72: =IF(OR(D72="",I72=""),"",D72*I72)
A73: NAC | B73: =IF(MOV_CC_NACIONAL!A73="","",MOV_CC_NACIONAL!A73) | C73: =IF(MOV_CC_NACIONAL!B73="","",MOV_CC_NACIONAL!B73) | D73: =IF(MOV_CC_NACIONAL!C73="","",MOV_CC_NACIONAL!C73) | E73: =IF(B73="","", "CLP") | F73: =IFERROR(__xludf.DUMMYFUNCTION("IF(C73="""","""", OR(REGEXMATCH(LOWER(C73),""cuota""), REGEXMATCH(C73,""\d+\s*/\s*\d+"")))"),"") | G73: =IFERROR(__xludf.DUMMYFUNCTION("IFERROR(VALUE(REGEXEXTRACT(C73,""(\d+)\s*/\s*\d+"")),"""")"),"") | H73: =IFERROR(__xludf.DUMMYFUNCTION("IFERROR(VALUE(REGEXEXTRACT(C73,""\d+\s*/\s*(\d+)"")),"""")"),"") | I73: =IF(OR(G73="",H73=""),"",H73-G73) | J73: =IF(OR(D73="",I73=""),"",D73*I73)
A74: NAC | B74: =IF(MOV_CC_NACIONAL!A74="","",MOV_CC_NACIONAL!A74) | C74: =IF(MOV_CC_NACIONAL!B74="","",MOV_CC_NACIONAL!B74) | D74: =IF(MOV_CC_NACIONAL!C74="","",MOV_CC_NACIONAL!C74) | E74: =IF(B74="","", "CLP") | F74: =IFERROR(__xludf.DUMMYFUNCTION("IF(C74="""","""", OR(REGEXMATCH(LOWER(C74),""cuota""), REGEXMATCH(C74,""\d+\s*/\s*\d+"")))"),"") | G74: =IFERROR(__xludf.DUMMYFUNCTION("IFERROR(VALUE(REGEXEXTRACT(C74,""(\d+)\s*/\s*\d+"")),"""")"),"") | H74: =IFERROR(__xludf.DUMMYFUNCTION("IFERROR(VALUE(REGEXEXTRACT(C74,""\d+\s*/\s*(\d+)"")),"""")"),"") | I74: =IF(OR(G74="",H74=""),"",H74-G74) | J74: =IF(OR(D74="",I74=""),"",D74*I74)
A75: NAC | B75: =IF(MOV_CC_NACIONAL!A75="","",MOV_CC_NACIONAL!A75) | C75: =IF(MOV_CC_NACIONAL!B75="","",MOV_CC_NACIONAL!B75) | D75: =IF(MOV_CC_NACIONAL!C75="","",MOV_CC_NACIONAL!C75) | E75: =IF(B75="","", "CLP") | F75: =IFERROR(__xludf.DUMMYFUNCTION("IF(C75="""","""", OR(REGEXMATCH(LOWER(C75),""cuota""), REGEXMATCH(C75,""\d+\s*/\s*\d+"")))"),"") | G75: =IFERROR(__xludf.DUMMYFUNCTION("IFERROR(VALUE(REGEXEXTRACT(C75,""(\d+)\s*/\s*\d+"")),"""")"),"") | H75: =IFERROR(__xludf.DUMMYFUNCTION("IFERROR(VALUE(REGEXEXTRACT(C75,""\d+\s*/\s*(\d+)"")),"""")"),"") | I75: =IF(OR(G75="",H75=""),"",H75-G75) | J75: =IF(OR(D75="",I75=""),"",D75*I75)
A76: NAC | B76: =IF(MOV_CC_NACIONAL!A76="","",MOV_CC_NACIONAL!A76) | C76: =IF(MOV_CC_NACIONAL!B76="","",MOV_CC_NACIONAL!B76) | D76: =IF(MOV_CC_NACIONAL!C76="","",MOV_CC_NACIONAL!C76) | E76: =IF(B76="","", "CLP") | F76: =IFERROR(__xludf.DUMMYFUNCTION("IF(C76="""","""", OR(REGEXMATCH(LOWER(C76),""cuota""), REGEXMATCH(C76,""\d+\s*/\s*\d+"")))"),"") | G76: =IFERROR(__xludf.DUMMYFUNCTION("IFERROR(VALUE(REGEXEXTRACT(C76,""(\d+)\s*/\s*\d+"")),"""")"),"") | H76: =IFERROR(__xludf.DUMMYFUNCTION("IFERROR(VALUE(REGEXEXTRACT(C76,""\d+\s*/\s*(\d+)"")),"""")"),"") | I76: =IF(OR(G76="",H76=""),"",H76-G76) | J76: =IF(OR(D76="",I76=""),"",D76*I76)
A77: NAC | B77: =IF(MOV_CC_NACIONAL!A77="","",MOV_CC_NACIONAL!A77) | C77: =IF(MOV_CC_NACIONAL!B77="","",MOV_CC_NACIONAL!B77) | D77: =IF(MOV_CC_NACIONAL!C77="","",MOV_CC_NACIONAL!C77) | E77: =IF(B77="","", "CLP") | F77: =IFERROR(__xludf.DUMMYFUNCTION("IF(C77="""","""", OR(REGEXMATCH(LOWER(C77),""cuota""), REGEXMATCH(C77,""\d+\s*/\s*\d+"")))"),"") | G77: =IFERROR(__xludf.DUMMYFUNCTION("IFERROR(VALUE(REGEXEXTRACT(C77,""(\d+)\s*/\s*\d+"")),"""")"),"") | H77: =IFERROR(__xludf.DUMMYFUNCTION("IFERROR(VALUE(REGEXEXTRACT(C77,""\d+\s*/\s*(\d+)"")),"""")"),"") | I77: =IF(OR(G77="",H77=""),"",H77-G77) | J77: =IF(OR(D77="",I77=""),"",D77*I77)
A78: NAC | B78: =IF(MOV_CC_NACIONAL!A78="","",MOV_CC_NACIONAL!A78) | C78: =IF(MOV_CC_NACIONAL!B78="","",MOV_CC_NACIONAL!B78) | D78: =IF(MOV_CC_NACIONAL!C78="","",MOV_CC_NACIONAL!C78) | E78: =IF(B78="","", "CLP") | F78: =IFERROR(__xludf.DUMMYFUNCTION("IF(C78="""","""", OR(REGEXMATCH(LOWER(C78),""cuota""), REGEXMATCH(C78,""\d+\s*/\s*\d+"")))"),"") | G78: =IFERROR(__xludf.DUMMYFUNCTION("IFERROR(VALUE(REGEXEXTRACT(C78,""(\d+)\s*/\s*\d+"")),"""")"),"") | H78: =IFERROR(__xludf.DUMMYFUNCTION("IFERROR(VALUE(REGEXEXTRACT(C78,""\d+\s*/\s*(\d+)"")),"""")"),"") | I78: =IF(OR(G78="",H78=""),"",H78-G78) | J78: =IF(OR(D78="",I78=""),"",D78*I78)
A79: NAC | B79: =IF(MOV_CC_NACIONAL!A79="","",MOV_CC_NACIONAL!A79) | C79: =IF(MOV_CC_NACIONAL!B79="","",MOV_CC_NACIONAL!B79) | D79: =IF(MOV_CC_NACIONAL!C79="","",MOV_CC_NACIONAL!C79) | E79: =IF(B79="","", "CLP") | F79: =IFERROR(__xludf.DUMMYFUNCTION("IF(C79="""","""", OR(REGEXMATCH(LOWER(C79),""cuota""), REGEXMATCH(C79,""\d+\s*/\s*\d+"")))"),"") | G79: =IFERROR(__xludf.DUMMYFUNCTION("IFERROR(VALUE(REGEXEXTRACT(C79,""(\d+)\s*/\s*\d+"")),"""")"),"") | H79: =IFERROR(__xludf.DUMMYFUNCTION("IFERROR(VALUE(REGEXEXTRACT(C79,""\d+\s*/\s*(\d+)"")),"""")"),"") | I79: =IF(OR(G79="",H79=""),"",H79-G79) | J79: =IF(OR(D79="",I79=""),"",D79*I79)
A80: NAC | B80: =IF(MOV_CC_NACIONAL!A80="","",MOV_CC_NACIONAL!A80) | C80: =IF(MOV_CC_NACIONAL!B80="","",MOV_CC_NACIONAL!B80) | D80: =IF(MOV_CC_NACIONAL!C80="","",MOV_CC_NACIONAL!C80) | E80: =IF(B80="","", "CLP") | F80: =IFERROR(__xludf.DUMMYFUNCTION("IF(C80="""","""", OR(REGEXMATCH(LOWER(C80),""cuota""), REGEXMATCH(C80,""\d+\s*/\s*\d+"")))"),"") | G80: =IFERROR(__xludf.DUMMYFUNCTION("IFERROR(VALUE(REGEXEXTRACT(C80,""(\d+)\s*/\s*\d+"")),"""")"),"") | H80: =IFERROR(__xludf.DUMMYFUNCTION("IFERROR(VALUE(REGEXEXTRACT(C80,""\d+\s*/\s*(\d+)"")),"""")"),"") | I80: =IF(OR(G80="",H80=""),"",H80-G80) | J80: =IF(OR(D80="",I80=""),"",D80*I80)
A81: NAC | B81: =IF(MOV_CC_NACIONAL!A81="","",MOV_CC_NACIONAL!A81) | C81: =IF(MOV_CC_NACIONAL!B81="","",MOV_CC_NACIONAL!B81) | D81: =IF(MOV_CC_NACIONAL!C81="","",MOV_CC_NACIONAL!C81) | E81: =IF(B81="","", "CLP") | F81: =IFERROR(__xludf.DUMMYFUNCTION("IF(C81="""","""", OR(REGEXMATCH(LOWER(C81),""cuota""), REGEXMATCH(C81,""\d+\s*/\s*\d+"")))"),"") | G81: =IFERROR(__xludf.DUMMYFUNCTION("IFERROR(VALUE(REGEXEXTRACT(C81,""(\d+)\s*/\s*\d+"")),"""")"),"") | H81: =IFERROR(__xludf.DUMMYFUNCTION("IFERROR(VALUE(REGEXEXTRACT(C81,""\d+\s*/\s*(\d+)"")),"""")"),"") | I81: =IF(OR(G81="",H81=""),"",H81-G81) | J81: =IF(OR(D81="",I81=""),"",D81*I81)
A82: NAC | B82: =IF(MOV_CC_NACIONAL!A82="","",MOV_CC_NACIONAL!A82) | C82: =IF(MOV_CC_NACIONAL!B82="","",MOV_CC_NACIONAL!B82) | D82: =IF(MOV_CC_NACIONAL!C82="","",MOV_CC_NACIONAL!C82) | E82: =IF(B82="","", "CLP") | F82: =IFERROR(__xludf.DUMMYFUNCTION("IF(C82="""","""", OR(REGEXMATCH(LOWER(C82),""cuota""), REGEXMATCH(C82,""\d+\s*/\s*\d+"")))"),"") | G82: =IFERROR(__xludf.DUMMYFUNCTION("IFERROR(VALUE(REGEXEXTRACT(C82,""(\d+)\s*/\s*\d+"")),"""")"),"") | H82: =IFERROR(__xludf.DUMMYFUNCTION("IFERROR(VALUE(REGEXEXTRACT(C82,""\d+\s*/\s*(\d+)"")),"""")"),"") | I82: =IF(OR(G82="",H82=""),"",H82-G82) | J82: =IF(OR(D82="",I82=""),"",D82*I82)
A83: NAC | B83: =IF(MOV_CC_NACIONAL!A83="","",MOV_CC_NACIONAL!A83) | C83: =IF(MOV_CC_NACIONAL!B83="","",MOV_CC_NACIONAL!B83) | D83: =IF(MOV_CC_NACIONAL!C83="","",MOV_CC_NACIONAL!C83) | E83: =IF(B83="","", "CLP") | F83: =IFERROR(__xludf.DUMMYFUNCTION("IF(C83="""","""", OR(REGEXMATCH(LOWER(C83),""cuota""), REGEXMATCH(C83,""\d+\s*/\s*\d+"")))"),"") | G83: =IFERROR(__xludf.DUMMYFUNCTION("IFERROR(VALUE(REGEXEXTRACT(C83,""(\d+)\s*/\s*\d+"")),"""")"),"") | H83: =IFERROR(__xludf.DUMMYFUNCTION("IFERROR(VALUE(REGEXEXTRACT(C83,""\d+\s*/\s*(\d+)"")),"""")"),"") | I83: =IF(OR(G83="",H83=""),"",H83-G83) | J83: =IF(OR(D83="",I83=""),"",D83*I83)
A84: NAC | B84: =IF(MOV_CC_NACIONAL!A84="","",MOV_CC_NACIONAL!A84) | C84: =IF(MOV_CC_NACIONAL!B84="","",MOV_CC_NACIONAL!B84) | D84: =IF(MOV_CC_NACIONAL!C84="","",MOV_CC_NACIONAL!C84) | E84: =IF(B84="","", "CLP") | F84: =IFERROR(__xludf.DUMMYFUNCTION("IF(C84="""","""", OR(REGEXMATCH(LOWER(C84),""cuota""), REGEXMATCH(C84,""\d+\s*/\s*\d+"")))"),"") | G84: =IFERROR(__xludf.DUMMYFUNCTION("IFERROR(VALUE(REGEXEXTRACT(C84,""(\d+)\s*/\s*\d+"")),"""")"),"") | H84: =IFERROR(__xludf.DUMMYFUNCTION("IFERROR(VALUE(REGEXEXTRACT(C84,""\d+\s*/\s*(\d+)"")),"""")"),"") | I84: =IF(OR(G84="",H84=""),"",H84-G84) | J84: =IF(OR(D84="",I84=""),"",D84*I84)
A85: NAC | B85: =IF(MOV_CC_NACIONAL!A85="","",MOV_CC_NACIONAL!A85) | C85: =IF(MOV_CC_NACIONAL!B85="","",MOV_CC_NACIONAL!B85) | D85: =IF(MOV_CC_NACIONAL!C85="","",MOV_CC_NACIONAL!C85) | E85: =IF(B85="","", "CLP") | F85: =IFERROR(__xludf.DUMMYFUNCTION("IF(C85="""","""", OR(REGEXMATCH(LOWER(C85),""cuota""), REGEXMATCH(C85,""\d+\s*/\s*\d+"")))"),"") | G85: =IFERROR(__xludf.DUMMYFUNCTION("IFERROR(VALUE(REGEXEXTRACT(C85,""(\d+)\s*/\s*\d+"")),"""")"),"") | H85: =IFERROR(__xludf.DUMMYFUNCTION("IFERROR(VALUE(REGEXEXTRACT(C85,""\d+\s*/\s*(\d+)"")),"""")"),"") | I85: =IF(OR(G85="",H85=""),"",H85-G85) | J85: =IF(OR(D85="",I85=""),"",D85*I85)
A86: NAC | B86: =IF(MOV_CC_NACIONAL!A86="","",MOV_CC_NACIONAL!A86) | C86: =IF(MOV_CC_NACIONAL!B86="","",MOV_CC_NACIONAL!B86) | D86: =IF(MOV_CC_NACIONAL!C86="","",MOV_CC_NACIONAL!C86) | E86: =IF(B86="","", "CLP") | F86: =IFERROR(__xludf.DUMMYFUNCTION("IF(C86="""","""", OR(REGEXMATCH(LOWER(C86),""cuota""), REGEXMATCH(C86,""\d+\s*/\s*\d+"")))"),"") | G86: =IFERROR(__xludf.DUMMYFUNCTION("IFERROR(VALUE(REGEXEXTRACT(C86,""(\d+)\s*/\s*\d+"")),"""")"),"") | H86: =IFERROR(__xludf.DUMMYFUNCTION("IFERROR(VALUE(REGEXEXTRACT(C86,""\d+\s*/\s*(\d+)"")),"""")"),"") | I86: =IF(OR(G86="",H86=""),"",H86-G86) | J86: =IF(OR(D86="",I86=""),"",D86*I86)
A87: NAC | B87: =IF(MOV_CC_NACIONAL!A87="","",MOV_CC_NACIONAL!A87) | C87: =IF(MOV_CC_NACIONAL!B87="","",MOV_CC_NACIONAL!B87) | D87: =IF(MOV_CC_NACIONAL!C87="","",MOV_CC_NACIONAL!C87) | E87: =IF(B87="","", "CLP") | F87: =IFERROR(__xludf.DUMMYFUNCTION("IF(C87="""","""", OR(REGEXMATCH(LOWER(C87),""cuota""), REGEXMATCH(C87,""\d+\s*/\s*\d+"")))"),"") | G87: =IFERROR(__xludf.DUMMYFUNCTION("IFERROR(VALUE(REGEXEXTRACT(C87,""(\d+)\s*/\s*\d+"")),"""")"),"") | H87: =IFERROR(__xludf.DUMMYFUNCTION("IFERROR(VALUE(REGEXEXTRACT(C87,""\d+\s*/\s*(\d+)"")),"""")"),"") | I87: =IF(OR(G87="",H87=""),"",H87-G87) | J87: =IF(OR(D87="",I87=""),"",D87*I87)
A88: NAC | B88: =IF(MOV_CC_NACIONAL!A88="","",MOV_CC_NACIONAL!A88) | C88: =IF(MOV_CC_NACIONAL!B88="","",MOV_CC_NACIONAL!B88) | D88: =IF(MOV_CC_NACIONAL!C88="","",MOV_CC_NACIONAL!C88) | E88: =IF(B88="","", "CLP") | F88: =IFERROR(__xludf.DUMMYFUNCTION("IF(C88="""","""", OR(REGEXMATCH(LOWER(C88),""cuota""), REGEXMATCH(C88,""\d+\s*/\s*\d+"")))"),"") | G88: =IFERROR(__xludf.DUMMYFUNCTION("IFERROR(VALUE(REGEXEXTRACT(C88,""(\d+)\s*/\s*\d+"")),"""")"),"") | H88: =IFERROR(__xludf.DUMMYFUNCTION("IFERROR(VALUE(REGEXEXTRACT(C88,""\d+\s*/\s*(\d+)"")),"""")"),"") | I88: =IF(OR(G88="",H88=""),"",H88-G88) | J88: =IF(OR(D88="",I88=""),"",D88*I88)
A89: NAC | B89: =IF(MOV_CC_NACIONAL!A89="","",MOV_CC_NACIONAL!A89) | C89: =IF(MOV_CC_NACIONAL!B89="","",MOV_CC_NACIONAL!B89) | D89: =IF(MOV_CC_NACIONAL!C89="","",MOV_CC_NACIONAL!C89) | E89: =IF(B89="","", "CLP") | F89: =IFERROR(__xludf.DUMMYFUNCTION("IF(C89="""","""", OR(REGEXMATCH(LOWER(C89),""cuota""), REGEXMATCH(C89,""\d+\s*/\s*\d+"")))"),"") | G89: =IFERROR(__xludf.DUMMYFUNCTION("IFERROR(VALUE(REGEXEXTRACT(C89,""(\d+)\s*/\s*\d+"")),"""")"),"") | H89: =IFERROR(__xludf.DUMMYFUNCTION("IFERROR(VALUE(REGEXEXTRACT(C89,""\d+\s*/\s*(\d+)"")),"""")"),"") | I89: =IF(OR(G89="",H89=""),"",H89-G89) | J89: =IF(OR(D89="",I89=""),"",D89*I89)
A90: NAC | B90: =IF(MOV_CC_NACIONAL!A90="","",MOV_CC_NACIONAL!A90) | C90: =IF(MOV_CC_NACIONAL!B90="","",MOV_CC_NACIONAL!B90) | D90: =IF(MOV_CC_NACIONAL!C90="","",MOV_CC_NACIONAL!C90) | E90: =IF(B90="","", "CLP") | F90: =IFERROR(__xludf.DUMMYFUNCTION("IF(C90="""","""", OR(REGEXMATCH(LOWER(C90),""cuota""), REGEXMATCH(C90,""\d+\s*/\s*\d+"")))"),"") | G90: =IFERROR(__xludf.DUMMYFUNCTION("IFERROR(VALUE(REGEXEXTRACT(C90,""(\d+)\s*/\s*\d+"")),"""")"),"") | H90: =IFERROR(__xludf.DUMMYFUNCTION("IFERROR(VALUE(REGEXEXTRACT(C90,""\d+\s*/\s*(\d+)"")),"""")"),"") | I90: =IF(OR(G90="",H90=""),"",H90-G90) | J90: =IF(OR(D90="",I90=""),"",D90*I90)
A91: NAC | B91: =IF(MOV_CC_NACIONAL!A91="","",MOV_CC_NACIONAL!A91) | C91: =IF(MOV_CC_NACIONAL!B91="","",MOV_CC_NACIONAL!B91) | D91: =IF(MOV_CC_NACIONAL!C91="","",MOV_CC_NACIONAL!C91) | E91: =IF(B91="","", "CLP") | F91: =IFERROR(__xludf.DUMMYFUNCTION("IF(C91="""","""", OR(REGEXMATCH(LOWER(C91),""cuota""), REGEXMATCH(C91,""\d+\s*/\s*\d+"")))"),"") | G91: =IFERROR(__xludf.DUMMYFUNCTION("IFERROR(VALUE(REGEXEXTRACT(C91,""(\d+)\s*/\s*\d+"")),"""")"),"") | H91: =IFERROR(__xludf.DUMMYFUNCTION("IFERROR(VALUE(REGEXEXTRACT(C91,""\d+\s*/\s*(\d+)"")),"""")"),"") | I91: =IF(OR(G91="",H91=""),"",H91-G91) | J91: =IF(OR(D91="",I91=""),"",D91*I91)
A92: NAC | B92: =IF(MOV_CC_NACIONAL!A92="","",MOV_CC_NACIONAL!A92) | C92: =IF(MOV_CC_NACIONAL!B92="","",MOV_CC_NACIONAL!B92) | D92: =IF(MOV_CC_NACIONAL!C92="","",MOV_CC_NACIONAL!C92) | E92: =IF(B92="","", "CLP") | F92: =IFERROR(__xludf.DUMMYFUNCTION("IF(C92="""","""", OR(REGEXMATCH(LOWER(C92),""cuota""), REGEXMATCH(C92,""\d+\s*/\s*\d+"")))"),"") | G92: =IFERROR(__xludf.DUMMYFUNCTION("IFERROR(VALUE(REGEXEXTRACT(C92,""(\d+)\s*/\s*\d+"")),"""")"),"") | H92: =IFERROR(__xludf.DUMMYFUNCTION("IFERROR(VALUE(REGEXEXTRACT(C92,""\d+\s*/\s*(\d+)"")),"""")"),"") | I92: =IF(OR(G92="",H92=""),"",H92-G92) | J92: =IF(OR(D92="",I92=""),"",D92*I92)
A93: NAC | B93: =IF(MOV_CC_NACIONAL!A93="","",MOV_CC_NACIONAL!A93) | C93: =IF(MOV_CC_NACIONAL!B93="","",MOV_CC_NACIONAL!B93) | D93: =IF(MOV_CC_NACIONAL!C93="","",MOV_CC_NACIONAL!C93) | E93: =IF(B93="","", "CLP") | F93: =IFERROR(__xludf.DUMMYFUNCTION("IF(C93="""","""", OR(REGEXMATCH(LOWER(C93),""cuota""), REGEXMATCH(C93,""\d+\s*/\s*\d+"")))"),"") | G93: =IFERROR(__xludf.DUMMYFUNCTION("IFERROR(VALUE(REGEXEXTRACT(C93,""(\d+)\s*/\s*\d+"")),"""")"),"") | H93: =IFERROR(__xludf.DUMMYFUNCTION("IFERROR(VALUE(REGEXEXTRACT(C93,""\d+\s*/\s*(\d+)"")),"""")"),"") | I93: =IF(OR(G93="",H93=""),"",H93-G93) | J93: =IF(OR(D93="",I93=""),"",D93*I93)
A94: NAC | B94: =IF(MOV_CC_NACIONAL!A94="","",MOV_CC_NACIONAL!A94) | C94: =IF(MOV_CC_NACIONAL!B94="","",MOV_CC_NACIONAL!B94) | D94: =IF(MOV_CC_NACIONAL!C94="","",MOV_CC_NACIONAL!C94) | E94: =IF(B94="","", "CLP") | F94: =IFERROR(__xludf.DUMMYFUNCTION("IF(C94="""","""", OR(REGEXMATCH(LOWER(C94),""cuota""), REGEXMATCH(C94,""\d+\s*/\s*\d+"")))"),"") | G94: =IFERROR(__xludf.DUMMYFUNCTION("IFERROR(VALUE(REGEXEXTRACT(C94,""(\d+)\s*/\s*\d+"")),"""")"),"") | H94: =IFERROR(__xludf.DUMMYFUNCTION("IFERROR(VALUE(REGEXEXTRACT(C94,""\d+\s*/\s*(\d+)"")),"""")"),"") | I94: =IF(OR(G94="",H94=""),"",H94-G94) | J94: =IF(OR(D94="",I94=""),"",D94*I94)
A95: NAC | B95: =IF(MOV_CC_NACIONAL!A95="","",MOV_CC_NACIONAL!A95) | C95: =IF(MOV_CC_NACIONAL!B95="","",MOV_CC_NACIONAL!B95) | D95: =IF(MOV_CC_NACIONAL!C95="","",MOV_CC_NACIONAL!C95) | E95: =IF(B95="","", "CLP") | F95: =IFERROR(__xludf.DUMMYFUNCTION("IF(C95="""","""", OR(REGEXMATCH(LOWER(C95),""cuota""), REGEXMATCH(C95,""\d+\s*/\s*\d+"")))"),"") | G95: =IFERROR(__xludf.DUMMYFUNCTION("IFERROR(VALUE(REGEXEXTRACT(C95,""(\d+)\s*/\s*\d+"")),"""")"),"") | H95: =IFERROR(__xludf.DUMMYFUNCTION("IFERROR(VALUE(REGEXEXTRACT(C95,""\d+\s*/\s*(\d+)"")),"""")"),"") | I95: =IF(OR(G95="",H95=""),"",H95-G95) | J95: =IF(OR(D95="",I95=""),"",D95*I95)
A96: NAC | B96: =IF(MOV_CC_NACIONAL!A96="","",MOV_CC_NACIONAL!A96) | C96: =IF(MOV_CC_NACIONAL!B96="","",MOV_CC_NACIONAL!B96) | D96: =IF(MOV_CC_NACIONAL!C96="","",MOV_CC_NACIONAL!C96) | E96: =IF(B96="","", "CLP") | F96: =IFERROR(__xludf.DUMMYFUNCTION("IF(C96="""","""", OR(REGEXMATCH(LOWER(C96),""cuota""), REGEXMATCH(C96,""\d+\s*/\s*\d+"")))"),"") | G96: =IFERROR(__xludf.DUMMYFUNCTION("IFERROR(VALUE(REGEXEXTRACT(C96,""(\d+)\s*/\s*\d+"")),"""")"),"") | H96: =IFERROR(__xludf.DUMMYFUNCTION("IFERROR(VALUE(REGEXEXTRACT(C96,""\d+\s*/\s*(\d+)"")),"""")"),"") | I96: =IF(OR(G96="",H96=""),"",H96-G96) | J96: =IF(OR(D96="",I96=""),"",D96*I96)
A97: NAC | B97: =IF(MOV_CC_NACIONAL!A97="","",MOV_CC_NACIONAL!A97) | C97: =IF(MOV_CC_NACIONAL!B97="","",MOV_CC_NACIONAL!B97) | D97: =IF(MOV_CC_NACIONAL!C97="","",MOV_CC_NACIONAL!C97) | E97: =IF(B97="","", "CLP") | F97: =IFERROR(__xludf.DUMMYFUNCTION("IF(C97="""","""", OR(REGEXMATCH(LOWER(C97),""cuota""), REGEXMATCH(C97,""\d+\s*/\s*\d+"")))"),"") | G97: =IFERROR(__xludf.DUMMYFUNCTION("IFERROR(VALUE(REGEXEXTRACT(C97,""(\d+)\s*/\s*\d+"")),"""")"),"") | H97: =IFERROR(__xludf.DUMMYFUNCTION("IFERROR(VALUE(REGEXEXTRACT(C97,""\d+\s*/\s*(\d+)"")),"""")"),"") | I97: =IF(OR(G97="",H97=""),"",H97-G97) | J97: =IF(OR(D97="",I97=""),"",D97*I97)
A98: NAC | B98: =IF(MOV_CC_NACIONAL!A98="","",MOV_CC_NACIONAL!A98) | C98: =IF(MOV_CC_NACIONAL!B98="","",MOV_CC_NACIONAL!B98) | D98: =IF(MOV_CC_NACIONAL!C98="","",MOV_CC_NACIONAL!C98) | E98: =IF(B98="","", "CLP") | F98: =IFERROR(__xludf.DUMMYFUNCTION("IF(C98="""","""", OR(REGEXMATCH(LOWER(C98),""cuota""), REGEXMATCH(C98,""\d+\s*/\s*\d+"")))"),"") | G98: =IFERROR(__xludf.DUMMYFUNCTION("IFERROR(VALUE(REGEXEXTRACT(C98,""(\d+)\s*/\s*\d+"")),"""")"),"") | H98: =IFERROR(__xludf.DUMMYFUNCTION("IFERROR(VALUE(REGEXEXTRACT(C98,""\d+\s*/\s*(\d+)"")),"""")"),"") | I98: =IF(OR(G98="",H98=""),"",H98-G98) | J98: =IF(OR(D98="",I98=""),"",D98*I98)
A99: NAC | B99: =IF(MOV_CC_NACIONAL!A99="","",MOV_CC_NACIONAL!A99) | C99: =IF(MOV_CC_NACIONAL!B99="","",MOV_CC_NACIONAL!B99) | D99: =IF(MOV_CC_NACIONAL!C99="","",MOV_CC_NACIONAL!C99) | E99: =IF(B99="","", "CLP") | F99: =IFERROR(__xludf.DUMMYFUNCTION("IF(C99="""","""", OR(REGEXMATCH(LOWER(C99),""cuota""), REGEXMATCH(C99,""\d+\s*/\s*\d+"")))"),"") | G99: =IFERROR(__xludf.DUMMYFUNCTION("IFERROR(VALUE(REGEXEXTRACT(C99,""(\d+)\s*/\s*\d+"")),"""")"),"") | H99: =IFERROR(__xludf.DUMMYFUNCTION("IFERROR(VALUE(REGEXEXTRACT(C99,""\d+\s*/\s*(\d+)"")),"""")"),"") | I99: =IF(OR(G99="",H99=""),"",H99-G99) | J99: =IF(OR(D99="",I99=""),"",D99*I99)
A100: NAC | B100: =IF(MOV_CC_NACIONAL!A100="","",MOV_CC_NACIONAL!A100) | C100: =IF(MOV_CC_NACIONAL!B100="","",MOV_CC_NACIONAL!B100) | D100: =IF(MOV_CC_NACIONAL!C100="","",MOV_CC_NACIONAL!C100) | E100: =IF(B100="","", "CLP") | F100: =IFERROR(__xludf.DUMMYFUNCTION("IF(C100="""","""", OR(REGEXMATCH(LOWER(C100),""cuota""), REGEXMATCH(C100,""\d+\s*/\s*\d+"")))"),"") | G100: =IFERROR(__xludf.DUMMYFUNCTION("IFERROR(VALUE(REGEXEXTRACT(C100,""(\d+)\s*/\s*\d+"")),"""")"),"") | H100: =IFERROR(__xludf.DUMMYFUNCTION("IFERROR(VALUE(REGEXEXTRACT(C100,""\d+\s*/\s*(\d+)"")),"""")"),"") | I100: =IF(OR(G100="",H100=""),"",H100-G100) | J100: =IF(OR(D100="",I100=""),"",D100*I100)
...

Sheet MOV_CC_NACIONAL
A1: Fecha | B1: Descripcion | C1: Monto_CLP
A2: 25-02-2026 | B2: UBER RIDES UBER RIDES LAS CO | C2: 12931
A3: 25-02-2026 | B3: CHILE DOGS LTDA CON CO | C3: 46990
A4: 24-02-2026 | B4: PAYU *FLIXBUS SANTIA | C4: 6499
A5: 24-02-2026 | B5: PAYU *UBER TRIP SANTIA | C5: 12600
A6: 24-02-2026 | B6: PAYU *FLIXBUS SANTIA | C6: 4999
A7: 24-02-2026 | B7: PAYU *UBER TRIP SANTIA | C7: 6078
A8: 23-02-2026 | B8: MERCADOPAGO*MERCADO COMPRAS | C8: 11980
A9: 23-02-2026 | B9: PAYU *FLIXBUS COMPRAS | C9: 7699
A10: 21-02-2026 | B10: LOCAL EU 15 NORTE COMPRAS | C10: 19990
A11: 21-02-2026 | B11: MORA LOUTIT SWEET S COMPRAS | C11: 11550
A12: 23-02-2026 | B12: MERCADOPAGO*MERCADO 03 CTAS-INT: 0 | C12: 86791
A13: 21-02-2026 | B13: MERPAGO*OPTICASLUXO HUE CC 01-06 | C13: 41030
... A16: 21-01-2026 | B16: MP *MERCADO LIB SAN CC 02-03 | C16: 15295
A17: 46235 | B17: MP *MERCADO LIB SAN CC 03-06 | C17: 20813
A18: 46204 | B18: MERCADOPAGO*STREETD LAS CF 02-06 | C18: 10997
A19: 21-12-2025 | B19: MERPAGO*MERCADOLIBR LAS CC 03-03 | C19: 17538
A20: 28-11-2025 | B20: CIC HOGAR TIENDA CO CON CC 04-06 | C20: 20496
A21: 28-08-2025 | B21: MERCADOPAGO*MONSTER LAS CF 06-06 | C21: 14667

Sheet MOV_CC_INTL
A1: Fecha | B1: Descripcion | C1: Monto_USD
A2: 22-02-2026 | B2: EMBY PREMIERE COMPRAS INT.VI | C2: 4.99
A3: 20-02-2026 | B3: CLAUDE.AI SUBSCRIPT COMPRAS INT.VI | C3: 102.76
A4: 19-02-2026 | B4: APPLE.COM/BILL COMPRAS INT.VI | C4: 12.48

Sheet RESUMEN
A1: Concepto | B1: Total
A2: Compras Nacional (solo >0) | B2: =SUMIF(MOV_NAC_AUTO!C:C,">0") -> 420514
A3: Compras Internacional CLP (solo >0) | B3: =SUMIF(MOV_INTL_AUTO!E:E,">0") -> 114218.5
A4: Pagos/Abonos Nacional (abs <0) | B4: =ABS(SUMIF(MOV_NAC_AUTO!C:C,"<0")) -> 0
A5: Pagos/Abonos Intl CLP (abs <0) | B5: =ABS(SUMIF(MOV_INTL_AUTO!E:E,"<0")) -> 0
A6: Net Nacional (compras - pagos) | B6: =B2-B4 -> 420514
A7: Net Intl CLP (compras - pagos) | B7: =B3-B5 -> 114218.5

Sheet PROYECCION
A1: Concepto | B1: Valor
A2: Ingreso | B2: =CONFIG!B2 -> 3000000
A3: Costos Fijos | B3: =CONFIG!B3+CONFIG!B4 -> 1300000
A4: Compras Nacional | B4: =RESUMEN!B2 -> 420514
A5: Compras Internacional | B5: =RESUMEN!B3 -> 114218.5
A6: Claude Plan | B6: =CONFIG!B6 -> 0
A7: Margen Disponible | B7: =B2-(B3+B4+B5+B6) -> 1165267.5
A8: Total a gastar (fijos+compras+Claude) | B8: =B3+B4+B5+B6 -> 1834732.5
A9: Ahorro sugerido (si hay margen) | B9: =MAX(0,MIN(500000,B7-300000)) -> 500000

Sheet BURN_CURVE
A1: Dia | B1: Liquidez Estimada
A2: 1 | B2: =PROYECCION!B7/30*A2 -> 38842.25
A3: 2 | B3: =PROYECCION!B7/30*A3 -> 77684.5
A4: 3 | B4: =PROYECCION!B7/30*A4 -> 116526.75
A5: 4 | B5: =PROYECCION!B7/30*A5 -> 155369
A6: 5 | B6: =PROYECCION!B7/30*A6 -> 194211.25
A7: 6 | B7: =PROYECCION!B7/30*A7 -> 233053.5
A8: 7 | B8: =PROYECCION!B7/30*A8 -> 271895.75
A9: 8 | B9: =PROYECCION!B7/30*A9 -> 310738
A10: 9 | B10: =PROYECCION!B7/30*A10 -> 349580.25
A11: 10 | B11: =PROYECCION!B7/30*A11 -> 388422.5
A12: 11 | B12: =PROYECCION!B7/30*A12 -> 427264.75
A13: 12 | B13: =PROYECCION!B7/30*A13 -> 466107
A14: 13 | B14: =PROYECCION!B7/30*A14 -> 504949.25
A15: 14 | B15: =PROYECCION!B7/30*A15 -> 543791.5
A16: 15 | B16: =PROYECCION!B7/30*A16 -> 582633.75
A17: 16 | B17: =PROYECCION!B7/30*A17 -> 621476
A18: 17 | B18: =PROYECCION!B7/30*A18 -> 660318.25
A19: 18 | B19: =PROYECCION!B7/30*A19 -> 699160.5
A20: 19 | B20: =PROYECCION!B7/30*A20 -> 738002.75
A21: 20 | B21: =PROYECCION!B7/30*A21 -> 776845
A22: 21 | B22: =PROYECCION!B7/30*A22 -> 815687.25
A23: 22 | B23: =PROYECCION!B7/30*A23 -> 854529.5
A24: 23 | B24: =PROYECCION!B7/30*A24 -> 893371.75
A25: 24 | B25: =PROYECCION!B7/30*A25 -> 932214
A26: 25 | B26: =PROYECCION!B7/30*A26 -> 971056.25
A27: 26 | B27: =PROYECCION!B7/30*A27 -> 1009898.5
A28: 27 | B28: =PROYECCION!B7/30*A28 -> 1048740.8
A29: 28 | B29: =PROYECCION!B7/30*A29 -> 1087583
A30: 29 | B30: =PROYECCION!B7/30*A30 -> 1126425.2
A31: 30 | B31: =PROYECCION!B7/30*A31 -> 1165267.5

Sheet CATEGORIAS
A1: Tipo | B1: Keyword (contains) | C1: Categoria
A2: NAC | B2: uber | C2: Food & Transport
A3: NAC | B3: payu *uber | C3: Food & Transport
A4: NAC | B4: kfc | C4: Food & Transport
A5: NAC | B5: cinemark | C5: Food & Transport
A6: NAC | B6: pethouse | C6: Pets & Health
A7: NAC | B7: superzoo | C7: Pets & Health
A8: NAC | B8: servicios medicos | C8: Pets & Health
A9: NAC | B9: farm | C9: Pharmacy
A10: NAC | B10: cruz verde | C10: Pharmacy
A11: NAC | B11: mercado | C11: Shopping
A12: NAC | B12: mercadopago | C12: Shopping
... A21: INTL | B21: battle | C21: Gaming

Sheet MOV_NAC_AUTO
A1: Fecha | B1: Descripcion | C1: Monto_CLP | D1: Categoria
A2: =IF(MOV_CC_NACIONAL!A2="","",MOV_CC_NACIONAL!A2) -> 25-02-2026 | B2: =IF(MOV_CC_NACIONAL!B2="","",MOV_CC_NACIONAL!B2) -> UBER RIDES UBER RIDES LAS CO | C2: =IF(MOV_CC_NACIONAL!C2="","",MOV_CC_NACIONAL!C2) -> 12931 | D2: =IF(ISNUMBER(SEARCH("uber",LOWER(B2))),"Food & Transport",IF(ISNUMBER(SEARCH("payu *uber",LOWER(B2))),"Food & Transport",IF(ISNUMBER(SEARCH("kfc",LOWER(B2))),"Food & Transport",IF(ISNUMBER(SEARCH("cinemark",LOWER(B2))),"Food & Transport",IF(ISNUMBER(SEARCH("pethouse",LOWER(B2))),"Pets & Health",IF(ISNUMBER(SEARCH("superzoo",LOWER(B2))),"Pets & Health",IF(ISNUMBER(SEARCH("servicios medicos",LOWER(B2))),"Pets & Health",IF(ISNUMBER(SEARCH("farm",LOWER(B2))),"Pharmacy",IF(ISNUMBER(SEARCH("cruz verde",LOWER(B2))),"Pharmacy",IF(ISNUMBER(SEARCH("mercado",LOWER(B2))),"Shopping",IF(ISNUMBER(SEARCH("mercadopago",LOWER(B2))),"Shopping",IF(ISNUMBER(SEARCH("ikea",LOWER(B2))),"Shopping",IF(ISNUMBER(SEARCH("spotify",LOWER(B2))),"Subscriptions","Other"))))))))))))) -> Food & Transport
A3: =IF(MOV_CC_NACIONAL!A3="","",MOV_CC_NACIONAL!A3) -> 25-02-2026 | B3: =IF(MOV_CC_NACIONAL!B3="","",MOV_CC_NACIONAL!B3) -> CHILE DOGS LTDA CON CO | C3: =IF(MOV_CC_NACIONAL!C3="","",MOV_CC_NACIONAL!C3) -> 46990 | D3: =IF(ISNUMBER(SEARCH("uber",LOWER(B3))),"Food & Transport",IF(ISNUMBER(SEARCH("payu *uber",LOWER(B3))),"Food & Transport",IF(ISNUMBER(SEARCH("kfc",LOWER(B3))),"Food & Transport",IF(ISNUMBER(SEARCH("cinemark",LOWER(B3))),"Food & Transport",IF(ISNUMBER(SEARCH("pethouse",LOWER(B3))),"Pets & Health",IF(ISNUMBER(SEARCH("superzoo",LOWER(B3))),"Pets & Health",IF(ISNUMBER(SEARCH("servicios medicos",LOWER(B3))),"Pets & Health",IF(ISNUMBER(SEARCH("farm",LOWER(B3))),"Pharmacy",IF(ISNUMBER(SEARCH("cruz verde",LOWER(B3))),"Pharmacy",IF(ISNUMBER(SEARCH("mercado",LOWER(B3))),"Shopping",IF(ISNUMBER(SEARCH("mercadopago",LOWER(B3))),"Shopping",IF(ISNUMBER(SEARCH("ikea",LOWER(B3))),"Shopping",IF(ISNUMBER(SEARCH("spotify",LOWER(B3))),"Subscriptions","Other"))))))))))))) -> Other
A4: =IF(MOV_CC_NACIONAL!A4="","",MOV_CC_NACIONAL!A4) -> 24-02-2026 | B4: =IF(MOV_CC_NACIONAL!B4="","",MOV_CC_NACIONAL!B4) -> PAYU *FLIXBUS SANTIA | C4: =IF(MOV_CC_NACIONAL!C4="","",MOV_CC_NACIONAL!C4) -> 6499 | D4: =IF(ISNUMBER(SEARCH("uber",LOWER(B4))),"Food & Transport",IF(ISNUMBER(SEARCH("payu *uber",LOWER(B4))),"Food & Transport",IF(ISNUMBER(SEARCH("kfc",LOWER(B4))),"Food & Transport",IF(ISNUMBER(SEARCH("cinemark",LOWER(B4))),"Food & Transport",IF(ISNUMBER(SEARCH("pethouse",LOWER(B4))),"Pets & Health",IF(ISNUMBER(SEARCH("superzoo",LOWER(B4))),"Pets & Health",IF(ISNUMBER(SEARCH("servicios medicos",LOWER(B4))),"Pets & Health",IF(ISNUMBER(SEARCH("farm",LOWER(B4))),"Pharmacy",IF(ISNUMBER(SEARCH("cruz verde",LOWER(B4))),"Pharmacy",IF(ISNUMBER(SEARCH("mercado",LOWER(B4))),"Shopping",IF(ISNUMBER(SEARCH("mercadopago",LOWER(B4))),"Shopping",IF(ISNUMBER(SEARCH("ikea",LOWER(B4))),"Shopping",IF(ISNUMBER(SEARCH("spotify",LOWER(B4))),"Subscriptions","Other"))))))))))))) -> Other
A5: =IF(MOV_CC_NACIONAL!A5="","",MOV_CC_NACIONAL!A5) -> 24-02-2026 | B5: =IF(MOV_CC_NACIONAL!B5="","",MOV_CC_NACIONAL!B5) -> PAYU *UBER TRIP SANTIA | C5: =IF(MOV_CC_NACIONAL!C5="","",MOV_CC_NACIONAL!C5) -> 12600 | D5: =IF(ISNUMBER(SEARCH("uber",LOWER(B5))),"Food & Transport",IF(ISNUMBER(SEARCH("payu *uber",LOWER(B5))),"Food & Transport",IF(ISNUMBER(SEARCH("kfc",LOWER(B5))),"Food & Transport",IF(ISNUMBER(SEARCH("cinemark",LOWER(B5))),"Food & Transport",IF(ISNUMBER(SEARCH("pethouse",LOWER(B5))),"Pets & Health",IF(ISNUMBER(SEARCH("superzoo",LOWER(B5))),"Pets & Health",IF(ISNUMBER(SEARCH("servicios medicos",LOWER(B5))),"Pets & Health",IF(ISNUMBER(SEARCH("farm",LOWER(B5))),"Pharmacy",IF(ISNUMBER(SEARCH("cruz verde",LOWER(B5))),"Pharmacy",IF(ISNUMBER(SEARCH("mercado",LOWER(B5))),"Shopping",IF(ISNUMBER(SEARCH("mercadopago",LOWER(B5))),"Shopping",IF(ISNUMBER(SEARCH("ikea",LOWER(B5))),"Shopping",IF(ISNUMBER(SEARCH("spotify",LOWER(B5))),"Subscriptions","Other"))))))))))))) -> Food & Transport
A6: =IF(MOV_CC_NACIONAL!A6="","",MOV_CC_NACIONAL!A6) -> 24-02-2026 | B6: =IF(MOV_CC_NACIONAL!B6="","",MOV_CC_NACIONAL!B6) -> PAYU *FLIXBUS SANTIA | C6: =IF(MOV_CC_NACIONAL!C6="","",MOV_CC_NACIONAL!C6) -> 4999 | D6: =IF(ISNUMBER(SEARCH("uber",LOWER(B6))),"Food & Transport",IF(ISNUMBER(SEARCH("payu *uber",LOWER(B6))),"Food & Transport",IF(ISNUMBER(SEARCH("kfc",LOWER(B6))),"Food & Transport",IF(ISNUMBER(SEARCH("cinemark",LOWER(B6))),"Food & Transport",IF(ISNUMBER(SEARCH("pethouse",LOWER(B6))),"Pets & Health",IF(ISNUMBER(SEARCH("superzoo",LOWER(B6))),"Pets & Health",IF(ISNUMBER(SEARCH("servicios medicos",LOWER(B6))),"Pets & Health",IF(ISNUMBER(SEARCH("farm",LOWER(B6))),"Pharmacy",IF(ISNUMBER(SEARCH("cruz verde",LOWER(B6))),"Pharmacy",IF(ISNUMBER(SEARCH("mercado",LOWER(B6))),"Shopping",IF(ISNUMBER(SEARCH("mercadopago",LOWER(B6))),"Shopping",IF(ISNUMBER(SEARCH("ikea",LOWER(B6))),"Shopping",IF(ISNUMBER(SEARCH("spotify",LOWER(B6))),"Subscriptions","Other"))))))))))))) -> Other
A7: =IF(MOV_CC_NACIONAL!A7="","",MOV_CC_NACIONAL!A7) -> 24-02-2026 | B7: =IF(MOV_CC_NACIONAL!B7="","",MOV_CC_NACIONAL!B7) -> PAYU *UBER TRIP SANTIA | C7: =IF(MOV_CC_NACIONAL!C7="","",MOV_CC_NACIONAL!C7) -> 6078 | D7: =IF(ISNUMBER(SEARCH("uber",LOWER(B7))),"Food & Transport",IF(ISNUMBER(SEARCH("payu *uber",LOWER(B7))),"Food & Transport",IF(ISNUMBER(SEARCH("kfc",LOWER(B7))),"Food & Transport",IF(ISNUMBER(SEARCH("cinemark",LOWER(B7))),"Food & Transport",IF(ISNUMBER(SEARCH("pethouse",LOWER(B7))),"Pets & Health",IF(ISNUMBER(SEARCH("superzoo",LOWER(B7))),"Pets & Health",IF(ISNUMBER(SEARCH("servicios medicos",LOWER(B7))),"Pets & Health",IF(ISNUMBER(SEARCH("farm",LOWER(B7))),"Pharmacy",IF(ISNUMBER(SEARCH("cruz verde",LOWER(B7))),"Pharmacy",IF(ISNUMBER(SEARCH("mercado",LOWER(B7))),"Shopping",IF(ISNUMBER(SEARCH("mercadopago",LOWER(B7))),"Shopping",IF(ISNUMBER(SEARCH("ikea",LOWER(B7))),"Shopping",IF(ISNUMBER(SEARCH("spotify",LOWER(B7))),"Subscriptions","Other"))))))))))))) -> Food & Transport
A8: =IF(MOV_CC_NACIONAL!A8="","",MOV_CC_NACIONAL!A8) -> 23-02-2026 | B8: =IF(MOV_CC_NACIONAL!B8="","",MOV_CC_NACIONAL!B8) -> MERCADOPAGO*MERCADO COMPRAS | C8: =IF(MOV_CC_NACIONAL!C8="","",MOV_CC_NACIONAL!C8) -> 11980 | D8: =IF(ISNUMBER(SEARCH("uber",LOWER(B8))),"Food & Transport",IF(ISNUMBER(SEARCH("payu *uber",LOWER(B8))),"Food & Transport",IF(ISNUMBER(SEARCH("kfc",LOWER(B8))),"Food & Transport",IF(ISNUMBER(SEARCH("cinemark",LOWER(B8))),"Food & Transport",IF(ISNUMBER(SEARCH("pethouse",LOWER(B8))),"Pets & Health",IF(ISNUMBER(SEARCH("superzoo",LOWER(B8))),"Pets & Health",IF(ISNUMBER(SEARCH("servicios medicos",LOWER(B8))),"Pets & Health",IF(ISNUMBER(SEARCH("farm",LOWER(B8))),"Pharmacy",IF(ISNUMBER(SEARCH("cruz verde",LOWER(B8))),"Pharmacy",IF(ISNUMBER(SEARCH("mercado",LOWER(B8))),"Shopping",IF(ISNUMBER(SEARCH("mercadopago",LOWER(B8))),"Shopping",IF(ISNUMBER(SEARCH("ikea",LOWER(B8))),"Shopping",IF(ISNUMBER(SEARCH("spotify",LOWER(B8))),"Subscriptions","Other"))))))))))))) -> Shopping
A9: =IF(MOV_CC_NACIONAL!A9="","",MOV_CC_NACIONAL!A9) -> 23-02-2026 | B9: =IF(MOV_CC_NACIONAL!B9="","",MOV_CC_NACIONAL!B9) -> PAYU *FLIXBUS COMPRAS | C9: =IF(MOV_CC_NACIONAL!C9="","",MOV_CC_NACIONAL!C9) -> 7699 | D9: =IF(ISNUMBER(SEARCH("uber",LOWER(B9))),"Food & Transport",IF(ISNUMBER(SEARCH("payu *uber",LOWER(B9))),"Food & Transport",IF(ISNUMBER(SEARCH("kfc",LOWER(B9))),"Food & Transport",IF(ISNUMBER(SEARCH("cinemark",LOWER(B9))),"Food & Transport",IF(ISNUMBER(SEARCH("pethouse",LOWER(B9))),"Pets & Health",IF(ISNUMBER(SEARCH("superzoo",LOWER(B9))),"Pets & Health",IF(ISNUMBER(SEARCH("servicios medicos",LOWER(B9))),"Pets & Health",IF(ISNUMBER(SEARCH("farm",LOWER(B9))),"Pharmacy",IF(ISNUMBER(SEARCH("cruz verde",LOWER(B9))),"Pharmacy",IF(ISNUMBER(SEARCH("mercado",LOWER(B9))),"Shopping",IF(ISNUMBER(SEARCH("mercadopago",LOWER(B9))),"Shopping",IF(ISNUMBER(SEARCH("ikea",LOWER(B9))),"Shopping",IF(ISNUMBER(SEARCH("spotify",LOWER(B9))),"Subscriptions","Other"))))))))))))) -> Other
A10: =IF(MOV_CC_NACIONAL!A10="","",MOV_CC_NACIONAL!A10) -> 21-02-2026 | B10: =IF(MOV_CC_NACIONAL!B10="","",MOV_CC_NACIONAL!B10) -> LOCAL EU 15 NORTE COMPRAS | C10: =IF(MOV_CC_NACIONAL!C10="","",MOV_CC_NACIONAL!C10) -> 19990 | D10: =IF(ISNUMBER(SEARCH("uber",LOWER(B10))),"Food & Transport",IF(ISNUMBER(SEARCH("payu *uber",LOWER(B10))),"Food & Transport",IF(ISNUMBER(SEARCH("kfc",LOWER(B10))),"Food & Transport",IF(ISNUMBER(SEARCH("cinemark",LOWER(B10))),"Food & Transport",IF(ISNUMBER(SEARCH("pethouse",LOWER(B10))),"Pets & Health",IF(ISNUMBER(SEARCH("superzoo",LOWER(B10))),"Pets & Health",IF(ISNUMBER(SEARCH("servicios medicos",LOWER(B10))),"Pets & Health",IF(ISNUMBER(SEARCH("farm",LOWER(B10))),"Pharmacy",IF(ISNUMBER(SEARCH("cruz verde",LOWER(B10))),"Pharmacy",IF(ISNUMBER(SEARCH("mercado",LOWER(B10))),"Shopping",IF(ISNUMBER(SEARCH("mercadopago",LOWER(B10))),"Shopping",IF(ISNUMBER(SEARCH("ikea",LOWER(B10))),"Shopping",IF(ISNUMBER(SEARCH("spotify",LOWER(B10))),"Subscriptions","Other"))))))))))))) -> Other
A11: =IF(MOV_CC_NACIONAL!A11="","",MOV_CC_NACIONAL!A11) -> 21-02-2026 | B11: =IF(MOV_CC_NACIONAL!B11="","",MOV_CC_NACIONAL!B11) -> MORA LOUTIT SWEET S COMPRAS | C11: =IF(MOV_CC_NACIONAL!C11="","",MOV_CC_NACIONAL!C11) -> 11550 | D11: =IF(ISNUMBER(SEARCH("uber",LOWER(B11))),"Food & Transport",IF(ISNUMBER(SEARCH("payu *uber",LOWER(B11))),"Food & Transport",IF(ISNUMBER(SEARCH("kfc",LOWER(B11))),"Food & Transport",IF(ISNUMBER(SEARCH("cinemark",LOWER(B11))),"Food & Transport",IF(ISNUMBER(SEARCH("pethouse",LOWER(B11))),"Pets & Health",IF(ISNUMBER(SEARCH("superzoo",LOWER(B11))),"Pets & Health",IF(ISNUMBER(SEARCH("servicios medicos",LOWER(B11))),"Pets & Health",IF(ISNUMBER(SEARCH("farm",LOWER(B11))),"Pharmacy",IF(ISNUMBER(SEARCH("cruz verde",LOWER(B11))),"Pharmacy",IF(ISNUMBER(SEARCH("mercado",LOWER(B11))),"Shopping",IF(ISNUMBER(SEARCH("mercadopago",LOWER(B11))),"Shopping",IF(ISNUMBER(SEARCH("ikea",LOWER(B11))),"Shopping",IF(ISNUMBER(SEARCH("spotify",LOWER(B11))),"Subscriptions","Other"))))))))))))) -> Other
A12: =IF(MOV_CC_NACIONAL!A12="","",MOV_CC_NACIONAL!A12) -> 23-02-2026 | B12: =IF(MOV_CC_NACIONAL!B12="","",MOV_CC_NACIONAL!B12) -> MERCADOPAGO*MERCADO 03 CTAS-INT: 0 | C12: =IF(MOV_CC_NACIONAL!C12="","",MOV_CC_NACIONAL!C12) -> 86791 | D12: =IF(ISNUMBER(SEARCH("uber",LOWER(B12))),"Food & Transport",IF(ISNUMBER(SEARCH("payu *uber",LOWER(B12))),"Food & Transport",IF(ISNUMBER(SEARCH("kfc",LOWER(B12))),"Food & Transport",IF(ISNUMBER(SEARCH("cinemark",LOWER(B12))),"Food & Transport",IF(ISNUMBER(SEARCH("pethouse",LOWER(B12))),"Pets & Health",IF(ISNUMBER(SEARCH("superzoo",LOWER(B12))),"Pets & Health",IF(ISNUMBER(SEARCH("servicios medicos",LOWER(B12))),"Pets & Health",IF(ISNUMBER(SEARCH("farm",LOWER(B12))),"Pharmacy",IF(ISNUMBER(SEARCH("cruz verde",LOWER(B12))),"Pharmacy",IF(ISNUMBER(SEARCH("mercado",LOWER(B12))),"Shopping",IF(ISNUMBER(SEARCH("mercadopago",LOWER(B12))),"Shopping",IF(ISNUMBER(SEARCH("ikea",LOWER(B12))),"Shopping",IF(ISNUMBER(SEARCH("spotify",LOWER(B12))),"Subscriptions","Other"))))))))))))) -> Shopping
A13: =IF(MOV_CC_NACIONAL!A13="","",MOV_CC_NACIONAL!A13) -> 21-02-2026 | B13: =IF(MOV_CC_NACIONAL!B13="","",MOV_CC_NACIONAL!B13) -> MERPAGO*OPTICASLUXO HUE CC 01-06 | C13: =IF(MOV_CC_NACIONAL!C13="","",MOV_CC_NACIONAL!C13) -> 41030 | D13: =IF(ISNUMBER(SEARCH("uber",LOWER(B13))),"Food & Transport",IF(ISNUMBER(SEARCH("payu *uber",LOWER(B13))),"Food & Transport",IF(ISNUMBER(SEARCH("kfc",LOWER(B13))),"Food & Transport",IF(ISNUMBER(SEARCH("cinemark",LOWER(B13))),"Food & Transport",IF(ISNUMBER(SEARCH("pethouse",LOWER(B13))),"Pets & Health",IF(ISNUMBER(SEARCH("superzoo",LOWER(B13))),"Pets & Health",IF(ISNUMBER(SEARCH("servicios medicos",LOWER(B13))),"Pets & Health",IF(ISNUMBER(SEARCH("farm",LOWER(B13))),"Pharmacy",IF(ISNUMBER(SEARCH("cruz verde",LOWER(B13))),"Pharmacy",IF(ISNUMBER(SEARCH("mercado",LOWER(B13))),"Shopping",IF(ISNUMBER(SEARCH("mercadopago",LOWER(B13))),"Shopping",IF(ISNUMBER(SEARCH("ikea",LOWER(B13))),"Shopping",IF(ISNUMBER(SEARCH("spotify",LOWER(B13))),"Subscriptions","Other"))))))))))))) -> Other
... A2001: =IF(MOV_CC_NACIONAL!A2001="","",MOV_CC_NACIONAL!A2001) | B2001: =IF(MOV_CC_NACIONAL!B2001="","",MOV_CC_NACIONAL!B2001) | C2001: =IF(MOV_CC_NACIONAL!C2001="","",MOV_CC_NACIONAL!C2001) | D2001: =IF(ISNUMBER(SEARCH("uber",LOWER(B2001))),"Food & Transport",IF(ISNUMBER(SEARCH("payu *uber",LOWER(B2001))),"Food & Transport",IF(ISNUMBER(SEARCH("kfc",LOWER(B2001))),"Food & Transport",IF(ISNUMBER(SEARCH("cinemark",LOWER(B2001))),"Food & Transport",IF(ISNUMBER(SEARCH("pethouse",LOWER(B2001))),"Pets & Health",IF(ISNUMBER(SEARCH("superzoo",LOWER(B2001))),"Pets & Health",IF(ISNUMBER(SEARCH("servicios medicos",LOWER(B2001))),"Pets & Health",IF(ISNUMBER(SEARCH("farm",LOWER(B2001))),"Pharmacy",IF(ISNUMBER(SEARCH("cruz verde",LOWER(B2001))),"Pharmacy",IF(ISNUMBER(SEARCH("mercado",LOWER(B2001))),"Shopping",IF(ISNUMBER(SEARCH("mercadopago",LOWER(B2001))),"Shopping",IF(ISNUMBER(SEARCH("ikea",LOWER(B2001))),"Shopping",IF(ISNUMBER(SEARCH("spotify",LOWER(B2001))),"Subscriptions","Other"))))))))))))) -> Other

Sheet MOV_INTL_AUTO
A1: Fecha | B1: Descripcion | C1: Monto_USD | D1: Categoria | E1: Monto_CLP_est
A2: =IF(MOV_CC_INTL!A2="","",MOV_CC_INTL!A2) -> 22-02-2026 | B2: =IF(MOV_CC_INTL!B2="","",MOV_CC_INTL!B2) -> EMBY PREMIERE COMPRAS INT.VI | C2: =IF(MOV_CC_INTL!C2="","",MOV_CC_INTL!C2) -> 4.99 | D2: =IF(ISNUMBER(SEARCH("openai",LOWER(B2))),"AI Tools",IF(ISNUMBER(SEARCH("anthropic",LOWER(B2))),"AI Tools",IF(ISNUMBER(SEARCH("claude",LOWER(B2))),"AI Tools",IF(ISNUMBER(SEARCH("appbox",LOWER(B2))),"Digital Services",IF(ISNUMBER(SEARCH("apple",LOWER(B2))),"Digital Services",IF(ISNUMBER(SEARCH("playstation",LOWER(B2))),"Digital Services",IF(ISNUMBER(SEARCH("battle",LOWER(B2))),"Gaming","Other"))))))) -> Other | E2: =IF(C2="","",C2*CONFIG!B5) -> 4740.5
A3: =IF(MOV_CC_INTL!A3="","",MOV_CC_INTL!A3) -> 20-02-2026 | B3: =IF(MOV_CC_INTL!B3="","",MOV_CC_INTL!B3) -> CLAUDE.AI SUBSCRIPT COMPRAS INT.VI | C3: =IF(MOV_CC_INTL!C3="","",MOV_CC_INTL!C3) -> 102.76 | D3: =IF(ISNUMBER(SEARCH("openai",LOWER(B3))),"AI Tools",IF(ISNUMBER(SEARCH("anthropic",LOWER(B3))),"AI Tools",IF(ISNUMBER(SEARCH("claude",LOWER(B3))),"AI Tools",IF(ISNUMBER(SEARCH("appbox",LOWER(B3))),"Digital Services",IF(ISNUMBER(SEARCH("apple",LOWER(B3))),"Digital Services",IF(ISNUMBER(SEARCH("playstation",LOWER(B3))),"Digital Services",IF(ISNUMBER(SEARCH("battle",LOWER(B3))),"Gaming","Other"))))))) -> AI Tools | E3: =IF(C3="","",C3*CONFIG!B5) -> 97622
A4: =IF(MOV_CC_INTL!A4="","",MOV_CC_INTL!A4) -> 19-02-2026 | B4: =IF(MOV_CC_INTL!B4="","",MOV_CC_INTL!B4) -> APPLE.COM/BILL COMPRAS INT.VI | C4: =IF(MOV_CC_INTL!C4="","",MOV_CC_INTL!C4) -> 12.48 | D4: =IF(ISNUMBER(SEARCH("openai",LOWER(B4))),"AI Tools",IF(ISNUMBER(SEARCH("anthropic",LOWER(B4))),"AI Tools",IF(ISNUMBER(SEARCH("claude",LOWER(B4))),"AI Tools",IF(ISNUMBER(SEARCH("appbox",LOWER(B4))),"Digital Services",IF(ISNUMBER(SEARCH("apple",LOWER(B4))),"Digital Services",IF(ISNUMBER(SEARCH("playstation",LOWER(B4))),"Digital Services",IF(ISNUMBER(SEARCH("battle",LOWER(B4))),"Gaming","Other"))))))) -> Digital Services | E4: =IF(C4="","",C4*CONFIG!B5) -> 11856
A5: =IF(MOV_CC_INTL!A5="","",MOV_CC_INTL!A5) | B5: =IF(MOV_CC_INTL!B5="","",MOV_CC_INTL!B5) | C5: =IF(MOV_CC_INTL!C5="","",MOV_CC_INTL!C5) | D5: =IF(ISNUMBER(SEARCH("openai",LOWER(B5))),"AI Tools",IF(ISNUMBER(SEARCH("anthropic",LOWER(B5))),"AI Tools",IF(ISNUMBER(SEARCH("claude",LOWER(B5))),"AI Tools",IF(ISNUMBER(SEARCH("appbox",LOWER(B5))),"Digital Services",IF(ISNUMBER(SEARCH("apple",LOWER(B5))),"Digital Services",IF(ISNUMBER(SEARCH("playstation",LOWER(B5))),"Digital Services",IF(ISNUMBER(SEARCH("battle",LOWER(B5))),"Gaming","Other"))))))) -> Other | E5: =IF(C5="","",C5*CONFIG!B5)
A6: =IF(MOV_CC_INTL!A6="","",MOV_CC_INTL!A6) | B6: =IF(MOV_CC_INTL!B6="","",MOV_CC_INTL!B6) | C6: =IF(MOV_CC_INTL!C6="","",MOV_CC_INTL!C6) | D6: =IF(ISNUMBER(SEARCH("openai",LOWER(B6))),"AI Tools",IF(ISNUMBER(SEARCH("anthropic",LOWER(B6))),"AI Tools",IF(ISNUMBER(SEARCH("claude",LOWER(B6))),"AI Tools",IF(ISNUMBER(SEARCH("appbox",LOWER(B6))),"Digital Services",IF(ISNUMBER(SEARCH("apple",LOWER(B6))),"Digital Services",IF(ISNUMBER(SEARCH("playstation",LOWER(B6))),"Digital Services",IF(ISNUMBER(SEARCH("battle",LOWER(B6))),"Gaming","Other"))))))) -> Other | E6: =IF(C6="","",C6*CONFIG!B5)
A7: =IF(MOV_CC_INTL!A7="","",MOV_CC_INTL!A7) | B7: =IF(MOV_CC_INTL!B7="","",MOV_CC_INTL!B7) | C7: =IF(MOV_CC_INTL!C7="","",MOV_CC_INTL!C7) | D7: =IF(ISNUMBER(SEARCH("openai",LOWER(B7))),"AI Tools",IF(ISNUMBER(SEARCH("anthropic",LOWER(B7))),"AI Tools",IF(ISNUMBER(SEARCH("claude",LOWER(B7))),"AI Tools",IF(ISNUMBER(SEARCH("appbox",LOWER(B7))),"Digital Services",IF(ISNUMBER(SEARCH("apple",LOWER(B7))),"Digital Services",IF(ISNUMBER(SEARCH("playstation",LOWER(B7))),"Digital Services",IF(ISNUMBER(SEARCH("battle",LOWER(B7))),"Gaming","Other"))))))) -> Other | E7: =IF(C7="","",C7*CONFIG!B5)
A8: =IF(MOV_CC_INTL!A8="","",MOV_CC_INTL!A8) | B8: =IF(MOV_CC_INTL!B8="","",MOV_CC_INTL!B8) | C8: =IF(MOV_CC_INTL!C8="","",MOV_CC_INTL!C8) | D8: =IF(ISNUMBER(SEARCH("openai",LOWER(B8))),"AI Tools",IF(ISNUMBER(SEARCH("anthropic",LOWER(B8))),"AI Tools",IF(ISNUMBER(SEARCH("claude",LOWER(B8))),"AI Tools",IF(ISNUMBER(SEARCH("appbox",LOWER(B8))),"Digital Services",IF(ISNUMBER(SEARCH("apple",LOWER(B8))),"Digital Services",IF(ISNUMBER(SEARCH("playstation",LOWER(B8))),"Digital Services",IF(ISNUMBER(SEARCH("battle",LOWER(B8))),"Gaming","Other"))))))) -> Other | E8: =IF(C8="","",C8*CONFIG!B5)
A9: =IF(MOV_CC_INTL!A9="","",MOV_CC_INTL!A9) | B9: =IF(MOV_CC_INTL!B9="","",MOV_CC_INTL!B9) | C9: =IF(MOV_CC_INTL!C9="","",MOV_CC_INTL!C9) | D9: =IF(ISNUMBER(SEARCH("openai",LOWER(B9))),"AI Tools",IF(ISNUMBER(SEARCH("anthropic",LOWER(B9))),"AI Tools",IF(ISNUMBER(SEARCH("claude",LOWER(B9))),"AI Tools",IF(ISNUMBER(SEARCH("appbox",LOWER(B9))),"Digital Services",IF(ISNUMBER(SEARCH("apple",LOWER(B9))),"Digital Services",IF(ISNUMBER(SEARCH("playstation",LOWER(B9))),"Digital Services",IF(ISNUMBER(SEARCH("battle",LOWER(B9))),"Gaming","Other"))))))) -> Other | E9: =IF(C9="","",C9*CONFIG!B5)
A10: =IF(MOV_CC_INTL!A10="","",MOV_CC_INTL!A10) | B10: =IF(MOV_CC_INTL!B10="","",MOV_CC_INTL!B10) | C10: =IF(MOV_CC_INTL!C10="","",MOV_CC_INTL!C10) | D10: =IF(ISNUMBER(SEARCH("openai",LOWER(B10))),"AI Tools",IF(ISNUMBER(SEARCH("anthropic",LOWER(B10))),"AI Tools",IF(ISNUMBER(SEARCH("claude",LOWER(B10))),"AI Tools",IF(ISNUMBER(SEARCH("appbox",LOWER(B10))),"Digital Services",IF(ISNUMBER(SEARCH("apple",LOWER(B10))),"Digital Services",IF(ISNUMBER(SEARCH("playstation",LOWER(B10))),"Digital Services",IF(ISNUMBER(SEARCH("battle",LOWER(B10))),"Gaming","Other"))))))) -> Other | E10: =IF(C10="","",C10*CONFIG!B5)
A11: =IF(MOV_CC_INTL!A11="","",MOV_CC_INTL!A11) | B11: =IF(MOV_CC_INTL!B11="","",MOV_CC_INTL!B11) | C11: =IF(MOV_CC_INTL!C11="","",MOV_CC_INTL!C11) | D11: =IF(ISNUMBER(SEARCH("openai",LOWER(B11))),"AI Tools",IF(ISNUMBER(SEARCH("anthropic",LOWER(B11))),"AI Tools",IF(ISNUMBER(SEARCH("claude",LOWER(B11))),"AI Tools",IF(ISNUMBER(SEARCH("appbox",LOWER(B11))),"Digital Services",IF(ISNUMBER(SEARCH("apple",LOWER(B11))),"Digital Services",IF(ISNUMBER(SEARCH("playstation",LOWER(B11))),"Digital Services",IF(ISNUMBER(SEARCH("battle",LOWER(B11))),"Gaming","Other"))))))) -> Other | E11: =IF(C11="","",C11*CONFIG!B5)
A12: =IF(MOV_CC_INTL!A12="","",MOV_CC_INTL!A12) | B12: =IF(MOV_CC_INTL!B12="","",MOV_CC_INTL!B12) | C12: =IF(MOV_CC_INTL!C12="","",MOV_CC_INTL!C12) | D12: =IF(ISNUMBER(SEARCH("openai",LOWER(B12))),"AI Tools",IF(ISNUMBER(SEARCH("anthropic",LOWER(B12))),"AI Tools",IF(ISNUMBER(SEARCH("claude",LOWER(B12))),"AI Tools",IF(ISNUMBER(SEARCH("appbox",LOWER(B12))),"Digital Services",IF(ISNUMBER(SEARCH("apple",LOWER(B12))),"Digital Services",IF(ISNUMBER(SEARCH("playstation",LOWER(B12))),"Digital Services",IF(ISNUMBER(SEARCH("battle",LOWER(B12))),"Gaming","Other"))))))) -> Other | E12: =IF(C12="","",C12*CONFIG!B5)
A13: =IF(MOV_CC_INTL!A13="","",MOV_CC_INTL!A13) | B13: =IF(MOV_CC_INTL!B13="","",MOV_CC_INTL!B13) | C13: =IF(MOV_CC_INTL!C13="","",MOV_CC_INTL!C13) | D13: =IF(ISNUMBER(SEARCH("openai",LOWER(B13))),"AI Tools",IF(ISNUMBER(SEARCH("anthropic",LOWER(B13))),"AI Tools",IF(ISNUMBER(SEARCH("claude",LOWER(B13))),"AI Tools",IF(ISNUMBER(SEARCH("appbox",LOWER(B13))),"Digital Services",IF(ISNUMBER(SEARCH("apple",LOWER(B13))),"Digital Services",IF(ISNUMBER(SEARCH("playstation",LOWER(B13))),"Digital Services",IF(ISNUMBER(SEARCH("battle",LOWER(B13))),"Gaming","Other"))))))) -> Other | E13: =IF(C13="","",C13*CONFIG!B5)
A14: =IF(MOV_CC_INTL!A14="","",MOV_CC_INTL!A14) | B14: =IF(MOV_CC_INTL!B14="","",MOV_CC_INTL!B14) | C14: =IF(MOV_CC_INTL!C14="","",MOV_CC_INTL!C14) | D14: =IF(ISNUMBER(SEARCH("openai",LOWER(B14))),"AI Tools",IF(ISNUMBER(SEARCH("anthropic",LOWER(B14))),"AI Tools",IF(ISNUMBER(SEARCH("claude",LOWER(B14))),"AI Tools",IF(ISNUMBER(SEARCH("appbox",LOWER(B14))),"Digital Services",IF(ISNUMBER(SEARCH("apple",LOWER(B14))),"Digital Services",IF(ISNUMBER(SEARCH("playstation",LOWER(B14))),"Digital Services",IF(ISNUMBER(SEARCH("battle",LOWER(B14))),"Gaming","Other"))))))) -> Other | E14: =IF(C14="","",C14*CONFIG!B5)
A15: =IF(MOV_CC_INTL!A15="","",MOV_CC_INTL!A15) | B15: =IF(MOV_CC_INTL!B15="","",MOV_CC_INTL!B15) | C15: =IF(MOV_CC_INTL!C15="","",MOV_CC_INTL!C15) | D15: =IF(ISNUMBER(SEARCH("openai",LOWER(B15))),"AI Tools",IF(ISNUMBER(SEARCH("anthropic",LOWER(B15))),"AI Tools",IF(ISNUMBER(SEARCH("claude",LOWER(B15))),"AI Tools",IF(ISNUMBER(SEARCH("appbox",LOWER(B15))),"Digital Services",IF(ISNUMBER(SEARCH("apple",LOWER(B15))),"Digital Services",IF(ISNUMBER(SEARCH("playstation",LOWER(B15))),"Digital Services",IF(ISNUMBER(SEARCH("battle",LOWER(B15))),"Gaming","Other"))))))) -> Other | E15: =IF(C15="","",C15*CONFIG!B5)
A16: =IF(MOV_CC_INTL!A16="","",MOV_CC_INTL!A16) | B16: =IF(MOV_CC_INTL!B16="","",MOV_CC_INTL!B16) | C16: =IF(MOV_CC_INTL!C16="","",MOV_CC_INTL!C16) | D16: =IF(ISNUMBER(SEARCH("openai",LOWER(B16))),"AI Tools",IF(ISNUMBER(SEARCH("anthropic",LOWER(B16))),"AI Tools",IF(ISNUMBER(SEARCH("claude",LOWER(B16))),"AI Tools",IF(ISNUMBER(SEARCH("appbox",LOWER(B16))),"Digital Services",IF(ISNUMBER(SEARCH("apple",LOWER(B16))),"Digital Services",IF(ISNUMBER(SEARCH("playstation",LOWER(B16))),"Digital Services",IF(ISNUMBER(SEARCH("battle",LOWER(B16))),"Gaming","Other"))))))) -> Other | E16: =IF(C16="","",C16*CONFIG!B5)
A17: =IF(MOV_CC_INTL!A17="","",MOV_CC_INTL!A17) | B17: =IF(MOV_CC_INTL!B17="","",MOV_CC_INTL!B17) | C17: =IF(MOV_CC_INTL!C17="","",MOV_CC_INTL!C17) | D17: =IF(ISNUMBER(SEARCH("openai",LOWER(B17))),"AI Tools",IF(ISNUMBER(SEARCH("anthropic",LOWER(B17))),"AI Tools",IF(ISNUMBER(SEARCH("claude",LOWER(B17))),"AI Tools",IF(ISNUMBER(SEARCH("appbox",LOWER(B17))),"Digital Services",IF(ISNUMBER(SEARCH("apple",LOWER(B17))),"Digital Services",IF(ISNUMBER(SEARCH("playstation",LOWER(B17))),"Digital Services",IF(ISNUMBER(SEARCH("battle",LOWER(B17))),"Gaming","Other"))))))) -> Other | E17: =IF(C17="","",C17*CONFIG!B5)
A18: =IF(MOV_CC_INTL!A18="","",MOV_CC_INTL!A18) | B18: =IF(MOV_CC_INTL!B18="","",MOV_CC_INTL!B18) | C18: =IF(MOV_CC_INTL!C18="","",MOV_CC_INTL!C18) | D18: =IF(ISNUMBER(SEARCH("openai",LOWER(B18))),"AI Tools",IF(ISNUMBER(SEARCH("anthropic",LOWER(B18))),"AI Tools",IF(ISNUMBER(SEARCH("claude",LOWER(B18))),"AI Tools",IF(ISNUMBER(SEARCH("appbox",LOWER(B18))),"Digital Services",IF(ISNUMBER(SEARCH("apple",LOWER(B18))),"Digital Services",IF(ISNUMBER(SEARCH("playstation",LOWER(B18))),"Digital Services",IF(ISNUMBER(SEARCH("battle",LOWER(B18))),"Gaming","Other"))))))) -> Other | E18: =IF(C18="","",C18*CONFIG!B5)
A19: =IF(MOV_CC_INTL!A19="","",MOV_CC_INTL!A19) | B19: =IF(MOV_CC_INTL!B19="","",MOV_CC_INTL!B19) | C19: =IF(MOV_CC_INTL!C19="","",MOV_CC_INTL!C19) | D19: =IF(ISNUMBER(SEARCH("openai",LOWER(B19))),"AI Tools",IF(ISNUMBER(SEARCH("anthropic",LOWER(B19))),"AI Tools",IF(ISNUMBER(SEARCH("claude",LOWER(B19))),"AI Tools",IF(ISNUMBER(SEARCH("appbox",LOWER(B19))),"Digital Services",IF(ISNUMBER(SEARCH("apple",LOWER(B19))),"Digital Services",IF(ISNUMBER(SEARCH("playstation",LOWER(B19))),"Digital Services",IF(ISNUMBER(SEARCH("battle",LOWER(B19))),"Gaming","Other"))))))) -> Other | E19: =IF(C19="","",C19*CONFIG!B5)
A20: =IF(MOV_CC_INTL!A20="","",MOV_CC_INTL!A20) | B20: =IF(MOV_CC_INTL!B20="","",MOV_CC_INTL!B20) | C20: =IF(MOV_CC_INTL!C20="","",MOV_CC_INTL!C20) | D20: =IF(ISNUMBER(SEARCH("openai",LOWER(B20))),"AI Tools",IF(ISNUMBER(SEARCH("anthropic",LOWER(B20))),"AI Tools",IF(ISNUMBER(SEARCH("claude",LOWER(B20))),"AI Tools",IF(ISNUMBER(SEARCH("appbox",LOWER(B20))),"Digital Services",IF(ISNUMBER(SEARCH("apple",LOWER(B20))),"Digital Services",IF(ISNUMBER(SEARCH("playstation",LOWER(B20))),"Digital Services",IF(ISNUMBER(SEARCH("battle",LOWER(B20))),"Gaming","Other"))))))) -> Other | E20: =IF(C20="","",C20*CONFIG!B5)
A21: =IF(MOV_CC_INTL!A21="","",MOV_CC_INTL!A21) | B21: =IF(MOV_CC_INTL!B21="","",MOV_CC_INTL!B21) | C21: =IF(MOV_CC_INTL!C21="","",MOV_CC_INTL!C21) | D21: =IF(ISNUMBER(SEARCH("openai",LOWER(B21))),"AI Tools",IF(ISNUMBER(SEARCH("anthropic",LOWER(B21))),"AI Tools",IF(ISNUMBER(SEARCH("claude",LOWER(B21))),"AI Tools",IF(ISNUMBER(SEARCH("appbox",LOWER(B21))),"Digital Services",IF(ISNUMBER(SEARCH("apple",LOWER(B21))),"Digital Services",IF(ISNUMBER(SEARCH("playstation",LOWER(B21))),"Digital Services",IF(ISNUMBER(SEARCH("battle",LOWER(B21))),"Gaming","Other"))))))) -> Other | E21: =IF(C21="","",C21*CONFIG!B5)
A22: =IF(MOV_CC_INTL!A22="","",MOV_CC_INTL!A22) | B22: =IF(MOV_CC_INTL!B22="","",MOV_CC_INTL!B22) | C22: =IF(MOV_CC_INTL!C22="","",MOV_CC_INTL!C22) | D22: =IF(ISNUMBER(SEARCH("openai",LOWER(B22))),"AI Tools",IF(ISNUMBER(SEARCH("anthropic",LOWER(B22))),"AI Tools",IF(ISNUMBER(SEARCH("claude",LOWER(B22))),"AI Tools",IF(ISNUMBER(SEARCH("appbox",LOWER(B22))),"Digital Services",IF(ISNUMBER(SEARCH("apple",LOWER(B22))),"Digital Services",IF(ISNUMBER(SEARCH("playstation",LOWER(B22))),"Digital Services",IF(ISNUMBER(SEARCH("battle",LOWER(B22))),"Gaming","Other"))))))) -> Other | E22: =IF(C22="","",C22*CONFIG!B5)
A23: =IF(MOV_CC_INTL!A23="","",MOV_CC_INTL!A23) | B23: =IF(MOV_CC_INTL!B23="","",MOV_CC_INTL!B23) | C23: =IF(MOV_CC_INTL!C23="","",MOV_CC_INTL!C23) | D23: =IF(ISNUMBER(SEARCH("openai",LOWER(B23))),"AI Tools",IF(ISNUMBER(SEARCH("anthropic",LOWER(B23))),"AI Tools",IF(ISNUMBER(SEARCH("claude",LOWER(B23))),"AI Tools",IF(ISNUMBER(SEARCH("appbox",LOWER(B23))),"Digital Services",IF(ISNUMBER(SEARCH("apple",LOWER(B23))),"Digital Services",IF(ISNUMBER(SEARCH("playstation",LOWER(B23))),"Digital Services",IF(ISNUMBER(SEARCH("battle",LOWER(B23))),"Gaming","Other"))))))) -> Other | E23: =IF(C23="","",C23*CONFIG!B5)
A24: =IF(MOV_CC_INTL!A24="","",MOV_CC_INTL!A24) | B24: =IF(MOV_CC_INTL!B24="","",MOV_CC_INTL!B24) | C24: =IF(MOV_CC_INTL!C24="","",MOV_CC_INTL!C24) | D24: =IF(ISNUMBER(SEARCH("openai",LOWER(B24))),"AI Tools",IF(ISNUMBER(SEARCH("anthropic",LOWER(B24))),"AI Tools",IF(ISNUMBER(SEARCH("claude",LOWER(B24))),"AI Tools",IF(ISNUMBER(SEARCH("appbox",LOWER(B24))),"Digital Services",IF(ISNUMBER(SEARCH("apple",LOWER(B24))),"Digital Services",IF(ISNUMBER(SEARCH("playstation",LOWER(B24))),"Digital Services",IF(ISNUMBER(SEARCH("battle",LOWER(B24))),"Gaming","Other"))))))) -> Other | E24: =IF(C24="","",C24*CONFIG!B5)
A25: =IF(MOV_CC_INTL!A25="","",MOV_CC_INTL!A25) | B25: =IF(MOV_CC_INTL!B25="","",MOV_CC_INTL!B25) | C25: =IF(MOV_CC_INTL!C25="","",MOV_CC_INTL!C25) | D25: =IF(ISNUMBER(SEARCH("openai",LOWER(B25))),"AI Tools",IF(ISNUMBER(SEARCH("anthropic",LOWER(B25))),"AI Tools",IF(ISNUMBER(SEARCH("claude",LOWER(B25))),"AI Tools",IF(ISNUMBER(SEARCH("appbox",LOWER(B25))),"Digital Services",IF(ISNUMBER(SEARCH("apple",LOWER(B25))),"Digital Services",IF(ISNUMBER(SEARCH("playstation",LOWER(B25))),"Digital Services",IF(ISNUMBER(SEARCH("battle",LOWER(B25))),"Gaming","Other"))))))) -> Other | E25: =IF(C25="","",C25*CONFIG!B5)
A26: =IF(MOV_CC_INTL!A26="","",MOV_CC_INTL!A26) | B26: =IF(MOV_CC_INTL!B26="","",MOV_CC_INTL!B26) | C26: =IF(MOV_CC_INTL!C26="","",MOV_CC_INTL!C26) | D26: =IF(ISNUMBER(SEARCH("openai",LOWER(B26))),"AI Tools",IF(ISNUMBER(SEARCH("anthropic",LOWER(B26))),"AI Tools",IF(ISNUMBER(SEARCH("claude",LOWER(B26))),"AI Tools",IF(ISNUMBER(SEARCH("appbox",LOWER(B26))),"Digital Services",IF(ISNUMBER(SEARCH("apple",LOWER(B26))),"Digital Services",IF(ISNUMBER(SEARCH("playstation",LOWER(B26))),"Digital Services",IF(ISNUMBER(SEARCH("battle",LOWER(B26))),"Gaming","Other"))))))) -> Other | E26: =IF(C26="","",C26*CONFIG!B5)
A27: =IF(MOV_CC_INTL!A27="","",MOV_CC_INTL!A27) | B27: =IF(MOV_CC_INTL!B27="","",MOV_CC_INTL!B27) | C27: =IF(MOV_CC_INTL!C27="","",MOV_CC_INTL!C27) | D27: =IF(ISNUMBER(SEARCH("openai",LOWER(B27))),"AI Tools",IF(ISNUMBER(SEARCH("anthropic",LOWER(B27))),"AI Tools",IF(ISNUMBER(SEARCH("claude",LOWER(B27))),"AI Tools",IF(ISNUMBER(SEARCH("appbox",LOWER(B27))),"Digital Services",IF(ISNUMBER(SEARCH("apple",LOWER(B27))),"Digital Services",IF(ISNUMBER(SEARCH("playstation",LOWER(B27))),"Digital Services",IF(ISNUMBER(SEARCH("battle",LOWER(B27))),"Gaming","Other"))))))) -> Other | E27: =IF(C27="","",C27*CONFIG!B5)
A28: =IF(MOV_CC_INTL!A28="","",MOV_CC_INTL!A28) | B28: =IF(MOV_CC_INTL!B28="","",MOV_CC_INTL!B28) | C28: =IF(MOV_CC_INTL!C28="","",MOV_CC_INTL!C28) | D28: =IF(ISNUMBER(SEARCH("openai",LOWER(B28))),"AI Tools",IF(ISNUMBER(SEARCH("anthropic",LOWER(B28))),"AI Tools",IF(ISNUMBER(SEARCH("claude",LOWER(B28))),"AI Tools",IF(ISNUMBER(SEARCH("appbox",LOWER(B28))),"Digital Services",IF(ISNUMBER(SEARCH("apple",LOWER(B28))),"Digital Services",IF(ISNUMBER(SEARCH("playstation",LOWER(B28))),"Digital Services",IF(ISNUMBER(SEARCH("battle",LOWER(B28))),"Gaming","Other"))))))) -> Other | E28: =IF(C28="","",C28*CONFIG!B5)
A29: =IF(MOV_CC_INTL!A29="","",MOV_CC_INTL!A29) | B29: =IF(MOV_CC_INTL!B29="","",MOV_CC_INTL!B29) | C29: =IF(MOV_CC_INTL!C29="","",MOV_CC_INTL!C29) | D29: =IF(ISNUMBER(SEARCH("openai",LOWER(B29))),"AI Tools",IF(ISNUMBER(SEARCH("anthropic",LOWER(B29))),"AI Tools",IF(ISNUMBER(SEARCH("claude",LOWER(B29))),"AI Tools",IF(ISNUMBER(SEARCH("appbox",LOWER(B29))),"Digital Services",IF(ISNUMBER(SEARCH("apple",LOWER(B29))),"Digital Services",IF(ISNUMBER(SEARCH("playstation",LOWER(B29))),"Digital Services",IF(ISNUMBER(SEARCH("battle",LOWER(B29))),"Gaming","Other"))))))) -> Other | E29: =IF(C29="","",C29*CONFIG!B5)
A30: =IF(MOV_CC_INTL!A30="","",MOV_CC_INTL!A30) | B30: =IF(MOV_CC_INTL!B30="","",MOV_CC_INTL!B30) | C30: =IF(MOV_CC_INTL!C30="","",MOV_CC_INTL!C30) | D30: =IF(ISNUMBER(SEARCH("openai",LOWER(B30))),"AI Tools",IF(ISNUMBER(SEARCH("anthropic",LOWER(B30))),"AI Tools",IF(ISNUMBER(SEARCH("claude",LOWER(B30))),"AI Tools",IF(ISNUMBER(SEARCH("appbox",LOWER(B30))),"Digital Services",IF(ISNUMBER(SEARCH("apple",LOWER(B30))),"Digital Services",IF(ISNUMBER(SEARCH("playstation",LOWER(B30))),"Digital Services",IF(ISNUMBER(SEARCH("battle",LOWER(B30))),"Gaming","Other"))))))) -> Other | E30: =IF(C30="","",C30*CONFIG!B5)
A31: =IF(MOV_CC_INTL!A31="","",MOV_CC_INTL!A31) | B31: =IF(MOV_CC_INTL!B31="","",MOV_CC_INTL!B31) | C31: =IF(MOV_CC_INTL!C31="","",MOV_CC_INTL!C31) | D31: =IF(ISNUMBER(SEARCH("openai",LOWER(B31))),"AI Tools",IF(ISNUMBER(SEARCH("anthropic",LOWER(B31))),"AI Tools",IF(ISNUMBER(SEARCH("claude",LOWER(B31))),"AI Tools",IF(ISNUMBER(SEARCH("appbox",LOWER(B31))),"Digital Services",IF(ISNUMBER(SEARCH("apple",LOWER(B31))),"Digital Services",IF(ISNUMBER(SEARCH("playstation",LOWER(B31))),"Digital Services",IF(ISNUMBER(SEARCH("battle",LOWER(B31))),"Gaming","Other"))))))) -> Other | E31: =IF(C31="","",C31*CONFIG!B5)
A32: =IF(MOV_CC_INTL!A32="","",MOV_CC_INTL!A32) | B32: =IF(MOV_CC_INTL!B32="","",MOV_CC_INTL!B32) | C32: =IF(MOV_CC_INTL!C32="","",MOV_CC_INTL!C32) | D32: =IF(ISNUMBER(SEARCH("openai",LOWER(B32))),"AI Tools",IF(ISNUMBER(SEARCH("anthropic",LOWER(B32))),"AI Tools",IF(ISNUMBER(SEARCH("claude",LOWER(B32))),"AI Tools",IF(ISNUMBER(SEARCH("appbox",LOWER(B32))),"Digital Services",IF(ISNUMBER(SEARCH("apple",LOWER(B32))),"Digital Services",IF(ISNUMBER(SEARCH("playstation",LOWER(B32))),"Digital Services",IF(ISNUMBER(SEARCH("battle",LOWER(B32))),"Gaming","Other"))))))) -> Other | E32: =IF(C32="","",C32*CONFIG!B5)
A33: =IF(MOV_CC_INTL!A33="","",MOV_CC_INTL!A33) | B33: =IF(MOV_CC_INTL!B33="","",MOV_CC_INTL!B33) | C33: =IF(MOV_CC_INTL!C33="","",MOV_CC_INTL!C33) | D33: =IF(ISNUMBER(SEARCH("openai",LOWER(B33))),"AI Tools",IF(ISNUMBER(SEARCH("anthropic",LOWER(B33))),"AI Tools",IF(ISNUMBER(SEARCH("claude",LOWER(B33))),"AI Tools",IF(ISNUMBER(SEARCH("appbox",LOWER(B33))),"Digital Services",IF(ISNUMBER(SEARCH("apple",LOWER(B33))),"Digital Services",IF(ISNUMBER(SEARCH("playstation",LOWER(B33))),"Digital Services",IF(ISNUMBER(SEARCH("battle",LOWER(B33))),"Gaming","Other"))))))) -> Other | E33: =IF(C33="","",C33*CONFIG!B5)
A34: =IF(MOV_CC_INTL!A34="","",MOV_CC_INTL!A34) | B34: =IF(MOV_CC_INTL!B34="","",MOV_CC_INTL!B34) | C34: =IF(MOV_CC_INTL!C34="","",MOV_CC_INTL!C34) | D34: =IF(ISNUMBER(SEARCH("openai",LOWER(B34))),"AI Tools",IF(ISNUMBER(SEARCH("anthropic",LOWER(B34))),"AI Tools",IF(ISNUMBER(SEARCH("claude",LOWER(B34))),"AI Tools",IF(ISNUMBER(SEARCH("appbox",LOWER(B34))),"Digital Services",IF(ISNUMBER(SEARCH("apple",LOWER(B34))),"Digital Services",IF(ISNUMBER(SEARCH("playstation",LOWER(B34))),"Digital Services",IF(ISNUMBER(SEARCH("battle",LOWER(B34))),"Gaming","Other"))))))) -> Other | E34: =IF(C34="","",C34*CONFIG!B5)
A35: =IF(MOV_CC_INTL!A35="","",MOV_CC_INTL!A35) | B35: =IF(MOV_CC_INTL!B35="","",MOV_CC_INTL!B35) | C35: =IF(MOV_CC_INTL!C35="","",MOV_CC_INTL!C35) | D35: =IF(ISNUMBER(SEARCH("openai",LOWER(B35))),"AI Tools",IF(ISNUMBER(SEARCH("anthropic",LOWER(B35))),"AI Tools",IF(ISNUMBER(SEARCH("claude",LOWER(B35))),"AI Tools",IF(ISNUMBER(SEARCH("appbox",LOWER(B35))),"Digital Services",IF(ISNUMBER(SEARCH("apple",LOWER(B35))),"Digital Services",IF(ISNUMBER(SEARCH("playstation",LOWER(B35))),"Digital Services",IF(ISNUMBER(SEARCH("battle",LOWER(B35))),"Gaming","Other"))))))) -> Other | E35: =IF(C35="","",C35*CONFIG!B5)
A36: =IF(MOV_CC_INTL!A36="","",MOV_CC_INTL!A36) | B36: =IF(MOV_CC_INTL!B36="","",MOV_CC_INTL!B36) | C36: =IF(MOV_CC_INTL!C36="","",MOV_CC_INTL!C36) | D36: =IF(ISNUMBER(SEARCH("openai",LOWER(B36))),"AI Tools",IF(ISNUMBER(SEARCH("anthropic",LOWER(B36))),"AI Tools",IF(ISNUMBER(SEARCH("claude",LOWER(B36))),"AI Tools",IF(ISNUMBER(SEARCH("appbox",LOWER(B36))),"Digital Services",IF(ISNUMBER(SEARCH("apple",LOWER(B36))),"Digital Services",IF(ISNUMBER(SEARCH("playstation",LOWER(B36))),"Digital Services",IF(ISNUMBER(SEARCH("battle",LOWER(B36))),"Gaming","Other"))))))) -> Other | E36: =IF(C36="","",C36*CONFIG!B5)
A37: =IF(MOV_CC_INTL!A37="","",MOV_CC_INTL!A37) | B37: =IF(MOV_CC_INTL!B37="","",MOV_CC_INTL!B37) | C37: =IF(MOV_CC_INTL!C37="","",MOV_CC_INTL!C37) | D37: =IF(ISNUMBER(SEARCH("openai",LOWER(B37))),"AI Tools",IF(ISNUMBER(SEARCH("anthropic",LOWER(B37))),"AI Tools",IF(ISNUMBER(SEARCH("claude",LOWER(B37))),"AI Tools",IF(ISNUMBER(SEARCH("appbox",LOWER(B37))),"Digital Services",IF(ISNUMBER(SEARCH("apple",LOWER(B37))),"Digital Services",IF(ISNUMBER(SEARCH("playstation",LOWER(B37))),"Digital Services",IF(ISNUMBER(SEARCH("battle",LOWER(B37))),"Gaming","Other"))))))) -> Other | E37: =IF(C37="","",C37*CONFIG!B5)
A38: =IF(MOV_CC_INTL!A38="","",MOV_CC_INTL!A38) | B38: =IF(MOV_CC_INTL!B38="","",MOV_CC_INTL!B38) | C38: =IF(MOV_CC_INTL!C38="","",MOV_CC_INTL!C38) | D38: =IF(ISNUMBER(SEARCH("openai",LOWER(B38))),"AI Tools",IF(ISNUMBER(SEARCH("anthropic",LOWER(B38))),"AI Tools",IF(ISNUMBER(SEARCH("claude",LOWER(B38))),"AI Tools",IF(ISNUMBER(SEARCH("appbox",LOWER(B38))),"Digital Services",IF(ISNUMBER(SEARCH("apple",LOWER(B38))),"Digital Services",IF(ISNUMBER(SEARCH("playstation",LOWER(B38))),"Digital Services",IF(ISNUMBER(SEARCH("battle",LOWER(B38))),"Gaming","Other"))))))) -> Other | E38: =IF(C38="","",C38*CONFIG!B5)
A39: =IF(MOV_CC_INTL!A39="","",MOV_CC_INTL!A39) | B39: =IF(MOV_CC_INTL!B39="","",MOV_CC_INTL!B39) | C39: =IF(MOV_CC_INTL!C39="","",MOV_CC_INTL!C39) | D39: =IF(ISNUMBER(SEARCH("openai",LOWER(B39))),"AI Tools",IF(ISNUMBER(SEARCH("anthropic",LOWER(B39))),"AI Tools",IF(ISNUMBER(SEARCH("claude",LOWER(B39))),"AI Tools",IF(ISNUMBER(SEARCH("appbox",LOWER(B39))),"Digital Services",IF(ISNUMBER(SEARCH("apple",LOWER(B39))),"Digital Services",IF(ISNUMBER(SEARCH("playstation",LOWER(B39))),"Digital Services",IF(ISNUMBER(SEARCH("battle",LOWER(B39))),"Gaming","Other"))))))) -> Other | E39: =IF(C39="","",C39*CONFIG!B5)
A40: =IF(MOV_CC_INTL!A40="","",MOV_CC_INTL!A40) | B40: =IF(MOV_CC_INTL!B40="","",MOV_CC_INTL!B40) | C40: =IF(MOV_CC_INTL!C40="","",MOV_CC_INTL!C40) | D40: =IF(ISNUMBER(SEARCH("openai",LOWER(B40))),"AI Tools",IF(ISNUMBER(SEARCH("anthropic",LOWER(B40))),"AI Tools",IF(ISNUMBER(SEARCH("claude",LOWER(B40))),"AI Tools",IF(ISNUMBER(SEARCH("appbox",LOWER(B40))),"Digital Services",IF(ISNUMBER(SEARCH("apple",LOWER(B40))),"Digital Services",IF(ISNUMBER(SEARCH("playstation",LOWER(B40))),"Digital Services",IF(ISNUMBER(SEARCH("battle",LOWER(B40))),"Gaming","Other"))))))) -> Other | E40: =IF(C40="","",C40*CONFIG!B5)
A41: =IF(MOV_CC_INTL!A41="","",MOV_CC_INTL!A41) | B41: =IF(MOV_CC_INTL!B41="","",MOV_CC_INTL!B41) | C41: =IF(MOV_CC_INTL!C41="","",MOV_CC_INTL!C41) | D41: =IF(ISNUMBER(SEARCH("openai",LOWER(B41))),"AI Tools",IF(ISNUMBER(SEARCH("anthropic",LOWER(B41))),"AI Tools",IF(ISNUMBER(SEARCH("claude",LOWER(B41))),"AI Tools",IF(ISNUMBER(SEARCH("appbox",LOWER(B41))),"Digital Services",IF(ISNUMBER(SEARCH("apple",LOWER(B41))),"Digital Services",IF(ISNUMBER(SEARCH("playstation",LOWER(B41))),"Digital Services",IF(ISNUMBER(SEARCH("battle",LOWER(B41))),"Gaming","Other"))))))) -> Other | E41: =IF(C41="","",C41*CONFIG!B5)
A42: =IF(MOV_CC_INTL!A42="","",MOV_CC_INTL!A42) | B42: =IF(MOV_CC_INTL!B42="","",MOV_CC_INTL!B42) | C42: =IF(MOV_CC_INTL!C42="","",MOV_CC_INTL!C42) | D42: =IF(ISNUMBER(SEARCH("openai",LOWER(B42))),"AI Tools",IF(ISNUMBER(SEARCH("anthropic",LOWER(B42))),"AI Tools",IF(ISNUMBER(SEARCH("claude",LOWER(B42))),"AI Tools",IF(ISNUMBER(SEARCH("appbox",LOWER(B42))),"Digital Services",IF(ISNUMBER(SEARCH("apple",LOWER(B42))),"Digital Services",IF(ISNUMBER(SEARCH("playstation",LOWER(B42))),"Digital Services",IF(ISNUMBER(SEARCH("battle",LOWER(B42))),"Gaming","Other"))))))) -> Other | E42: =IF(C42="","",C42*CONFIG!B5)
A43: =IF(MOV_CC_INTL!A43="","",MOV_CC_INTL!A43) | B43: =IF(MOV_CC_INTL!B43="","",MOV_CC_INTL!B43) | C43: =IF(MOV_CC_INTL!C43="","",MOV_CC_INTL!C43) | D43: =IF(ISNUMBER(SEARCH("openai",LOWER(B43))),"AI Tools",IF(ISNUMBER(SEARCH("anthropic",LOWER(B43))),"AI Tools",IF(ISNUMBER(SEARCH("claude",LOWER(B43))),"AI Tools",IF(ISNUMBER(SEARCH("appbox",LOWER(B43))),"Digital Services",IF(ISNUMBER(SEARCH("apple",LOWER(B43))),"Digital Services",IF(ISNUMBER(SEARCH("playstation",LOWER(B43))),"Digital Services",IF(ISNUMBER(SEARCH("battle",LOWER(B43))),"Gaming","Other"))))))) -> Other | E43: =IF(C43="","",C43*CONFIG!B5)
A44: =IF(MOV_CC_INTL!A44="","",MOV_CC_INTL!A44) | B44: =IF(MOV_CC_INTL!B44="","",MOV_CC_INTL!B44) | C44: =IF(MOV_CC_INTL!C44="","",MOV_CC_INTL!C44) | D44: =IF(ISNUMBER(SEARCH("openai",LOWER(B44))),"AI Tools",IF(ISNUMBER(SEARCH("anthropic",LOWER(B44))),"AI Tools",IF(ISNUMBER(SEARCH("claude",LOWER(B44))),"AI Tools",IF(ISNUMBER(SEARCH("appbox",LOWER(B44))),"Digital Services",IF(ISNUMBER(SEARCH("apple",LOWER(B44))),"Digital Services",IF(ISNUMBER(SEARCH("playstation",LOWER(B44))),"Digital Services",IF(ISNUMBER(SEARCH("battle",LOWER(B44))),"Gaming","Other"))))))) -> Other | E44: =IF(C44="","",C44*CONFIG!B5)
A45: =IF(MOV_CC_INTL!A45="","",MOV_CC_INTL!A45) | B45: =IF(MOV_CC_INTL!B45="","",MOV_CC_INTL!B45) | C45: =IF(MOV_CC_INTL!C45="","",MOV_CC_INTL!C45) | D45: =IF(ISNUMBER(SEARCH("openai",LOWER(B45))),"AI Tools",IF(ISNUMBER(SEARCH("anthropic",LOWER(B45))),"AI Tools",IF(ISNUMBER(SEARCH("claude",LOWER(B45))),"AI Tools",IF(ISNUMBER(SEARCH("appbox",LOWER(B45))),"Digital Services",IF(ISNUMBER(SEARCH("apple",LOWER(B45))),"Digital Services",IF(ISNUMBER(SEARCH("playstation",LOWER(B45))),"Digital Services",IF(ISNUMBER(SEARCH("battle",LOWER(B45))),"Gaming","Other"))))))) -> Other | E45: =IF(C45="","",C45*CONFIG!B5)
A46: =IF(MOV_CC_INTL!A46="","",MOV_CC_INTL!A46) | B46: =IF(MOV_CC_INTL!B46="","",MOV_CC_INTL!B46) | C46: =IF(MOV_CC_INTL!C46="","",MOV_CC_INTL!C46) | D46: =IF(ISNUMBER(SEARCH("openai",LOWER(B46))),"AI Tools",IF(ISNUMBER(SEARCH("anthropic",LOWER(B46))),"AI Tools",IF(ISNUMBER(SEARCH("claude",LOWER(B46))),"AI Tools",IF(ISNUMBER(SEARCH("appbox",LOWER(B46))),"Digital Services",IF(ISNUMBER(SEARCH("apple",LOWER(B46))),"Digital Services",IF(ISNUMBER(SEARCH("playstation",LOWER(B46))),"Digital Services",IF(ISNUMBER(SEARCH("battle",LOWER(B46))),"Gaming","Other"))))))) -> Other | E46: =IF(C46="","",C46*CONFIG!B5)
A47: =IF(MOV_CC_INTL!A47="","",MOV_CC_INTL!A47) | B47: =IF(MOV_CC_INTL!B47="","",MOV_CC_INTL!B47) | C47: =IF(MOV_CC_INTL!C47="","",MOV_CC_INTL!C47) | D47: =IF(ISNUMBER(SEARCH("openai",LOWER(B47))),"AI Tools",IF(ISNUMBER(SEARCH("anthropic",LOWER(B47))),"AI Tools",IF(ISNUMBER(SEARCH("claude",LOWER(B47))),"AI Tools",IF(ISNUMBER(SEARCH("appbox",LOWER(B47))),"Digital Services",IF(ISNUMBER(SEARCH("apple",LOWER(B47))),"Digital Services",IF(ISNUMBER(SEARCH("playstation",LOWER(B47))),"Digital Services",IF(ISNUMBER(SEARCH("battle",LOWER(B47))),"Gaming","Other"))))))) -> Other | E47: =IF(C47="","",C47*CONFIG!B5)
A48: =IF(MOV_CC_INTL!A48="","",MOV_CC_INTL!A48) | B48: =IF(MOV_CC_INTL!B48="","",MOV_CC_INTL!B48) | C48: =IF(MOV_CC_INTL!C48="","",MOV_CC_INTL!C48) | D48: =IF(ISNUMBER(SEARCH("openai",LOWER(B48))),"AI Tools",IF(ISNUMBER(SEARCH("anthropic",LOWER(B48))),"AI Tools",IF(ISNUMBER(SEARCH("claude",LOWER(B48))),"AI Tools",IF(ISNUMBER(SEARCH("appbox",LOWER(B48))),"Digital Services",IF(ISNUMBER(SEARCH("apple",LOWER(B48))),"Digital Services",IF(ISNUMBER(SEARCH("playstation",LOWER(B48))),"Digital Services",IF(ISNUMBER(SEARCH("battle",LOWER(B48))),"Gaming","Other"))))))) -> Other | E48: =IF(C48="","",C48*CONFIG!B5)
A49: =IF(MOV_CC_INTL!A49="","",MOV_CC_INTL!A49) | B49: =IF(MOV_CC_INTL!B49="","",MOV_CC_INTL!B49) | C49: =IF(MOV_CC_INTL!C49="","",MOV_CC_INTL!C49) | D49: =IF(ISNUMBER(SEARCH("openai",LOWER(B49))),"AI Tools",IF(ISNUMBER(SEARCH("anthropic",LOWER(B49))),"AI Tools",IF(ISNUMBER(SEARCH("claude",LOWER(B49))),"AI Tools",IF(ISNUMBER(SEARCH("appbox",LOWER(B49))),"Digital Services",IF(ISNUMBER(SEARCH("apple",LOWER(B49))),"Digital Services",IF(ISNUMBER(SEARCH("playstation",LOWER(B49))),"Digital Services",IF(ISNUMBER(SEARCH("battle",LOWER(B49))),"Gaming","Other"))))))) -> Other | E49: =IF(C49="","",C49*CONFIG!B5)
A50: =IF(MOV_CC_INTL!A50="","",MOV_CC_INTL!A50) | B50: =IF(MOV_CC_INTL!B50="","",MOV_CC_INTL!B50) | C50: =IF(MOV_CC_INTL!C50="","",MOV_CC_INTL!C50) | D50: =IF(ISNUMBER(SEARCH("openai",LOWER(B50))),"AI Tools",IF(ISNUMBER(SEARCH("anthropic",LOWER(B50))),"AI Tools",IF(ISNUMBER(SEARCH("claude",LOWER(B50))),"AI Tools",IF(ISNUMBER(SEARCH("appbox",LOWER(B50))),"Digital Services",IF(ISNUMBER(SEARCH("apple",LOWER(B50))),"Digital Services",IF(ISNUMBER(SEARCH("playstation",LOWER(B50))),"Digital Services",IF(ISNUMBER(SEARCH("battle",LOWER(B50))),"Gaming","Other"))))))) -> Other | E50: =IF(C50="","",C50*CONFIG!B5)
A51: =IF(MOV_CC_INTL!A51="","",MOV_CC_INTL!A51) | B51: =IF(MOV_CC_INTL!B51="","",MOV_CC_INTL!B51) | C51: =IF(MOV_CC_INTL!C51="","",MOV_CC_INTL!C51) | D51: =IF(ISNUMBER(SEARCH("openai",LOWER(B51))),"AI Tools",IF(ISNUMBER(SEARCH("anthropic",LOWER(B51))),"AI Tools",IF(ISNUMBER(SEARCH("claude",LOWER(B51))),"AI Tools",IF(ISNUMBER(SEARCH("appbox",LOWER(B51))),"Digital Services",IF(ISNUMBER(SEARCH("apple",LOWER(B51))),"Digital Services",IF(ISNUMBER(SEARCH("playstation",LOWER(B51))),"Digital Services",IF(ISNUMBER(SEARCH("battle",LOWER(B51))),"Gaming","Other"))))))) -> Other | E51: =IF(C51="","",C51*CONFIG!B5)
A52: =IF(MOV_CC_INTL!A52="","",MOV_CC_INTL!A52) | B52: =IF(MOV_CC_INTL!B52="","",MOV_CC_INTL!B52) | C52: =IF(MOV_CC_INTL!C52="","",MOV_CC_INTL!C52) | D52: =IF(ISNUMBER(SEARCH("openai",LOWER(B52))),"AI Tools",IF(ISNUMBER(SEARCH("anthropic",LOWER(B52))),"AI Tools",IF(ISNUMBER(SEARCH("claude",LOWER(B52))),"AI Tools",IF(ISNUMBER(SEARCH("appbox",LOWER(B52))),"Digital Services",IF(ISNUMBER(SEARCH("apple",LOWER(B52))),"Digital Services",IF(ISNUMBER(SEARCH("playstation",LOWER(B52))),"Digital Services",IF(ISNUMBER(SEARCH("battle",LOWER(B52))),"Gaming","Other"))))))) -> Other | E52: =IF(C52="","",C52*CONFIG!B5)
A53: =IF(MOV_CC_INTL!A53="","",MOV_CC_INTL!A53) | B53: =IF(MOV_CC_INTL!B53="","",MOV_CC_INTL!B53) | C53: =IF(MOV_CC_INTL!C53="","",MOV_CC_INTL!C53) | D53: =IF(ISNUMBER(SEARCH("openai",LOWER(B53))),"AI Tools",IF(ISNUMBER(SEARCH("anthropic",LOWER(B53))),"AI Tools",IF(ISNUMBER(SEARCH("claude",LOWER(B53))),"AI Tools",IF(ISNUMBER(SEARCH("appbox",LOWER(B53))),"Digital Services",IF(ISNUMBER(SEARCH("apple",LOWER(B53))),"Digital Services",IF(ISNUMBER(SEARCH("playstation",LOWER(B53))),"Digital Services",IF(ISNUMBER(SEARCH("battle",LOWER(B53))),"Gaming","Other"))))))) -> Other | E53: =IF(C53="","",C53*CONFIG!B5)
A54: =IF(MOV_CC_INTL!A54="","",MOV_CC_INTL!A54) | B54: =IF(MOV_CC_INTL!B54="","",MOV_CC_INTL!B54) | C54: =IF(MOV_CC_INTL!C54="","",MOV_CC_INTL!C54) | D54: =IF(ISNUMBER(SEARCH("openai",LOWER(B54))),"AI Tools",IF(ISNUMBER(SEARCH("anthropic",LOWER(B54))),"AI Tools",IF(ISNUMBER(SEARCH("claude",LOWER(B54))),"AI Tools",IF(ISNUMBER(SEARCH("appbox",LOWER(B54))),"Digital Services",IF(ISNUMBER(SEARCH("apple",LOWER(B54))),"Digital Services",IF(ISNUMBER(SEARCH("playstation",LOWER(B54))),"Digital Services",IF(ISNUMBER(SEARCH("battle",LOWER(B54))),"Gaming","Other"))))))) -> Other | E54: =IF(C54="","",C54*CONFIG!B5)
A55: =IF(MOV_CC_INTL!A55="","",MOV_CC_INTL!A55) | B55: =IF(MOV_CC_INTL!B55="","",MOV_CC_INTL!B55) | C55: =IF(MOV_CC_INTL!C55="","",MOV_CC_INTL!C55) | D55: =IF(ISNUMBER(SEARCH("openai",LOWER(B55))),"AI Tools",IF(ISNUMBER(SEARCH("anthropic",LOWER(B55))),"AI Tools",IF(ISNUMBER(SEARCH("claude",LOWER(B55))),"AI Tools",IF(ISNUMBER(SEARCH("appbox",LOWER(B55))),"Digital Services",IF(ISNUMBER(SEARCH("apple",LOWER(B55))),"Digital Services",IF(ISNUMBER(SEARCH("playstation",LOWER(B55))),"Digital Services",IF(ISNUMBER(SEARCH("battle",LOWER(B55))),"Gaming","Other"))))))) -> Other | E55: =IF(C55="","",C55*CONFIG!B5)
A56: =IF(MOV_CC_INTL!A56="","",MOV_CC_INTL!A56) | B56: =IF(MOV_CC_INTL!B56="","",MOV_CC_INTL!B56) | C56: =IF(MOV_CC_INTL!C56="","",MOV_CC_INTL!C56) | D56: =IF(ISNUMBER(SEARCH("openai",LOWER(B56))),"AI Tools",IF(ISNUMBER(SEARCH("anthropic",LOWER(B56))),"AI Tools",IF(ISNUMBER(SEARCH("claude",LOWER(B56))),"AI Tools",IF(ISNUMBER(SEARCH("appbox",LOWER(B56))),"Digital Services",IF(ISNUMBER(SEARCH("apple",LOWER(B56))),"Digital Services",IF(ISNUMBER(SEARCH("playstation",LOWER(B56))),"Digital Services",IF(ISNUMBER(SEARCH("battle",LOWER(B56))),"Gaming","Other"))))))) -> Other | E56: =IF(C56="","",C56*CONFIG!B5)
A57: =IF(MOV_CC_INTL!A57="","",MOV_CC_INTL!A57) | B57: =IF(MOV_CC_INTL!B57="","",MOV_CC_INTL!B57) | C57: =IF(MOV_CC_INTL!C57="","",MOV_CC_INTL!C57) | D57: =IF(ISNUMBER(SEARCH("openai",LOWER(B57))),"AI Tools",IF(ISNUMBER(SEARCH("anthropic",LOWER(B57))),"AI Tools",IF(ISNUMBER(SEARCH("claude",LOWER(B57))),"AI Tools",IF(ISNUMBER(SEARCH("appbox",LOWER(B57))),"Digital Services",IF(ISNUMBER(SEARCH("apple",LOWER(B57))),"Digital Services",IF(ISNUMBER(SEARCH("playstation",LOWER(B57))),"Digital Services",IF(ISNUMBER(SEARCH("battle",LOWER(B57))),"Gaming","Other"))))))) -> Other | E57: =IF(C57="","",C57*CONFIG!B5)
A58: =IF(MOV_CC_INTL!A58="","",MOV_CC_INTL!A58) | B58: =IF(MOV_CC_INTL!B58="","",MOV_CC_INTL!B58) | C58: =IF(MOV_CC_INTL!C58="","",MOV_CC_INTL!C58) | D58: =IF(ISNUMBER(SEARCH("openai",LOWER(B58))),"AI Tools",IF(ISNUMBER(SEARCH("anthropic",LOWER(B58))),"AI Tools",IF(ISNUMBER(SEARCH("claude",LOWER(B58))),"AI Tools",IF(ISNUMBER(SEARCH("appbox",LOWER(B58))),"Digital Services",IF(ISNUMBER(SEARCH("apple",LOWER(B58))),"Digital Services",IF(ISNUMBER(SEARCH("playstation",LOWER(B58))),"Digital Services",IF(ISNUMBER(SEARCH("battle",LOWER(B58))),"Gaming","Other"))))))) -> Other | E58: =IF(C58="","",C58*CONFIG!B5)
A59: =IF(MOV_CC_INTL!A59="","",MOV_CC_INTL!A59) | B59: =IF(MOV_CC_INTL!B59="","",MOV_CC_INTL!B59) | C59: =IF(MOV_CC_INTL!C59="","",MOV_CC_INTL!C59) | D59: =IF(ISNUMBER(SEARCH("openai",LOWER(B59))),"AI Tools",IF(ISNUMBER(SEARCH("anthropic",LOWER(B59))),"AI Tools",IF(ISNUMBER(SEARCH("claude",LOWER(B59))),"AI Tools",IF(ISNUMBER(SEARCH("appbox",LOWER(B59))),"Digital Services",IF(ISNUMBER(SEARCH("apple",LOWER(B59))),"Digital Services",IF(ISNUMBER(SEARCH("playstation",LOWER(B59))),"Digital Services",IF(ISNUMBER(SEARCH("battle",LOWER(B59))),"Gaming","Other"))))))) -> Other | E59: =IF(C59="","",C59*CONFIG!B5)
A60: =IF(MOV_CC_INTL!A60="","",MOV_CC_INTL!A60) | B60: =IF(MOV_CC_INTL!B60="","",MOV_CC_INTL!B60) | C60: =IF(MOV_CC_INTL!C60="","",MOV_CC_INTL!C60) | D60: =IF(ISNUMBER(SEARCH("openai",LOWER(B60))),"AI Tools",IF(ISNUMBER(SEARCH("anthropic",LOWER(B60))),"AI Tools",IF(ISNUMBER(SEARCH("claude",LOWER(B60))),"AI Tools",IF(ISNUMBER(SEARCH("appbox",LOWER(B60))),"Digital Services",IF(ISNUMBER(SEARCH("apple",LOWER(B60))),"Digital Services",IF(ISNUMBER(SEARCH("playstation",LOWER(B60))),"Digital Services",IF(ISNUMBER(SEARCH("battle",LOWER(B60))),"Gaming","Other"))))))) -> Other | E60: =IF(C60="","",C60*CONFIG!B5)
A61: =IF(MOV_CC_INTL!A61="","",MOV_CC_INTL!A61) | B61: =IF(MOV_CC_INTL!B61="","",MOV_CC_INTL!B61) | C61: =IF(MOV_CC_INTL!C61="","",MOV_CC_INTL!C61) | D61: =IF(ISNUMBER(SEARCH("openai",LOWER(B61))),"AI Tools",IF(ISNUMBER(SEARCH("anthropic",LOWER(B61))),"AI Tools",IF(ISNUMBER(SEARCH("claude",LOWER(B61))),"AI Tools",IF(ISNUMBER(SEARCH("appbox",LOWER(B61))),"Digital Services",IF(ISNUMBER(SEARCH("apple",LOWER(B61))),"Digital Services",IF(ISNUMBER(SEARCH("playstation",LOWER(B61))),"Digital Services",IF(ISNUMBER(SEARCH("battle",LOWER(B61))),"Gaming","Other"))))))) -> Other | E61: =IF(C61="","",C61*CONFIG!B5)
A62: =IF(MOV_CC_INTL!A62="","",MOV_CC_INTL!A62) | B62: =IF(MOV_CC_INTL!B62="","",MOV_CC_INTL!B62) | C62: =IF(MOV_CC_INTL!C62="","",MOV_CC_INTL!C62) | D62: =IF(ISNUMBER(SEARCH("openai",LOWER(B62))),"AI Tools",IF(ISNUMBER(SEARCH("anthropic",LOWER(B62))),"AI Tools",IF(ISNUMBER(SEARCH("claude",LOWER(B62))),"AI Tools",IF(ISNUMBER(SEARCH("appbox",LOWER(B62))),"Digital Services",IF(ISNUMBER(SEARCH("apple",LOWER(B62))),"Digital Services",IF(ISNUMBER(SEARCH("playstation",LOWER(B62))),"Digital Services",IF(ISNUMBER(SEARCH("battle",LOWER(B62))),"Gaming","Other"))))))) -> Other | E62: =IF(C62="","",C62*CONFIG!B5)
A63: =IF(MOV_CC_INTL!A63="","",MOV_CC_INTL!A63) | B63: =IF(MOV_CC_INTL!B63="","",MOV_CC_INTL!B63) | C63: =IF(MOV_CC_INTL!C63="","",MOV_CC_INTL!C63) | D63: =IF(ISNUMBER(SEARCH("openai",LOWER(B63))),"AI Tools",IF(ISNUMBER(SEARCH("anthropic",LOWER(B63))),"AI Tools",IF(ISNUMBER(SEARCH("claude",LOWER(B63))),"AI Tools",IF(ISNUMBER(SEARCH("appbox",LOWER(B63))),"Digital Services",IF(ISNUMBER(SEARCH("apple",LOWER(B63))),"Digital Services",IF(ISNUMBER(SEARCH("playstation",LOWER(B63))),"Digital Services",IF(ISNUMBER(SEARCH("battle",LOWER(B63))),"Gaming","Other"))))))) -> Other | E63: =IF(C63="","",C63*CONFIG!B5)
A64: =IF(MOV_CC_INTL!A64="","",MOV_CC_INTL!A64) | B64: =IF(MOV_CC_INTL!B64="","",MOV_CC_INTL!B64) | C64: =IF(MOV_CC_INTL!C64="","",MOV_CC_INTL!C64) | D64: =IF(ISNUMBER(SEARCH("openai",LOWER(B64))),"AI Tools",IF(ISNUMBER(SEARCH("anthropic",LOWER(B64))),"AI Tools",IF(ISNUMBER(SEARCH("claude",LOWER(B64))),"AI Tools",IF(ISNUMBER(SEARCH("appbox",LOWER(B64))),"Digital Services",IF(ISNUMBER(SEARCH("apple",LOWER(B64))),"Digital Services",IF(ISNUMBER(SEARCH("playstation",LOWER(B64))),"Digital Services",IF(ISNUMBER(SEARCH("battle",LOWER(B64))),"Gaming","Other"))))))) -> Other | E64: =IF(C64="","",C64*CONFIG!B5)
A65: =IF(MOV_CC_INTL!A65="","",MOV_CC_INTL!A65) | B65: =IF(MOV_CC_INTL!B65="","",MOV_CC_INTL!B65) | C65: =IF(MOV_CC_INTL!C65="","",MOV_CC_INTL!C65) | D65: =IF(ISNUMBER(SEARCH("openai",LOWER(B65))),"AI Tools",IF(ISNUMBER(SEARCH("anthropic",LOWER(B65))),"AI Tools",IF(ISNUMBER(SEARCH("claude",LOWER(B65))),"AI Tools",IF(ISNUMBER(SEARCH("appbox",LOWER(B65))),"Digital Services",IF(ISNUMBER(SEARCH("apple",LOWER(B65))),"Digital Services",IF(ISNUMBER(SEARCH("playstation",LOWER(B65))),"Digital Services",IF(ISNUMBER(SEARCH("battle",LOWER(B65))),"Gaming","Other"))))))) -> Other | E65: =IF(C65="","",C65*CONFIG!B5)
A66: =IF(MOV_CC_INTL!A66="","",MOV_CC_INTL!A66) | B66: =IF(MOV_CC_INTL!B66="","",MOV_CC_INTL!B66) | C66: =IF(MOV_CC_INTL!C66="","",MOV_CC_INTL!C66) | D66: =IF(ISNUMBER(SEARCH("openai",LOWER(B66))),"AI Tools",IF(ISNUMBER(SEARCH("anthropic",LOWER(B66))),"AI Tools",IF(ISNUMBER(SEARCH("claude",LOWER(B66))),"AI Tools",IF(ISNUMBER(SEARCH("appbox",LOWER(B66))),"Digital Services",IF(ISNUMBER(SEARCH("apple",LOWER(B66))),"Digital Services",IF(ISNUMBER(SEARCH("playstation",LOWER(B66))),"Digital Services",IF(ISNUMBER(SEARCH("battle",LOWER(B66))),"Gaming","Other"))))))) -> Other | E66: =IF(C66="","",C66*CONFIG!B5)
A67: =IF(MOV_CC_INTL!A67="","",MOV_CC_INTL!A67) | B67: =IF(MOV_CC_INTL!B67="","",MOV_CC_INTL!B67) | C67: =IF(MOV_CC_INTL!C67="","",MOV_CC_INTL!C67) | D67: =IF(ISNUMBER(SEARCH("openai",LOWER(B67))),"AI Tools",IF(ISNUMBER(SEARCH("anthropic",LOWER(B67))),"AI Tools",IF(ISNUMBER(SEARCH("claude",LOWER(B67))),"AI Tools",IF(ISNUMBER(SEARCH("appbox",LOWER(B67))),"Digital Services",IF(ISNUMBER(SEARCH("apple",LOWER(B67))),"Digital Services",IF(ISNUMBER(SEARCH("playstation",LOWER(B67))),"Digital Services",IF(ISNUMBER(SEARCH("battle",LOWER(B67))),"Gaming","Other"))))))) -> Other | E67: =IF(C67="","",C67*CONFIG!B5)
A68: =IF(MOV_CC_INTL!A68="","",MOV_CC_INTL!A68) | B68: =IF(MOV_CC_INTL!B68="","",MOV_CC_INTL!B68) | C68: =IF(MOV_CC_INTL!C68="","",MOV_CC_INTL!C68) | D68: =IF(ISNUMBER(SEARCH("openai",LOWER(B68))),"AI Tools",IF(ISNUMBER(SEARCH("anthropic",LOWER(B68))),"AI Tools",IF(ISNUMBER(SEARCH("claude",LOWER(B68))),"AI Tools",IF(ISNUMBER(SEARCH("appbox",LOWER(B68))),"Digital Services",IF(ISNUMBER(SEARCH("apple",LOWER(B68))),"Digital Services",IF(ISNUMBER(SEARCH("playstation",LOWER(B68))),"Digital Services",IF(ISNUMBER(SEARCH("battle",LOWER(B68))),"Gaming","Other"))))))) -> Other | E68: =IF(C68="","",C68*CONFIG!B5)
A69: =IF(MOV_CC_INTL!A69="","",MOV_CC_INTL!A69) | B69: =IF(MOV_CC_INTL!B69="","",MOV_CC_INTL!B69) | C69: =IF(MOV_CC_INTL!C69="","",MOV_CC_INTL!C69) | D69: =IF(ISNUMBER(SEARCH("openai",LOWER(B69))),"AI Tools",IF(ISNUMBER(SEARCH("anthropic",LOWER(B69))),"AI Tools",IF(ISNUMBER(SEARCH("claude",LOWER(B69))),"AI Tools",IF(ISNUMBER(SEARCH("appbox",LOWER(B69))),"Digital Services",IF(ISNUMBER(SEARCH("apple",LOWER(B69))),"Digital Services",IF(ISNUMBER(SEARCH("playstation",LOWER(B69))),"Digital Services",IF(ISNUMBER(SEARCH("battle",LOWER(B69))),"Gaming","Other"))))))) -> Other | E69: =IF(C69="","",C69*CONFIG!B5)
A70: =IF(MOV_CC_INTL!A70="","",MOV_CC_INTL!A70) | B70: =IF(MOV_CC_INTL!B70="","",MOV_CC_INTL!B70) | C70: =IF(MOV_CC_INTL!C70="","",MOV_CC_INTL!C70) | D70: =IF(ISNUMBER(SEARCH("openai",LOWER(B70))),"AI Tools",IF(ISNUMBER(SEARCH("anthropic",LOWER(B70))),"AI Tools",IF(ISNUMBER(SEARCH("claude",LOWER(B70))),"AI Tools",IF(ISNUMBER(SEARCH("appbox",LOWER(B70))),"Digital Services",IF(ISNUMBER(SEARCH("apple",LOWER(B70))),"Digital Services",IF(ISNUMBER(SEARCH("playstation",LOWER(B70))),"Digital Services",IF(ISNUMBER(SEARCH("battle",LOWER(B70))),"Gaming","Other"))))))) -> Other | E70: =IF(C70="","",C70*CONFIG!B5)
A71: =IF(MOV_CC_INTL!A71="","",MOV_CC_INTL!A71) | B71: =IF(MOV_CC_INTL!B71="","",MOV_CC_INTL!B71) | C71: =IF(MOV_CC_INTL!C71="","",MOV_CC_INTL!C71) | D71: =IF(ISNUMBER(SEARCH("openai",LOWER(B71))),"AI Tools",IF(ISNUMBER(SEARCH("anthropic",LOWER(B71))),"AI Tools",IF(ISNUMBER(SEARCH("claude",LOWER(B71))),"AI Tools",IF(ISNUMBER(SEARCH("appbox",LOWER(B71))),"Digital Services",IF(ISNUMBER(SEARCH("apple",LOWER(B71))),"Digital Services",IF(ISNUMBER(SEARCH("playstation",LOWER(B71))),"Digital Services",IF(ISNUMBER(SEARCH("battle",LOWER(B71))),"Gaming","Other"))))))) -> Other | E71: =IF(C71="","",C71*CONFIG!B5)
A72: =IF(MOV_CC_INTL!A72="","",MOV_CC_INTL!A72) | B72: =IF(MOV_CC_INTL!B72="","",MOV_CC_INTL!B72) | C72: =IF(MOV_CC_INTL!C72="","",MOV_CC_INTL!C72) | D72: =IF(ISNUMBER(SEARCH("openai",LOWER(B72))),"AI Tools",IF(ISNUMBER(SEARCH("anthropic",LOWER(B72))),"AI Tools",IF(ISNUMBER(SEARCH("claude",LOWER(B72))),"AI Tools",IF(ISNUMBER(SEARCH("appbox",LOWER(B72))),"Digital Services",IF(ISNUMBER(SEARCH("apple",LOWER(B72))),"Digital Services",IF(ISNUMBER(SEARCH("playstation",LOWER(B72))),"Digital Services",IF(ISNUMBER(SEARCH("battle",LOWER(B72))),"Gaming","Other"))))))) -> Other | E72: =IF(C72="","",C72*CONFIG!B5)
A73: =IF(MOV_CC_INTL!A73="","",MOV_CC_INTL!A73) | B73: =IF(MOV_CC_INTL!B73="","",MOV_CC_INTL!B73) | C73: =IF(MOV_CC_INTL!C73="","",MOV_CC_INTL!C73) | D73: =IF(ISNUMBER(SEARCH("openai",LOWER(B73))),"AI Tools",IF(ISNUMBER(SEARCH("anthropic",LOWER(B73))),"AI Tools",IF(ISNUMBER(SEARCH("claude",LOWER(B73))),"AI Tools",IF(ISNUMBER(SEARCH("appbox",LOWER(B73))),"Digital Services",IF(ISNUMBER(SEARCH("apple",LOWER(B73))),"Digital Services",IF(ISNUMBER(SEARCH("playstation",LOWER(B73))),"Digital Services",IF(ISNUMBER(SEARCH("battle",LOWER(B73))),"Gaming","Other"))))))) -> Other | E73: =IF(C73="","",C73*CONFIG!B5)
A74: =IF(MOV_CC_INTL!A74="","",MOV_CC_INTL!A74) | B74: =IF(MOV_CC_INTL!B74="","",MOV_CC_INTL!B74) | C74: =IF(MOV_CC_INTL!C74="","",MOV_CC_INTL!C74) | D74: =IF(ISNUMBER(SEARCH("openai",LOWER(B74))),"AI Tools",IF(ISNUMBER(SEARCH("anthropic",LOWER(B74))),"AI Tools",IF(ISNUMBER(SEARCH("claude",LOWER(B74))),"AI Tools",IF(ISNUMBER(SEARCH("appbox",LOWER(B74))),"Digital Services",IF(ISNUMBER(SEARCH("apple",LOWER(B74))),"Digital Services",IF(ISNUMBER(SEARCH("playstation",LOWER(B74))),"Digital Services",IF(ISNUMBER(SEARCH("battle",LOWER(B74))),"Gaming","Other"))))))) -> Other | E74: =IF(C74="","",C74*CONFIG!B5)
A75: =IF(MOV_CC_INTL!A75="","",MOV_CC_INTL!A75) | B75: =IF(MOV_CC_INTL!B75="","",MOV_CC_INTL!B75) | C75: =IF(MOV_CC_INTL!C75="","",MOV_CC_INTL!C75) | D75: =IF(ISNUMBER(SEARCH("openai",LOWER(B75))),"AI Tools",IF(ISNUMBER(SEARCH("anthropic",LOWER(B75))),"AI Tools",IF(ISNUMBER(SEARCH("claude",LOWER(B75))),"AI Tools",IF(ISNUMBER(SEARCH("appbox",LOWER(B75))),"Digital Services",IF(ISNUMBER(SEARCH("apple",LOWER(B75))),"Digital Services",IF(ISNUMBER(SEARCH("playstation",LOWER(B75))),"Digital Services",IF(ISNUMBER(SEARCH("battle",LOWER(B75))),"Gaming","Other"))))))) -> Other | E75: =IF(C75="","",C75*CONFIG!B5)
A76: =IF(MOV_CC_INTL!A76="","",MOV_CC_INTL!A76) | B76: =IF(MOV_CC_INTL!B76="","",MOV_CC_INTL!B76) | C76: =IF(MOV_CC_INTL!C76="","",MOV_CC_INTL!C76) | D76: =IF(ISNUMBER(SEARCH("openai",LOWER(B76))),"AI Tools",IF(ISNUMBER(SEARCH("anthropic",LOWER(B76))),"AI Tools",IF(ISNUMBER(SEARCH("claude",LOWER(B76))),"AI Tools",IF(ISNUMBER(SEARCH("appbox",LOWER(B76))),"Digital Services",IF(ISNUMBER(SEARCH("apple",LOWER(B76))),"Digital Services",IF(ISNUMBER(SEARCH("playstation",LOWER(B76))),"Digital Services",IF(ISNUMBER(SEARCH("battle",LOWER(B76))),"Gaming","Other"))))))) -> Other | E76: =IF(C76="","",C76*CONFIG!B5)
A77: =IF(MOV_CC_INTL!A77="","",MOV_CC_INTL!A77) | B77: =IF(MOV_CC_INTL!B77="","",MOV_CC_INTL!B77) | C77: =IF(MOV_CC_INTL!C77="","",MOV_CC_INTL!C77) | D77: =IF(ISNUMBER(SEARCH("openai",LOWER(B77))),"AI Tools",IF(ISNUMBER(SEARCH("anthropic",LOWER(B77))),"AI Tools",IF(ISNUMBER(SEARCH("claude",LOWER(B77))),"AI Tools",IF(ISNUMBER(SEARCH("appbox",LOWER(B77))),"Digital Services",IF(ISNUMBER(SEARCH("apple",LOWER(B77))),"Digital Services",IF(ISNUMBER(SEARCH("playstation",LOWER(B77))),"Digital Services",IF(ISNUMBER(SEARCH("battle",LOWER(B77))),"Gaming","Other"))))))) -> Other | E77: =IF(C77="","",C77*CONFIG!B5)
A78: =IF(MOV_CC_INTL!A78="","",MOV_CC_INTL!A78) | B78: =IF(MOV_CC_INTL!B78="","",MOV_CC_INTL!B78) | C78: =IF(MOV_CC_INTL!C78="","",MOV_CC_INTL!C78) | D78: =IF(ISNUMBER(SEARCH("openai",LOWER(B78))),"AI Tools",IF(ISNUMBER(SEARCH("anthropic",LOWER(B78))),"AI Tools",IF(ISNUMBER(SEARCH("claude",LOWER(B78))),"AI Tools",IF(ISNUMBER(SEARCH("appbox",LOWER(B78))),"Digital Services",IF(ISNUMBER(SEARCH("apple",LOWER(B78))),"Digital Services",IF(ISNUMBER(SEARCH("playstation",LOWER(B78))),"Digital Services",IF(ISNUMBER(SEARCH("battle",LOWER(B78))),"Gaming","Other"))))))) -> Other | E78: =IF(C78="","",C78*CONFIG!B5)
A79: =IF(MOV_CC_INTL!A79="","",MOV_CC_INTL!A79) | B79: =IF(MOV_CC_INTL!B79="","",MOV_CC_INTL!B79) | C79: =IF(MOV_CC_INTL!C79="","",MOV_CC_INTL!C79) | D79: =IF(ISNUMBER(SEARCH("openai",LOWER(B79))),"AI Tools",IF(ISNUMBER(SEARCH("anthropic",LOWER(B79))),"AI Tools",IF(ISNUMBER(SEARCH("claude",LOWER(B79))),"AI Tools",IF(ISNUMBER(SEARCH("appbox",LOWER(B79))),"Digital Services",IF(ISNUMBER(SEARCH("apple",LOWER(B79))),"Digital Services",IF(ISNUMBER(SEARCH("playstation",LOWER(B79))),"Digital Services",IF(ISNUMBER(SEARCH("battle",LOWER(B79))),"Gaming","Other"))))))) -> Other | E79: =IF(C79="","",C79*CONFIG!B5)
A80: =IF(MOV_CC_INTL!A80="","",MOV_CC_INTL!A80) | B80: =IF(MOV_CC_INTL!B80="","",MOV_CC_INTL!B80) | C80: =IF(MOV_CC_INTL!C80="","",MOV_CC_INTL!C80) | D80: =IF(ISNUMBER(SEARCH("openai",LOWER(B80))),"AI Tools",IF(ISNUMBER(SEARCH("anthropic",LOWER(B80))),"AI Tools",IF(ISNUMBER(SEARCH("claude",LOWER(B80))),"AI Tools",IF(ISNUMBER(SEARCH("appbox",LOWER(B80))),"Digital Services",IF(ISNUMBER(SEARCH("apple",LOWER(B80))),"Digital Services",IF(ISNUMBER(SEARCH("playstation",LOWER(B80))),"Digital Services",IF(ISNUMBER(SEARCH("battle",LOWER(B80))),"Gaming","Other"))))))) -> Other | E80: =IF(C80="","",C80*CONFIG!B5)
A81: =IF(MOV_CC_INTL!A81="","",MOV_CC_INTL!A81) | B81: =IF(MOV_CC_INTL!B81="","",MOV_CC_INTL!B81) | C81: =IF(MOV_CC_INTL!C81="","",MOV_CC_INTL!C81) | D81: =IF(ISNUMBER(SEARCH("openai",LOWER(B81))),"AI Tools",IF(ISNUMBER(SEARCH("anthropic",LOWER(B81))),"AI Tools",IF(ISNUMBER(SEARCH("claude",LOWER(B81))),"AI Tools",IF(ISNUMBER(SEARCH("appbox",LOWER(B81))),"Digital Services",IF(ISNUMBER(SEARCH("apple",LOWER(B81))),"Digital Services",IF(ISNUMBER(SEARCH("playstation",LOWER(B81))),"Digital Services",IF(ISNUMBER(SEARCH("battle",LOWER(B81))),"Gaming","Other"))))))) -> Other | E81: =IF(C81="","",C81*CONFIG!B5)
A82: =IF(MOV_CC_INTL!A82="","",MOV_CC_INTL!A82) | B82: =IF(MOV_CC_INTL!B82="","",MOV_CC_INTL!B82) | C82: =IF(MOV_CC_INTL!C82="","",MOV_CC_INTL!C82) | D82: =IF(ISNUMBER(SEARCH("openai",LOWER(B82))),"AI Tools",IF(ISNUMBER(SEARCH("anthropic",LOWER(B82))),"AI Tools",IF(ISNUMBER(SEARCH("claude",LOWER(B82))),"AI Tools",IF(ISNUMBER(SEARCH("appbox",LOWER(B82))),"Digital Services",IF(ISNUMBER(SEARCH("apple",LOWER(B82))),"Digital Services",IF(ISNUMBER(SEARCH("playstation",LOWER(B82))),"Digital Services",IF(ISNUMBER(SEARCH("battle",LOWER(B82))),"Gaming","Other"))))))) -> Other | E82: =IF(C82="","",C82*CONFIG!B5)
A83: =IF(MOV_CC_INTL!A83="","",MOV_CC_INTL!A83) | B83: =IF(MOV_CC_INTL!B83="","",MOV_CC_INTL!B83) | C83: =IF(MOV_CC_INTL!C83="","",MOV_CC_INTL!C83) | D83: =IF(ISNUMBER(SEARCH("openai",LOWER(B83))),"AI Tools",IF(ISNUMBER(SEARCH("anthropic",LOWER(B83))),"AI Tools",IF(ISNUMBER(SEARCH("claude",LOWER(B83))),"AI Tools",IF(ISNUMBER(SEARCH("appbox",LOWER(B83))),"Digital Services",IF(ISNUMBER(SEARCH("apple",LOWER(B83))),"Digital Services",IF(ISNUMBER(SEARCH("playstation",LOWER(B83))),"Digital Services",IF(ISNUMBER(SEARCH("battle",LOWER(B83))),"Gaming","Other"))))))) -> Other | E83: =IF(C83="","",C83*CONFIG!B5)
A84: =IF(MOV_CC_INTL!A84="","",MOV_CC_INTL!A84) | B84: =IF(MOV_CC_INTL!B84="","",MOV_CC_INTL!B84) | C84: =IF(MOV_CC_INTL!C84="","",MOV_CC_INTL!C84) | D84: =IF(ISNUMBER(SEARCH("openai",LOWER(B84))),"AI Tools",IF(ISNUMBER(SEARCH("anthropic",LOWER(B84))),"AI Tools",IF(ISNUMBER(SEARCH("claude",LOWER(B84))),"AI Tools",IF(ISNUMBER(SEARCH("appbox",LOWER(B84))),"Digital Services",IF(ISNUMBER(SEARCH("apple",LOWER(B84))),"Digital Services",IF(ISNUMBER(SEARCH("playstation",LOWER(B84))),"Digital Services",IF(ISNUMBER(SEARCH("battle",LOWER(B84))),"Gaming","Other"))))))) -> Other | E84: =IF(C84="","",C84*CONFIG!B5)
A85: =IF(MOV_CC_INTL!A85="","",MOV_CC_INTL!A85) | B85: =IF(MOV_CC_INTL!B85="","",MOV_CC_INTL!B85) | C85: =IF(MOV_CC_INTL!C85="","",MOV_CC_INTL!C85) | D85: =IF(ISNUMBER(SEARCH("openai",LOWER(B85))),"AI Tools",IF(ISNUMBER(SEARCH("anthropic",LOWER(B85))),"AI Tools",IF(ISNUMBER(SEARCH("claude",LOWER(B85))),"AI Tools",IF(ISNUMBER(SEARCH("appbox",LOWER(B85))),"Digital Services",IF(ISNUMBER(SEARCH("apple",LOWER(B85))),"Digital Services",IF(ISNUMBER(SEARCH("playstation",LOWER(B85))),"Digital Services",IF(ISNUMBER(SEARCH("battle",LOWER(B85))),"Gaming","Other"))))))) -> Other | E85: =IF(C85="","",C85*CONFIG!B5)
A86: =IF(MOV_CC_INTL!A86="","",MOV_CC_INTL!A86) | B86: =IF(MOV_CC_INTL!B86="","",MOV_CC_INTL!B86) | C86: =IF(MOV_CC_INTL!C86="","",MOV_CC_INTL!C86) | D86: =IF(ISNUMBER(SEARCH("openai",LOWER(B86))),"AI Tools",IF(ISNUMBER(SEARCH("anthropic",LOWER(B86))),"AI Tools",IF(ISNUMBER(SEARCH("claude",LOWER(B86))),"AI Tools",IF(ISNUMBER(SEARCH("appbox",LOWER(B86))),"Digital Services",IF(ISNUMBER(SEARCH("apple",LOWER(B86))),"Digital Services",IF(ISNUMBER(SEARCH("playstation",LOWER(B86))),"Digital Services",IF(ISNUMBER(SEARCH("battle",LOWER(B86))),"Gaming","Other"))))))) -> Other | E86: =IF(C86="","",C86*CONFIG!B5)
A87: =IF(MOV_CC_INTL!A87="","",MOV_CC_INTL!A87) | B87: =IF(MOV_CC_INTL!B87="","",MOV_CC_INTL!B87) | C87: =IF(MOV_CC_INTL!C87="","",MOV_CC_INTL!C87) | D87: =IF(ISNUMBER(SEARCH("openai",LOWER(B87))),"AI Tools",IF(ISNUMBER(SEARCH("anthropic",LOWER(B87))),"AI Tools",IF(ISNUMBER(SEARCH("claude",LOWER(B87))),"AI Tools",IF(ISNUMBER(SEARCH("appbox",LOWER(B87))),"Digital Services",IF(ISNUMBER(SEARCH("apple",LOWER(B87))),"Digital Services",IF(ISNUMBER(SEARCH("playstation",LOWER(B87))),"Digital Services",IF(ISNUMBER(SEARCH("battle",LOWER(B87))),"Gaming","Other"))))))) -> Other | E87: =IF(C87="","",C87*CONFIG!B5)
A88: =IF(MOV_CC_INTL!A88="","",MOV_CC_INTL!A88) | B88: =IF(MOV_CC_INTL!B88="","",MOV_CC_INTL!B88) | C88: =IF(MOV_CC_INTL!C88="","",MOV_CC_INTL!C88) | D88: =IF(ISNUMBER(SEARCH("openai",LOWER(B88))),"AI Tools",IF(ISNUMBER(SEARCH("anthropic",LOWER(B88))),"AI Tools",IF(ISNUMBER(SEARCH("claude",LOWER(B88))),"AI Tools",IF(ISNUMBER(SEARCH("appbox",LOWER(B88))),"Digital Services",IF(ISNUMBER(SEARCH("apple",LOWER(B88))),"Digital Services",IF(ISNUMBER(SEARCH("playstation",LOWER(B88))),"Digital Services",IF(ISNUMBER(SEARCH("battle",LOWER(B88))),"Gaming","Other"))))))) -> Other | E88: =IF(C88="","",C88*CONFIG!B5)
A89: =IF(MOV_CC_INTL!A89="","",MOV_CC_INTL!A89) | B89: =IF(MOV_CC_INTL!B89="","",MOV_CC_INTL!B89) | C89: =IF(MOV_CC_INTL!C89="","",MOV_CC_INTL!C89) | D89: =IF(ISNUMBER(SEARCH("openai",LOWER(B89))),"AI Tools",IF(ISNUMBER(SEARCH("anthropic",LOWER(B89))),"AI Tools",IF(ISNUMBER(SEARCH("claude",LOWER(B89))),"AI Tools",IF(ISNUMBER(SEARCH("appbox",LOWER(B89))),"Digital Services",IF(ISNUMBER(SEARCH("apple",LOWER(B89))),"Digital Services",IF(ISNUMBER(SEARCH("playstation",LOWER(B89))),"Digital Services",IF(ISNUMBER(SEARCH("battle",LOWER(B89))),"Gaming","Other"))))))) -> Other | E89: =IF(C89="","",C89*CONFIG!B5)
A90: =IF(MOV_CC_INTL!A90="","",MOV_CC_INTL!A90) | B90: =IF(MOV_CC_INTL!B90="","",MOV_CC_INTL!B90) | C90: =IF(MOV_CC_INTL!C90="","",MOV_CC_INTL!C90) | D90: =IF(ISNUMBER(SEARCH("openai",LOWER(B90))),"AI Tools",IF(ISNUMBER(SEARCH("anthropic",LOWER(B90))),"AI Tools",IF(ISNUMBER(SEARCH("claude",LOWER(B90))),"AI Tools",IF(ISNUMBER(SEARCH("appbox",LOWER(B90))),"Digital Services",IF(ISNUMBER(SEARCH("apple",LOWER(B90))),"Digital Services",IF(ISNUMBER(SEARCH("playstation",LOWER(B90))),"Digital Services",IF(ISNUMBER(SEARCH("battle",LOWER(B90))),"Gaming","Other"))))))) -> Other | E90: =IF(C90="","",C90*CONFIG!B5)
A91: =IF(MOV_CC_INTL!A91="","",MOV_CC_INTL!A91) | B91: =IF(MOV_CC_INTL!B91="","",MOV_CC_INTL!B91) | C91: =IF(MOV_CC_INTL!C91="","",MOV_CC_INTL!C91) | D91: =IF(ISNUMBER(SEARCH("openai",LOWER(B91))),"AI Tools",IF(ISNUMBER(SEARCH("anthropic",LOWER(B91))),"AI Tools",IF(ISNUMBER(SEARCH("claude",LOWER(B91))),"AI Tools",IF(ISNUMBER(SEARCH("appbox",LOWER(B91))),"Digital Services",IF(ISNUMBER(SEARCH("apple",LOWER(B91))),"Digital Services",IF(ISNUMBER(SEARCH("playstation",LOWER(B91))),"Digital Services",IF(ISNUMBER(SEARCH("battle",LOWER(B91))),"Gaming","Other"))))))) -> Other | E91: =IF(C91="","",C91*CONFIG!B5)
A92: =IF(MOV_CC_INTL!A92="","",MOV_CC_INTL!A92) | B92: =IF(MOV_CC_INTL!B92="","",MOV_CC_INTL!B92) | C92: =IF(MOV_CC_INTL!C92="","",MOV_CC_INTL!C92) | D92: =IF(ISNUMBER(SEARCH("openai",LOWER(B92))),"AI Tools",IF(ISNUMBER(SEARCH("anthropic",LOWER(B92))),"AI Tools",IF(ISNUMBER(SEARCH("claude",LOWER(B92))),"AI Tools",IF(ISNUMBER(SEARCH("appbox",LOWER(B92))),"Digital Services",IF(ISNUMBER(SEARCH("apple",LOWER(B92))),"Digital Services",IF(ISNUMBER(SEARCH("playstation",LOWER(B92))),"Digital Services",IF(ISNUMBER(SEARCH("battle",LOWER(B92))),"Gaming","Other"))))))) -> Other | E92: =IF(C92="","",C92*CONFIG!B5)
A93: =IF(MOV_CC_INTL!A93="","",MOV_CC_INTL!A93) | B93: =IF(MOV_CC_INTL!B93="","",MOV_CC_INTL!B93) | C93: =IF(MOV_CC_INTL!C93="","",MOV_CC_INTL!C93) | D93: =IF(ISNUMBER(SEARCH("openai",LOWER(B93))),"AI Tools",IF(ISNUMBER(SEARCH("anthropic",LOWER(B93))),"AI Tools",IF(ISNUMBER(SEARCH("claude",LOWER(B93))),"AI Tools",IF(ISNUMBER(SEARCH("appbox",LOWER(B93))),"Digital Services",IF(ISNUMBER(SEARCH("apple",LOWER(B93))),"Digital Services",IF(ISNUMBER(SEARCH("playstation",LOWER(B93))),"Digital Services",IF(ISNUMBER(SEARCH("battle",LOWER(B93))),"Gaming","Other"))))))) -> Other | E93: =IF(C93="","",C93*CONFIG!B5)
A94: =IF(MOV_CC_INTL!A94="","",MOV_CC_INTL!A94) | B94: =IF(MOV_CC_INTL!B94="","",MOV_CC_INTL!B94) | C94: =IF(MOV_CC_INTL!C94="","",MOV_CC_INTL!C94) | D94: =IF(ISNUMBER(SEARCH("openai",LOWER(B94))),"AI Tools",IF(ISNUMBER(SEARCH("anthropic",LOWER(B94))),"AI Tools",IF(ISNUMBER(SEARCH("claude",LOWER(B94))),"AI Tools",IF(ISNUMBER(SEARCH("appbox",LOWER(B94))),"Digital Services",IF(ISNUMBER(SEARCH("apple",LOWER(B94))),"Digital Services",IF(ISNUMBER(SEARCH("playstation",LOWER(B94))),"Digital Services",IF(ISNUMBER(SEARCH("battle",LOWER(B94))),"Gaming","Other"))))))) -> Other | E94: =IF(C94="","",C94*CONFIG!B5)
A95: =IF(MOV_CC_INTL!A95="","",MOV_CC_INTL!A95) | B95: =IF(MOV_CC_INTL!B95="","",MOV_CC_INTL!B95) | C95: =IF(MOV_CC_INTL!C95="","",MOV_CC_INTL!C95) | D95: =IF(ISNUMBER(SEARCH("openai",LOWER(B95))),"AI Tools",IF(ISNUMBER(SEARCH("anthropic",LOWER(B95))),"AI Tools",IF(ISNUMBER(SEARCH("claude",LOWER(B95))),"AI Tools",IF(ISNUMBER(SEARCH("appbox",LOWER(B95))),"Digital Services",IF(ISNUMBER(SEARCH("apple",LOWER(B95))),"Digital Services",IF(ISNUMBER(SEARCH("playstation",LOWER(B95))),"Digital Services",IF(ISNUMBER(SEARCH("battle",LOWER(B95))),"Gaming","Other"))))))) -> Other | E95: =IF(C95="","",C95*CONFIG!B5)
A96: =IF(MOV_CC_INTL!A96="","",MOV_CC_INTL!A96) | B96: =IF(MOV_CC_INTL!B96="","",MOV_CC_INTL!B96) | C96: =IF(MOV_CC_INTL!C96="","",MOV_CC_INTL!C96) | D96: =IF(ISNUMBER(SEARCH("openai",LOWER(B96))),"AI Tools",IF(ISNUMBER(SEARCH("anthropic",LOWER(B96))),"AI Tools",IF(ISNUMBER(SEARCH("claude",LOWER(B96))),"AI Tools",IF(ISNUMBER(SEARCH("appbox",LOWER(B96))),"Digital Services",IF(ISNUMBER(SEARCH("apple",LOWER(B96))),"Digital Services",IF(ISNUMBER(SEARCH("playstation",LOWER(B96))),"Digital Services",IF(ISNUMBER(SEARCH("battle",LOWER(B96))),"Gaming","Other"))))))) -> Other | E96: =IF(C96="","",C96*CONFIG!B5)
A97: =IF(MOV_CC_INTL!A97="","",MOV_CC_INTL!A97) | B97: =IF(MOV_CC_INTL!B97="","",MOV_CC_INTL!B97) | C97: =IF(MOV_CC_INTL!C97="","",MOV_CC_INTL!C97) | D97: =IF(ISNUMBER(SEARCH("openai",LOWER(B97))),"AI Tools",IF(ISNUMBER(SEARCH("anthropic",LOWER(B97))),"AI Tools",IF(ISNUMBER(SEARCH("claude",LOWER(B97))),"AI Tools",IF(ISNUMBER(SEARCH("appbox",LOWER(B97))),"Digital Services",IF(ISNUMBER(SEARCH("apple",LOWER(B97))),"Digital Services",IF(ISNUMBER(SEARCH("playstation",LOWER(B97))),"Digital Services",IF(ISNUMBER(SEARCH("battle",LOWER(B97))),"Gaming","Other"))))))) -> Other | E97: =IF(C97="","",C97*CONFIG!B5)
A98: =IF(MOV_CC_INTL!A98="","",MOV_CC_INTL!A98) | B98: =IF(MOV_CC_INTL!B98="","",MOV_CC_INTL!B98) | C98: =IF(MOV_CC_INTL!C98="","",MOV_CC_INTL!C98) | D98: =IF(ISNUMBER(SEARCH("openai",LOWER(B98))),"AI Tools",IF(ISNUMBER(SEARCH("anthropic",LOWER(B98))),"AI Tools",IF(ISNUMBER(SEARCH("claude",LOWER(B98))),"AI Tools",IF(ISNUMBER(SEARCH("appbox",LOWER(B98))),"Digital Services",IF(ISNUMBER(SEARCH("apple",LOWER(B98))),"Digital Services",IF(ISNUMBER(SEARCH("playstation",LOWER(B98))),"Digital Services",IF(ISNUMBER(SEARCH("battle",LOWER(B98))),"Gaming","Other"))))))) -> Other | E98: =IF(C98="","",C98*CONFIG!B5)
A99: =IF(MOV_CC_INTL!A99="","",MOV_CC_INTL!A99) | B99: =IF(MOV_CC_INTL!B99="","",MOV_CC_INTL!B99) | C99: =IF(MOV_CC_INTL!C99="","",MOV_CC_INTL!C99) | D99: =IF(ISNUMBER(SEARCH("openai",LOWER(B99))),"AI Tools",IF(ISNUMBER(SEARCH("anthropic",LOWER(B99))),"AI Tools",IF(ISNUMBER(SEARCH("claude",LOWER(B99))),"AI Tools",IF(ISNUMBER(SEARCH("appbox",LOWER(B99))),"Digital Services",IF(ISNUMBER(SEARCH("apple",LOWER(B99))),"Digital Services",IF(ISNUMBER(SEARCH("playstation",LOWER(B99))),"Digital Services",IF(ISNUMBER(SEARCH("battle",LOWER(B99))),"Gaming","Other"))))))) -> Other | E99: =IF(C99="","",C99*CONFIG!B5)
A100: =IF(MOV_CC_INTL!A100="","",MOV_CC_INTL!A100) | B100: =IF(MOV_CC_INTL!B100="","",MOV_CC_INTL!B100) | C100: =IF(MOV_CC_INTL!C100="","",MOV_CC_INTL!C100) | D100: =IF(ISNUMBER(SEARCH("openai",LOWER(B100))),"AI Tools",IF(ISNUMBER(SEARCH("anthropic",LOWER(B100))),"AI Tools",IF(ISNUMBER(SEARCH("claude",LOWER(B100))),"AI Tools",IF(ISNUMBER(SEARCH("appbox",LOWER(B100))),"Digital Services",IF(ISNUMBER(SEARCH("apple",LOWER(B100))),"Digital Services",IF(ISNUMBER(SEARCH("playstation",LOWER(B100))),"Digital Services",IF(ISNUMBER(SEARCH("battle",LOWER(B100))),"Gaming","Other"))))))) -> Other | E100: =IF(C100="","",C100*CONFIG!B5)
...

Sheet RESUMEN_CATEGORIAS
A1: Resumen por categoría (Nacional) | E1: Resumen por categoría (Internacional, CLP est.)
A2: Categoria | B2: Total_CLP | C2: % del nacional | E2: Categoria | F2: Total_CLP | G2: % del intl
A3: Food & Transport | B3: =SUMIF(MOV_NAC_AUTO!D:D,"Food & Transport",MOV_NAC_AUTO!C:C) -> 31609 | C3: =IFERROR(B3/SUM(B3:B8),0) -> 0.075167533 | E3: AI Tools | F3: =SUMIF(MOV_INTL_AUTO!D:D,"AI Tools",MOV_INTL_AUTO!E:E) -> 97622 | G3: =IFERROR(F3/SUM(F3:F6),0) -> 0.85469517
A4: Pets & Health | B4: =SUMIF(MOV_NAC_AUTO!D:D,"Pets & Health",MOV_NAC_AUTO!C:C) -> 0 | C4: =IFERROR(B4/SUM(B3:B8),0) -> 0 | E4: Digital Services | F4: =SUMIF(MOV_INTL_AUTO!D:D,"Digital Services",MOV_INTL_AUTO!E:E) -> 11856 | G4: =IFERROR(F4/SUM(F3:F6),0) -> 0.10380105
A5: Pharmacy | B5: =SUMIF(MOV_NAC_AUTO!D:D,"Pharmacy",MOV_NAC_AUTO!C:C) -> 0 | C5: =IFERROR(B5/SUM(B3:B8),0) -> 0 | E5: Gaming | F5: =SUMIF(MOV_INTL_AUTO!D:D,"Gaming",MOV_INTL_AUTO!E:E) -> 0 | G5: =IFERROR(F5/SUM(F3:F6),0) -> 0
A6: Shopping | B6: =SUMIF(MOV_NAC_AUTO!D:D,"Shopping",MOV_NAC_AUTO!C:C) -> 211321 | C6: =IFERROR(B6/SUM(B3:B8),0) -> 0.50253024 | E6: Other | F6: =SUMIF(MOV_INTL_AUTO!D:D,"Other",MOV_INTL_AUTO!E:E) -> 4740.5 | G6: =IFERROR(F6/SUM(F3:F6),0) -> 0.041503784
A7: Subscriptions | B7: =SUMIF(MOV_NAC_AUTO!D:D,"Subscriptions",MOV_NAC_AUTO!C:C) -> 0 | C7: =IFERROR(B7/SUM(B3:B8),0) -> 0
A8: Other | B8: =SUMIF(MOV_NAC_AUTO!D:D,"Other",MOV_NAC_AUTO!C:C) -> 177584 | C8: =IFERROR(B8/SUM(B3:B8),0) -> 0.42230223

Sheet CHART_DATA
A1: Categoria | B1: Nacional_CLP | C1: Internacional_CLP_est
A2: Food & Transport | B2: =RESUMEN_CATEGORIAS!B3 -> 31609 | C2: 0
A3: Pets & Health | B3: =RESUMEN_CATEGORIAS!B4 -> 0 | C3: 0
A4: Pharmacy | B4: =RESUMEN_CATEGORIAS!B5 -> 0 | C4: 0
A5: Shopping | B5: =RESUMEN_CATEGORIAS!B6 -> 211321 | C5: 0
A6: Subscriptions | B6: =RESUMEN_CATEGORIAS!B7 -> 0 | C6: 0
A7: Other | B7: =RESUMEN_CATEGORIAS!B8 -> 177584 | C7: 0
A9: —
A10: AI Tools | B10: 0 | C10: =RESUMEN_CATEGORIAS!F3 -> 97622
A11: Digital Services | B11: 0 | C11: =RESUMEN_CATEGORIAS!F4 -> 11856
A12: Gaming | B12: 0 | C12: =RESUMEN_CATEGORIAS!F5 -> 0
A13: Other | B13: 0 | C13: =RESUMEN_CATEGORIAS!F6 -> 4740.5
